Workbook
Name projectRemainDaysTitle: #REF!
Name projectRemainWorkTitle: #REF!
Name projectRemainWorkVal: #REF!
Name projectNameTitle: #REF!
Name projectWorkVal: #REF!
Name projectStartTitle: #REF!
Name projectManagerTitle: #REF!
Name task: #REF!
Name projectDurationTitle: #REF!
Name projectRemainDaysVal: #REF!
Name projectRemainWeeksTitle: #REF!
Name projectDurationVal: #REF!
Name projectWorkTitle: #REF!
Name projectProgressVal: #REF!
Name projectFinishVal: #REF!
Name projectStartVal: #REF!
Name projectCostTitle: #REF!
Name projectCostVal: #REF!
Name MODULO2: PRESUPUESTO!$A$43:$G$102
Name projectProgressTitle: #REF!
Name projectSummaryTitle: #REF!
Name MODULO1: PRESUPUESTO!$A$10:$G$42
Name gantt: #REF!
Name MODULO3: PRESUPUESTO!$A$103:$F$128
Name projectNameVal: #REF!
Name projectRemainWeeksVal: #REF!
Name projectFinishTitle: #REF!
Name projectManagerVal: #REF!

Sheet TRANSGOOGLE
A1: translate (contact in English please) | B1: traducir (contactar en inglés, por favor)

Sheet GENERADORES
A1: GENERADORES DE VOLUMEN · MEMORIA DE CUANTIFICACIÓN
A2: PROYECTO | C2: =CARATULA!$C$10
A3: CLIENTE | C3: =CARATULA!$C$12
A4: UBICACIÓN | C4: =CARATULA!$C$14
A5: EMPRESA | C5: =CARATULA!$C$19
A6: FOLIO | B6: ='NORMA BIM'!$H$16
A7: Es a la cantidad lo que la tarjeta de precios unitarios es al precio: aquí nace el número, no se escribe a mano.
A9: CLAVE DEL CONCEPTO | B9: MÓDULO | C9: ELEMENTO / UBICACIÓN | D9: EJE O TRAMO | E9: LARGO | F9: ANCHO | G9: ALTO / ESP. | H9: No. | I9: VOLUMEN | J9: UNIDAD | K9: FUENTE / SUPUESTO | L9: DESCRIPCIÓN DEL CONCEPTO | M9: CANTIDAD EN PRESUPUESTO | N9: DIFERENCIA
A10: DEM5029 | B10: {=IF($A10="","",IFERROR(INDEX(PRESUPUESTO!$N$10:$N$262,MATCH($A10,PRESUPUESTO!$A$10:$A$262,0)),""))} | C10: Muro interior central longitudinal | D10: — | E10: 3.85 | F10: 0.35 | G10: 3.4 | H10: 1 | I10: =E10*F10*G10*H10 | J10: {=IF($A10="","",IFERROR(INDEX(PRESUPUESTO!$D$10:$D$174,MATCH($A10&"|"&$B10,PRESUPUESTO!$O$10:$O$174,0)),"⚠"))} | K10: {=IF($A10="","",IFERROR(INDEX(PRESUPUESTO!$C$10:$C$174,MATCH($A10&"|"&$B10,PRESUPUESTO!$O$10:$O$174,0)),""))} | L10: {=IF($A10="","",IFERROR(INDEX(PRESUPUESTO!$B$10:$B$174,MATCH($A10,PRESUPUESTO!$A$10:$A$174,0)),"⚠ clave no existe"))} | M10: {=IF($A10="","",IFERROR(INDEX(PRESUPUESTO!$C$10:$C$262,MATCH($A10,PRESUPUESTO!$A$10:$A$262,0)),""))} | N10: =IF($A10="","",IFERROR(SUMIF($A$10:$A$509,$A10,$I$10:$I$509)-$M10,""))
A11: DEM5029 | B11: {=IF($A11="","",IFERROR(INDEX(PRESUPUESTO!$N$10:$N$262,MATCH($A11,PRESUPUESTO!$A$10:$A$262,0)),""))} | C11: Muro interior transversal 1 | D11: — | E11: 7.53 | F11: 0.2 | G11: 3.4 | H11: 1 | I11: =E11*F11*G11*H11 | J11: {=IF($A11="","",IFERROR(INDEX(PRESUPUESTO!$D$10:$D$174,MATCH($A11&"|"&$B11,PRESUPUESTO!$O$10:$O$174,0)),"⚠"))} | K11: {=IF($A11="","",IFERROR(INDEX(PRESUPUESTO!$C$10:$C$174,MATCH($A11&"|"&$B11,PRESUPUESTO!$O$10:$O$174,0)),""))} | L11: {=IF($A11="","",IFERROR(INDEX(PRESUPUESTO!$B$10:$B$174,MATCH($A11,PRESUPUESTO!$A$10:$A$174,0)),"⚠ clave no existe"))} | M11: {=IF($A11="","",IFERROR(INDEX(PRESUPUESTO!$C$10:$C$262,MATCH($A11,PRESUPUESTO!$A$10:$A$262,0)),""))} | N11: =IF($A11="","",IFERROR(SUMIF($A$10:$A$509,$A11,$I$10:$I$509)-$M11,""))
A12: DEM5029 | B12: {=IF($A12="","",IFERROR(INDEX(PRESUPUESTO!$N$10:$N$262,MATCH($A12,PRESUPUESTO!$A$10:$A$262,0)),""))} | C12: Muro interior transversal 2 | D12: — | E12: 7.53 | F12: 0.23 | G12: 3.4 | H12: 1 | I12: =E12*F12*G12*H12 | J12: {=IF($A12="","",IFERROR(INDEX(PRESUPUESTO!$D$10:$D$174,MATCH($A12&"|"&$B12,PRESUPUESTO!$O$10:$O$174,0)),"⚠"))} | K12: {=IF($A12="","",IFERROR(INDEX(PRESUPUESTO!$C$10:$C$174,MATCH($A12&"|"&$B12,PRESUPUESTO!$O$10:$O$174,0)),""))} | L12: {=IF($A12="","",IFERROR(INDEX(PRESUPUESTO!$B$10:$B$174,MATCH($A12,PRESUPUESTO!$A$10:$A$174,0)),"⚠ clave no existe"))} | M12: {=IF($A12="","",IFERROR(INDEX(PRESUPUESTO!$C$10:$C$262,MATCH($A12,PRESUPUESTO!$A$10:$A$262,0)),""))} | N12: =IF($A12="","",IFERROR(SUMIF($A$10:$A$509,$A12,$I$10:$I$509)-$M12,""))
A13: DEM5029 | B13: {=IF($A13="","",IFERROR(INDEX(PRESUPUESTO!$N$10:$N$262,MATCH($A13,PRESUPUESTO!$A$10:$A$262,0)),""))} | C13: Muro interior transversal 3 | D13: — | E13: 7.53 | F13: 0.2 | G13: 3.4 | H13: 1 | I13: =E13*F13*G13*H13 | J13: {=IF($A13="","",IFERROR(INDEX(PRESUPUESTO!$D$10:$D$174,MATCH($A13&"|"&$B13,PRESUPUESTO!$O$10:$O$174,0)),"⚠"))} | K13: {=IF($A13="","",IFERROR(INDEX(PRESUPUESTO!$C$10:$C$174,MATCH($A13&"|"&$B13,PRESUPUESTO!$O$10:$O$174,0)),""))} | L13: {=IF($A13="","",IFERROR(INDEX(PRESUPUESTO!$B$10:$B$174,MATCH($A13,PRESUPUESTO!$A$10:$A$174,0)),"⚠ clave no existe"))} | M13: {=IF($A13="","",IFERROR(INDEX(PRESUPUESTO!$C$10:$C$262,MATCH($A13,PRESUPUESTO!$A$10:$A$262,0)),""))} | N13: =IF($A13="","",IFERROR(SUMIF($A$10:$A$509,$A13,$I$10:$I$509)-$M13,""))
A14: DEM5029 | B14: {=IF($A14="","",IFERROR(INDEX(PRESUPUESTO!$N$10:$N$262,MATCH($A14,PRESUPUESTO!$A$10:$A$262,0)),""))} | C14: Muros interiores zona inferior | D14: — | E14: 2.05 | F14: 0.88 | G14: 3.4 | H14: 1 | I14: =E14*F14*G14*H14 | J14: {=IF($A14="","",IFERROR(INDEX(PRESUPUESTO!$D$10:$D$174,MATCH($A14&"|"&$B14,PRESUPUESTO!$O$10:$O$174,0)),"⚠"))} | K14: {=IF($A14="","",IFERROR(INDEX(PRESUPUESTO!$C$10:$C$174,MATCH($A14&"|"&$B14,PRESUPUESTO!$O$10:$O$174,0)),""))} | L14: {=IF($A14="","",IFERROR(INDEX(PRESUPUESTO!$B$10:$B$174,MATCH($A14,PRESUPUESTO!$A$10:$A$174,0)),"⚠ clave no existe"))} | M14: {=IF($A14="","",IFERROR(INDEX(PRESUPUESTO!$C$10:$C$262,MATCH($A14,PRESUPUESTO!$A$10:$A$262,0)),""))} | N14: =IF($A14="","",IFERROR(SUMIF($A$10:$A$509,$A14,$I$10:$I$509)-$M14,""))
A15: DEM5029 | B15: {=IF($A15="","",IFERROR(INDEX(PRESUPUESTO!$N$10:$N$262,MATCH($A15,PRESUPUESTO!$A$10:$A$262,0)),""))} | C15: Muro de fachada a paso de servidumbre | D15: — | E15: 7.53 | F15: 0.2 | G15: 3.4 | H15: 1 | I15: =E15*F15*G15*H15 | J15: {=IF($A15="","",IFERROR(INDEX(PRESUPUESTO!$D$10:$D$174,MATCH($A15&"|"&$B15,PRESUPUESTO!$O$10:$O$174,0)),"⚠"))} | K15: {=IF($A15="","",IFERROR(INDEX(PRESUPUESTO!$C$10:$C$174,MATCH($A15&"|"&$B15,PRESUPUESTO!$O$10:$O$174,0)),""))} | L15: {=IF($A15="","",IFERROR(INDEX(PRESUPUESTO!$B$10:$B$174,MATCH($A15,PRESUPUESTO!$A$10:$A$174,0)),"⚠ clave no existe"))} | M15: {=IF($A15="","",IFERROR(INDEX(PRESUPUESTO!$C$10:$C$262,MATCH($A15,PRESUPUESTO!$A$10:$A$262,0)),""))} | N15: =IF($A15="","",IFERROR(SUMIF($A$10:$A$509,$A15,$I$10:$I$509)-$M15,""))
A16: DEM5029 | B16: {=IF($A16="","",IFERROR(INDEX(PRESUPUESTO!$N$10:$N$262,MATCH($A16,PRESUPUESTO!$A$10:$A$262,0)),""))} | C16: Muro posterior contra patio propio | D16: — | E16: 7.53 | F16: 0.16 | G16: 3.4 | H16: 1 | I16: =E16*F16*G16*H16 | J16: {=IF($A16="","",IFERROR(INDEX(PRESUPUESTO!$D$10:$D$174,MATCH($A16&"|"&$B16,PRESUPUESTO!$O$10:$O$174,0)),"⚠"))} | K16: {=IF($A16="","",IFERROR(INDEX(PRESUPUESTO!$C$10:$C$174,MATCH($A16&"|"&$B16,PRESUPUESTO!$O$10:$O$174,0)),""))} | L16: {=IF($A16="","",IFERROR(INDEX(PRESUPUESTO!$B$10:$B$174,MATCH($A16,PRESUPUESTO!$A$10:$A$174,0)),"⚠ clave no existe"))} | M16: {=IF($A16="","",IFERROR(INDEX(PRESUPUESTO!$C$10:$C$262,MATCH($A16,PRESUPUESTO!$A$10:$A$262,0)),""))} | N16: =IF($A16="","",IFERROR(SUMIF($A$10:$A$509,$A16,$I$10:$I$509)-$M16,""))
A17: DEM5030 | B17: {=IF($A17="","",IFERROR(INDEX(PRESUPUESTO!$N$10:$N$262,MATCH($A17,PRESUPUESTO!$A$10:$A$262,0)),""))} | C17: Losa de cubierta de la casa actual | D17: Zona A | E17: 7.93 | F17: 6.36 | G17: 0.12 | H17: 1 | I17: =E17*F17*G17*H17 | J17: {=IF($A17="","",IFERROR(INDEX(PRESUPUESTO!$D$10:$D$174,MATCH($A17&"|"&$B17,PRESUPUESTO!$O$10:$O$174,0)),"⚠"))} | K17: {=IF($A17="","",IFERROR(INDEX(PRESUPUESTO!$C$10:$C$174,MATCH($A17&"|"&$B17,PRESUPUESTO!$O$10:$O$174,0)),""))} | L17: {=IF($A17="","",IFERROR(INDEX(PRESUPUESTO!$B$10:$B$174,MATCH($A17,PRESUPUESTO!$A$10:$A$174,0)),"⚠ clave no existe"))} | M17: {=IF($A17="","",IFERROR(INDEX(PRESUPUESTO!$C$10:$C$262,MATCH($A17,PRESUPUESTO!$A$10:$A$262,0)),""))} | N17: =IF($A17="","",IFERROR(SUMIF($A$10:$A$509,$A17,$I$10:$I$509)-$M17,""))
A18: DEM5031 | B18: {=IF($A18="","",IFERROR(INDEX(PRESUPUESTO!$N$10:$N$262,MATCH($A18,PRESUPUESTO!$A$10:$A$262,0)),""))} | C18: Concreto pobre del patio | D18: Zona B | E18: 7.93 | F18: 3.69 | G18: 0.08 | H18: 1 | I18: =E18*F18*G18*H18 | J18: {=IF($A18="","",IFERROR(INDEX(PRESUPUESTO!$D$10:$D$174,MATCH($A18&"|"&$B18,PRESUPUESTO!$O$10:$O$174,0)),"⚠"))} | K18: {=IF($A18="","",IFERROR(INDEX(PRESUPUESTO!$C$10:$C$174,MATCH($A18&"|"&$B18,PRESUPUESTO!$O$10:$O$174,0)),""))} | L18: {=IF($A18="","",IFERROR(INDEX(PRESUPUESTO!$B$10:$B$174,MATCH($A18,PRESUPUESTO!$A$10:$A$174,0)),"⚠ clave no existe"))} | M18: {=IF($A18="","",IFERROR(INDEX(PRESUPUESTO!$C$10:$C$262,MATCH($A18,PRESUPUESTO!$A$10:$A$262,0)),""))} | N18: =IF($A18="","",IFERROR(SUMIF($A$10:$A$509,$A18,$I$10:$I$509)-$M18,""))
A19: EXV3018 | B19: {=IF($A19="","",IFERROR(INDEX(PRESUPUESTO!$N$10:$N$262,MATCH($A19,PRESUPUESTO!$A$10:$A$262,0)),""))} | C19: Trinchera CT-1 colindancia | D19: ES-07 | E19: 48.55 | F19: 0.2 | G19: 0.4 | H19: 1 | I19: =E19*F19*G19*H19 | J19: {=IF($A19="","",IFERROR(INDEX(PRESUPUESTO!$D$10:$D$174,MATCH($A19&"|"&$B19,PRESUPUESTO!$O$10:$O$174,0)),"⚠"))} | K19: {=IF($A19="","",IFERROR(INDEX(PRESUPUESTO!$C$10:$C$174,MATCH($A19&"|"&$B19,PRESUPUESTO!$O$10:$O$174,0)),""))} | L19: {=IF($A19="","",IFERROR(INDEX(PRESUPUESTO!$B$10:$B$174,MATCH($A19,PRESUPUESTO!$A$10:$A$174,0)),"⚠ clave no existe"))} | M19: {=IF($A19="","",IFERROR(INDEX(PRESUPUESTO!$C$10:$C$262,MATCH($A19,PRESUPUESTO!$A$10:$A$262,0)),""))} | N19: =IF($A19="","",IFERROR(SUMIF($A$10:$A$509,$A19,$I$10:$I$509)-$M19,""))
A20: EXV3018 | B20: {=IF($A20="","",IFERROR(INDEX(PRESUPUESTO!$N$10:$N$262,MATCH($A20,PRESUPUESTO!$A$10:$A$262,0)),""))} | C20: Trinchera CT-1 central | D20: ES-07 | E20: 40.55 | F20: 0.2 | G20: 0.4 | H20: 1 | I20: =E20*F20*G20*H20 | J20: {=IF($A20="","",IFERROR(INDEX(PRESUPUESTO!$D$10:$D$174,MATCH($A20&"|"&$B20,PRESUPUESTO!$O$10:$O$174,0)),"⚠"))} | K20: {=IF($A20="","",IFERROR(INDEX(PRESUPUESTO!$C$10:$C$174,MATCH($A20&"|"&$B20,PRESUPUESTO!$O$10:$O$174,0)),""))} | L20: {=IF($A20="","",IFERROR(INDEX(PRESUPUESTO!$B$10:$B$174,MATCH($A20,PRESUPUESTO!$A$10:$A$174,0)),"⚠ clave no existe"))} | M20: {=IF($A20="","",IFERROR(INDEX(PRESUPUESTO!$C$10:$C$262,MATCH($A20,PRESUPUESTO!$A$10:$A$262,0)),""))} | N20: =IF($A20="","",IFERROR(SUMIF($A$10:$A$509,$A20,$I$10:$I$509)-$M20,""))
A21: EXV3019 | B21: {=IF($A21="","",IFERROR(INDEX(PRESUPUESTO!$N$10:$N$262,MATCH($A21,PRESUPUESTO!$A$10:$A$262,0)),""))} | C21: Rebaje de terreno mejorado | D21: Zona B | E21: 7.93 | F21: 3.69 | G21: 0.2 | H21: 1 | I21: =E21*F21*G21*H21 | J21: {=IF($A21="","",IFERROR(INDEX(PRESUPUESTO!$D$10:$D$174,MATCH($A21&"|"&$B21,PRESUPUESTO!$O$10:$O$174,0)),"⚠"))} | K21: {=IF($A21="","",IFERROR(INDEX(PRESUPUESTO!$C$10:$C$174,MATCH($A21&"|"&$B21,PRESUPUESTO!$O$10:$O$174,0)),""))} | L21: {=IF($A21="","",IFERROR(INDEX(PRESUPUESTO!$B$10:$B$174,MATCH($A21,PRESUPUESTO!$A$10:$A$174,0)),"⚠ clave no existe"))} | M21: {=IF($A21="","",IFERROR(INDEX(PRESUPUESTO!$C$10:$C$262,MATCH($A21,PRESUPUESTO!$A$10:$A$262,0)),""))} | N21: =IF($A21="","",IFERROR(SUMIF($A$10:$A$509,$A21,$I$10:$I$509)-$M21,""))
... A31: ALB08216 | B31: {=IF($A31="","",IFERROR(INDEX(PRESUPUESTO!$N$10:$N$262,MATCH($A31,PRESUPUESTO!$A$10:$A$262,0)),""))} | C31: K-1 castillos · nivel 1 | D31: ES-07 N-2 | E31: 72.9 | F31: 1 | G31: 1 | H31: 1 | I31: =E31*F31*G31*H31 | J31: {=IF($A31="","",IFERROR(INDEX(PRESUPUESTO!$D$10:$D$174,MATCH($A31&"|"&$B31,PRESUPUESTO!$O$10:$O$174,0)),"⚠"))} | K31: {=IF($A31="","",IFERROR(INDEX(PRESUPUESTO!$C$10:$C$174,MATCH($A31&"|"&$B31,PRESUPUESTO!$O$10:$O$174,0)),""))} | L31: {=IF($A31="","",IFERROR(INDEX(PRESUPUESTO!$B$10:$B$174,MATCH($A31,PRESUPUESTO!$A$10:$A$174,0)),"⚠ clave no existe"))} | M31: {=IF($A31="","",IFERROR(INDEX(PRESUPUESTO!$C$10:$C$262,MATCH($A31,PRESUPUESTO!$A$10:$A$262,0)),""))} | N31: =IF($A31="","",IFERROR(SUMIF($A$10:$A$509,$A31,$I$10:$I$509)-$M31,""))
B32: {=IF($A32="","",IFERROR(INDEX(PRESUPUESTO!$N$10:$N$262,MATCH($A32,PRESUPUESTO!$A$10:$A$262,0)),""))} | J32: {=IF($A32="","",IFERROR(INDEX(PRESUPUESTO!$D$10:$D$174,MATCH($A32&"|"&$B32,PRESUPUESTO!$O$10:$O$174,0)),"⚠"))} | K32: {=IF($A32="","",IFERROR(INDEX(PRESUPUESTO!$C$10:$C$174,MATCH($A32&"|"&$B32,PRESUPUESTO!$O$10:$O$174,0)),""))} | L32: {=IF($A32="","",IFERROR(INDEX(PRESUPUESTO!$B$10:$B$174,MATCH($A32,PRESUPUESTO!$A$10:$A$174,0)),"⚠ clave no existe"))} | M32: {=IF($A32="","",IFERROR(INDEX(PRESUPUESTO!$C$10:$C$262,MATCH($A32,PRESUPUESTO!$A$10:$A$262,0)),""))} | N32: =IF($A32="","",IFERROR(SUMIF($A$10:$A$509,$A32,$I$10:$I$509)-$M32,""))
A33: VOLUMEN ACUMULADO POR CLAVE · esto es lo que lee la columna CANTIDAD del PRESUPUESTO | B33: {=IF($A33="","",IFERROR(INDEX(PRESUPUESTO!$N$10:$N$262,MATCH($A33,PRESUPUESTO!$A$10:$A$262,0)),""))} | J33: {=IF($A33="","",IFERROR(INDEX(PRESUPUESTO!$D$10:$D$174,MATCH($A33&"|"&$B33,PRESUPUESTO!$O$10:$O$174,0)),"⚠"))} | K33: {=IF($A33="","",IFERROR(INDEX(PRESUPUESTO!$C$10:$C$174,MATCH($A33&"|"&$B33,PRESUPUESTO!$O$10:$O$174,0)),""))} | L33: {=IF($A33="","",IFERROR(INDEX(PRESUPUESTO!$B$10:$B$174,MATCH($A33,PRESUPUESTO!$A$10:$A$174,0)),"⚠ clave no existe"))} | M33: {=IF($A33="","",IFERROR(INDEX(PRESUPUESTO!$C$10:$C$262,MATCH($A33,PRESUPUESTO!$A$10:$A$262,0)),""))} | N33: =IF($A33="","",IFERROR(SUMIF($A$10:$A$509,$A33,$I$10:$I$509)-$M33,""))
A34: CLAVE | B34: {=IF($A34="","",IFERROR(INDEX(PRESUPUESTO!$N$10:$N$262,MATCH($A34,PRESUPUESTO!$A$10:$A$262,0)),""))} | C34: CONCEPTO | I34: VOLUMEN | J34: {=IF($A34="","",IFERROR(INDEX(PRESUPUESTO!$D$10:$D$174,MATCH($A34&"|"&$B34,PRESUPUESTO!$O$10:$O$174,0)),"⚠"))} | K34: {=IF($A34="","",IFERROR(INDEX(PRESUPUESTO!$C$10:$C$174,MATCH($A34&"|"&$B34,PRESUPUESTO!$O$10:$O$174,0)),""))} | L34: {=IF($A34="","",IFERROR(INDEX(PRESUPUESTO!$B$10:$B$174,MATCH($A34,PRESUPUESTO!$A$10:$A$174,0)),"⚠ clave no existe"))} | M34: {=IF($A34="","",IFERROR(INDEX(PRESUPUESTO!$C$10:$C$262,MATCH($A34,PRESUPUESTO!$A$10:$A$262,0)),""))} | N34: =IF($A34="","",IFERROR(SUMIF($A$10:$A$509,$A34,$I$10:$I$509)-$M34,""))
A35: ALB08216 | B35: {=IF($A35="","",IFERROR(INDEX(PRESUPUESTO!$N$10:$N$262,MATCH($A35,PRESUPUESTO!$A$10:$A$262,0)),""))} | C35: {=IFERROR(INDEX(PRESUPUESTO!$B$10:$B$204,MATCH($A35&"|"&$B35,PRESUPUESTO!$O$10:$O$204,0)),"⚠ no existe en ese módulo")} | I35: =SUMIFS($I$10:$I$31,$A$10:$A$31,$A35,$B$10:$B$31,$B35) | J35: {=IF($A35="","",IFERROR(INDEX(PRESUPUESTO!$D$10:$D$174,MATCH($A35&"|"&$B35,PRESUPUESTO!$O$10:$O$174,0)),"⚠"))} | K35: {=IF($A35="","",IFERROR(INDEX(PRESUPUESTO!$C$10:$C$174,MATCH($A35&"|"&$B35,PRESUPUESTO!$O$10:$O$174,0)),""))} | L35: {=IF($A35="","",IFERROR(INDEX(PRESUPUESTO!$B$10:$B$174,MATCH($A35,PRESUPUESTO!$A$10:$A$174,0)),"⚠ clave no existe"))} | M35: {=IF($A35="","",IFERROR(INDEX(PRESUPUESTO!$C$10:$C$262,MATCH($A35,PRESUPUESTO!$A$10:$A$262,0)),""))} | N35: =IF($A35="","",IFERROR(SUMIF($A$10:$A$509,$A35,$I$10:$I$509)-$M35,""))
A36: ALB08216 | B36: {=IF($A36="","",IFERROR(INDEX(PRESUPUESTO!$N$10:$N$262,MATCH($A36,PRESUPUESTO!$A$10:$A$262,0)),""))} | C36: {=IFERROR(INDEX(PRESUPUESTO!$B$10:$B$204,MATCH($A36&"|"&$B36,PRESUPUESTO!$O$10:$O$204,0)),"⚠ no existe en ese módulo")} | I36: =SUMIFS($I$10:$I$31,$A$10:$A$31,$A36,$B$10:$B$31,$B36) | J36: {=IF($A36="","",IFERROR(INDEX(PRESUPUESTO!$D$10:$D$174,MATCH($A36&"|"&$B36,PRESUPUESTO!$O$10:$O$174,0)),"⚠"))} | K36: {=IF($A36="","",IFERROR(INDEX(PRESUPUESTO!$C$10:$C$174,MATCH($A36&"|"&$B36,PRESUPUESTO!$O$10:$O$174,0)),""))} | L36: {=IF($A36="","",IFERROR(INDEX(PRESUPUESTO!$B$10:$B$174,MATCH($A36,PRESUPUESTO!$A$10:$A$174,0)),"⚠ clave no existe"))} | M36: {=IF($A36="","",IFERROR(INDEX(PRESUPUESTO!$C$10:$C$262,MATCH($A36,PRESUPUESTO!$A$10:$A$262,0)),""))} | N36: =IF($A36="","",IFERROR(SUMIF($A$10:$A$509,$A36,$I$10:$I$509)-$M36,""))
A37: ALB08219 | B37: {=IF($A37="","",IFERROR(INDEX(PRESUPUESTO!$N$10:$N$262,MATCH($A37,PRESUPUESTO!$A$10:$A$262,0)),""))} | C37: {=IFERROR(INDEX(PRESUPUESTO!$B$10:$B$204,MATCH($A37&"|"&$B37,PRESUPUESTO!$O$10:$O$204,0)),"⚠ no existe en ese módulo")} | I37: =SUMIFS($I$10:$I$31,$A$10:$A$31,$A37,$B$10:$B$31,$B37) | J37: {=IF($A37="","",IFERROR(INDEX(PRESUPUESTO!$D$10:$D$174,MATCH($A37&"|"&$B37,PRESUPUESTO!$O$10:$O$174,0)),"⚠"))} | K37: {=IF($A37="","",IFERROR(INDEX(PRESUPUESTO!$C$10:$C$174,MATCH($A37&"|"&$B37,PRESUPUESTO!$O$10:$O$174,0)),""))} | L37: {=IF($A37="","",IFERROR(INDEX(PRESUPUESTO!$B$10:$B$174,MATCH($A37,PRESUPUESTO!$A$10:$A$174,0)),"⚠ clave no existe"))} | M37: {=IF($A37="","",IFERROR(INDEX(PRESUPUESTO!$C$10:$C$262,MATCH($A37,PRESUPUESTO!$A$10:$A$262,0)),""))} | N37: =IF($A37="","",IFERROR(SUMIF($A$10:$A$509,$A37,$I$10:$I$509)-$M37,""))
A38: ALB08219 | B38: {=IF($A38="","",IFERROR(INDEX(PRESUPUESTO!$N$10:$N$262,MATCH($A38,PRESUPUESTO!$A$10:$A$262,0)),""))} | C38: {=IFERROR(INDEX(PRESUPUESTO!$B$10:$B$204,MATCH($A38&"|"&$B38,PRESUPUESTO!$O$10:$O$204,0)),"⚠ no existe en ese módulo")} | I38: =SUMIFS($I$10:$I$31,$A$10:$A$31,$A38,$B$10:$B$31,$B38) | J38: {=IF($A38="","",IFERROR(INDEX(PRESUPUESTO!$D$10:$D$174,MATCH($A38&"|"&$B38,PRESUPUESTO!$O$10:$O$174,0)),"⚠"))} | K38: {=IF($A38="","",IFERROR(INDEX(PRESUPUESTO!$C$10:$C$174,MATCH($A38&"|"&$B38,PRESUPUESTO!$O$10:$O$174,0)),""))} | L38: {=IF($A38="","",IFERROR(INDEX(PRESUPUESTO!$B$10:$B$174,MATCH($A38,PRESUPUESTO!$A$10:$A$174,0)),"⚠ clave no existe"))} | M38: {=IF($A38="","",IFERROR(INDEX(PRESUPUESTO!$C$10:$C$262,MATCH($A38,PRESUPUESTO!$A$10:$A$262,0)),""))} | N38: =IF($A38="","",IFERROR(SUMIF($A$10:$A$509,$A38,$I$10:$I$509)-$M38,""))
A39: ALB08224 | B39: {=IF($A39="","",IFERROR(INDEX(PRESUPUESTO!$N$10:$N$262,MATCH($A39,PRESUPUESTO!$A$10:$A$262,0)),""))} | C39: {=IFERROR(INDEX(PRESUPUESTO!$B$10:$B$204,MATCH($A39&"|"&$B39,PRESUPUESTO!$O$10:$O$204,0)),"⚠ no existe en ese módulo")} | I39: =SUMIFS($I$10:$I$31,$A$10:$A$31,$A39,$B$10:$B$31,$B39) | J39: {=IF($A39="","",IFERROR(INDEX(PRESUPUESTO!$D$10:$D$174,MATCH($A39&"|"&$B39,PRESUPUESTO!$O$10:$O$174,0)),"⚠"))} | K39: {=IF($A39="","",IFERROR(INDEX(PRESUPUESTO!$C$10:$C$174,MATCH($A39&"|"&$B39,PRESUPUESTO!$O$10:$O$174,0)),""))} | L39: {=IF($A39="","",IFERROR(INDEX(PRESUPUESTO!$B$10:$B$174,MATCH($A39,PRESUPUESTO!$A$10:$A$174,0)),"⚠ clave no existe"))} | M39: {=IF($A39="","",IFERROR(INDEX(PRESUPUESTO!$C$10:$C$262,MATCH($A39,PRESUPUESTO!$A$10:$A$262,0)),""))} | N39: =IF($A39="","",IFERROR(SUMIF($A$10:$A$509,$A39,$I$10:$I$509)-$M39,""))
A40: ALB08226 | B40: {=IF($A40="","",IFERROR(INDEX(PRESUPUESTO!$N$10:$N$262,MATCH($A40,PRESUPUESTO!$A$10:$A$262,0)),""))} | C40: {=IFERROR(INDEX(PRESUPUESTO!$B$10:$B$204,MATCH($A40&"|"&$B40,PRESUPUESTO!$O$10:$O$204,0)),"⚠ no existe en ese módulo")} | I40: =SUMIFS($I$10:$I$31,$A$10:$A$31,$A40,$B$10:$B$31,$B40) | J40: {=IF($A40="","",IFERROR(INDEX(PRESUPUESTO!$D$10:$D$174,MATCH($A40&"|"&$B40,PRESUPUESTO!$O$10:$O$174,0)),"⚠"))} | K40: {=IF($A40="","",IFERROR(INDEX(PRESUPUESTO!$C$10:$C$174,MATCH($A40&"|"&$B40,PRESUPUESTO!$O$10:$O$174,0)),""))} | L40: {=IF($A40="","",IFERROR(INDEX(PRESUPUESTO!$B$10:$B$174,MATCH($A40,PRESUPUESTO!$A$10:$A$174,0)),"⚠ clave no existe"))} | M40: {=IF($A40="","",IFERROR(INDEX(PRESUPUESTO!$C$10:$C$262,MATCH($A40,PRESUPUESTO!$A$10:$A$262,0)),""))} | N40: =IF($A40="","",IFERROR(SUMIF($A$10:$A$509,$A40,$I$10:$I$509)-$M40,""))
A41: CIM04002 | B41: {=IF($A41="","",IFERROR(INDEX(PRESUPUESTO!$N$10:$N$262,MATCH($A41,PRESUPUESTO!$A$10:$A$262,0)),""))} | C41: {=IFERROR(INDEX(PRESUPUESTO!$B$10:$B$204,MATCH($A41&"|"&$B41,PRESUPUESTO!$O$10:$O$204,0)),"⚠ no existe en ese módulo")} | I41: =SUMIFS($I$10:$I$31,$A$10:$A$31,$A41,$B$10:$B$31,$B41) | J41: {=IF($A41="","",IFERROR(INDEX(PRESUPUESTO!$D$10:$D$174,MATCH($A41&"|"&$B41,PRESUPUESTO!$O$10:$O$174,0)),"⚠"))} | K41: {=IF($A41="","",IFERROR(INDEX(PRESUPUESTO!$C$10:$C$174,MATCH($A41&"|"&$B41,PRESUPUESTO!$O$10:$O$174,0)),""))} | L41: {=IF($A41="","",IFERROR(INDEX(PRESUPUESTO!$B$10:$B$174,MATCH($A41,PRESUPUESTO!$A$10:$A$174,0)),"⚠ clave no existe"))} | M41: {=IF($A41="","",IFERROR(INDEX(PRESUPUESTO!$C$10:$C$262,MATCH($A41,PRESUPUESTO!$A$10:$A$262,0)),""))} | N41: =IF($A41="","",IFERROR(SUMIF($A$10:$A$509,$A41,$I$10:$I$509)-$M41,""))
A42: CIM04003 | B42: {=IF($A42="","",IFERROR(INDEX(PRESUPUESTO!$N$10:$N$262,MATCH($A42,PRESUPUESTO!$A$10:$A$262,0)),""))} | C42: {=IFERROR(INDEX(PRESUPUESTO!$B$10:$B$204,MATCH($A42&"|"&$B42,PRESUPUESTO!$O$10:$O$204,0)),"⚠ no existe en ese módulo")} | I42: =SUMIFS($I$10:$I$31,$A$10:$A$31,$A42,$B$10:$B$31,$B42) | J42: {=IF($A42="","",IFERROR(INDEX(PRESUPUESTO!$D$10:$D$174,MATCH($A42&"|"&$B42,PRESUPUESTO!$O$10:$O$174,0)),"⚠"))} | K42: {=IF($A42="","",IFERROR(INDEX(PRESUPUESTO!$C$10:$C$174,MATCH($A42&"|"&$B42,PRESUPUESTO!$O$10:$O$174,0)),""))} | L42: {=IF($A42="","",IFERROR(INDEX(PRESUPUESTO!$B$10:$B$174,MATCH($A42,PRESUPUESTO!$A$10:$A$174,0)),"⚠ clave no existe"))} | M42: {=IF($A42="","",IFERROR(INDEX(PRESUPUESTO!$C$10:$C$262,MATCH($A42,PRESUPUESTO!$A$10:$A$262,0)),""))} | N42: =IF($A42="","",IFERROR(SUMIF($A$10:$A$509,$A42,$I$10:$I$509)-$M42,""))
A43: CIM04004 | B43: {=IF($A43="","",IFERROR(INDEX(PRESUPUESTO!$N$10:$N$262,MATCH($A43,PRESUPUESTO!$A$10:$A$262,0)),""))} | C43: {=IFERROR(INDEX(PRESUPUESTO!$B$10:$B$204,MATCH($A43&"|"&$B43,PRESUPUESTO!$O$10:$O$204,0)),"⚠ no existe en ese módulo")} | I43: =SUMIFS($I$10:$I$31,$A$10:$A$31,$A43,$B$10:$B$31,$B43) | J43: {=IF($A43="","",IFERROR(INDEX(PRESUPUESTO!$D$10:$D$174,MATCH($A43&"|"&$B43,PRESUPUESTO!$O$10:$O$174,0)),"⚠"))} | K43: {=IF($A43="","",IFERROR(INDEX(PRESUPUESTO!$C$10:$C$174,MATCH($A43&"|"&$B43,PRESUPUESTO!$O$10:$O$174,0)),""))} | L43: {=IF($A43="","",IFERROR(INDEX(PRESUPUESTO!$B$10:$B$174,MATCH($A43,PRESUPUESTO!$A$10:$A$174,0)),"⚠ clave no existe"))} | M43: {=IF($A43="","",IFERROR(INDEX(PRESUPUESTO!$C$10:$C$262,MATCH($A43,PRESUPUESTO!$A$10:$A$262,0)),""))} | N43: =IF($A43="","",IFERROR(SUMIF($A$10:$A$509,$A43,$I$10:$I$509)-$M43,""))
A44: DEM5029 | B44: {=IF($A44="","",IFERROR(INDEX(PRESUPUESTO!$N$10:$N$262,MATCH($A44,PRESUPUESTO!$A$10:$A$262,0)),""))} | C44: {=IFERROR(INDEX(PRESUPUESTO!$B$10:$B$204,MATCH($A44&"|"&$B44,PRESUPUESTO!$O$10:$O$204,0)),"⚠ no existe en ese módulo")} | I44: =SUMIFS($I$10:$I$31,$A$10:$A$31,$A44,$B$10:$B$31,$B44) | J44: {=IF($A44="","",IFERROR(INDEX(PRESUPUESTO!$D$10:$D$174,MATCH($A44&"|"&$B44,PRESUPUESTO!$O$10:$O$174,0)),"⚠"))} | K44: {=IF($A44="","",IFERROR(INDEX(PRESUPUESTO!$C$10:$C$174,MATCH($A44&"|"&$B44,PRESUPUESTO!$O$10:$O$174,0)),""))} | L44: {=IF($A44="","",IFERROR(INDEX(PRESUPUESTO!$B$10:$B$174,MATCH($A44,PRESUPUESTO!$A$10:$A$174,0)),"⚠ clave no existe"))} | M44: {=IF($A44="","",IFERROR(INDEX(PRESUPUESTO!$C$10:$C$262,MATCH($A44,PRESUPUESTO!$A$10:$A$262,0)),""))} | N44: =IF($A44="","",IFERROR(SUMIF($A$10:$A$509,$A44,$I$10:$I$509)-$M44,""))
A45: DEM5030 | B45: {=IF($A45="","",IFERROR(INDEX(PRESUPUESTO!$N$10:$N$262,MATCH($A45,PRESUPUESTO!$A$10:$A$262,0)),""))} | C45: {=IFERROR(INDEX(PRESUPUESTO!$B$10:$B$204,MATCH($A45&"|"&$B45,PRESUPUESTO!$O$10:$O$204,0)),"⚠ no existe en ese módulo")} | I45: =SUMIFS($I$10:$I$31,$A$10:$A$31,$A45,$B$10:$B$31,$B45) | J45: {=IF($A45="","",IFERROR(INDEX(PRESUPUESTO!$D$10:$D$174,MATCH($A45&"|"&$B45,PRESUPUESTO!$O$10:$O$174,0)),"⚠"))} | K45: {=IF($A45="","",IFERROR(INDEX(PRESUPUESTO!$C$10:$C$174,MATCH($A45&"|"&$B45,PRESUPUESTO!$O$10:$O$174,0)),""))} | L45: {=IF($A45="","",IFERROR(INDEX(PRESUPUESTO!$B$10:$B$174,MATCH($A45,PRESUPUESTO!$A$10:$A$174,0)),"⚠ clave no existe"))} | M45: {=IF($A45="","",IFERROR(INDEX(PRESUPUESTO!$C$10:$C$262,MATCH($A45,PRESUPUESTO!$A$10:$A$262,0)),""))} | N45: =IF($A45="","",IFERROR(SUMIF($A$10:$A$509,$A45,$I$10:$I$509)-$M45,""))
A46: DEM5031 | B46: {=IF($A46="","",IFERROR(INDEX(PRESUPUESTO!$N$10:$N$262,MATCH($A46,PRESUPUESTO!$A$10:$A$262,0)),""))} | C46: {=IFERROR(INDEX(PRESUPUESTO!$B$10:$B$204,MATCH($A46&"|"&$B46,PRESUPUESTO!$O$10:$O$204,0)),"⚠ no existe en ese módulo")} | I46: =SUMIFS($I$10:$I$31,$A$10:$A$31,$A46,$B$10:$B$31,$B46) | J46: {=IF($A46="","",IFERROR(INDEX(PRESUPUESTO!$D$10:$D$174,MATCH($A46&"|"&$B46,PRESUPUESTO!$O$10:$O$174,0)),"⚠"))} | K46: {=IF($A46="","",IFERROR(INDEX(PRESUPUESTO!$C$10:$C$174,MATCH($A46&"|"&$B46,PRESUPUESTO!$O$10:$O$174,0)),""))} | L46: {=IF($A46="","",IFERROR(INDEX(PRESUPUESTO!$B$10:$B$174,MATCH($A46,PRESUPUESTO!$A$10:$A$174,0)),"⚠ clave no existe"))} | M46: {=IF($A46="","",IFERROR(INDEX(PRESUPUESTO!$C$10:$C$262,MATCH($A46,PRESUPUESTO!$A$10:$A$262,0)),""))} | N46: =IF($A46="","",IFERROR(SUMIF($A$10:$A$509,$A46,$I$10:$I$509)-$M46,""))
... A49: PRE02226 | B49: {=IF($A49="","",IFERROR(INDEX(PRESUPUESTO!$N$10:$N$262,MATCH($A49,PRESUPUESTO!$A$10:$A$262,0)),""))} | C49: {=IFERROR(INDEX(PRESUPUESTO!$B$10:$B$204,MATCH($A49&"|"&$B49,PRESUPUESTO!$O$10:$O$204,0)),"⚠ no existe en ese módulo")} | I49: =SUMIFS($I$10:$I$31,$A$10:$A$31,$A49,$B$10:$B$31,$B49) | J49: {=IF($A49="","",IFERROR(INDEX(PRESUPUESTO!$D$10:$D$174,MATCH($A49&"|"&$B49,PRESUPUESTO!$O$10:$O$174,0)),"⚠"))} | K49: {=IF($A49="","",IFERROR(INDEX(PRESUPUESTO!$C$10:$C$174,MATCH($A49&"|"&$B49,PRESUPUESTO!$O$10:$O$174,0)),""))} | L49: {=IF($A49="","",IFERROR(INDEX(PRESUPUESTO!$B$10:$B$174,MATCH($A49,PRESUPUESTO!$A$10:$A$174,0)),"⚠ clave no existe"))} | M49: {=IF($A49="","",IFERROR(INDEX(PRESUPUESTO!$C$10:$C$262,MATCH($A49,PRESUPUESTO!$A$10:$A$262,0)),""))} | N49: =IF($A49="","",IFERROR(SUMIF($A$10:$A$509,$A49,$I$10:$I$509)-$M49,""))
B50: {=IF($A50="","",IFERROR(INDEX(PRESUPUESTO!$N$10:$N$262,MATCH($A50,PRESUPUESTO!$A$10:$A$262,0)),""))} | J50: {=IF($A50="","",IFERROR(INDEX(PRESUPUESTO!$D$10:$D$174,MATCH($A50&"|"&$B50,PRESUPUESTO!$O$10:$O$174,0)),"⚠"))} | K50: {=IF($A50="","",IFERROR(INDEX(PRESUPUESTO!$C$10:$C$174,MATCH($A50&"|"&$B50,PRESUPUESTO!$O$10:$O$174,0)),""))} | L50: {=IF($A50="","",IFERROR(INDEX(PRESUPUESTO!$B$10:$B$174,MATCH($A50,PRESUPUESTO!$A$10:$A$174,0)),"⚠ clave no existe"))} | M50: {=IF($A50="","",IFERROR(INDEX(PRESUPUESTO!$C$10:$C$262,MATCH($A50,PRESUPUESTO!$A$10:$A$262,0)),""))} | N50: =IF($A50="","",IFERROR(SUMIF($A$10:$A$509,$A50,$I$10:$I$509)-$M50,""))
B51: {=IF($A51="","",IFERROR(INDEX(PRESUPUESTO!$N$10:$N$262,MATCH($A51,PRESUPUESTO!$A$10:$A$262,0)),""))} | C51: Renglón en rojo = el volumen del generador NO coincide con la cantidad capturada en el presupuesto. | J51: {=IF($A51="","",IFERROR(INDEX(PRESUPUESTO!$D$10:$D$174,MATCH($A51&"|"&$B51,PRESUPUESTO!$O$10:$O$174,0)),"⚠"))} | K51: {=IF($A51="","",IFERROR(INDEX(PRESUPUESTO!$C$10:$C$174,MATCH($A51&"|"&$B51,PRESUPUESTO!$O$10:$O$174,0)),""))} | L51: {=IF($A51="","",IFERROR(INDEX(PRESUPUESTO!$B$10:$B$174,MATCH($A51,PRESUPUESTO!$A$10:$A$174,0)),"⚠ clave no existe"))} | M51: {=IF($A51="","",IFERROR(INDEX(PRESUPUESTO!$C$10:$C$262,MATCH($A51,PRESUPUESTO!$A$10:$A$262,0)),""))} | N51: =IF($A51="","",IFERROR(SUMIF($A$10:$A$509,$A51,$I$10:$I$509)-$M51,""))
B52: {=IF($A52="","",IFERROR(INDEX(PRESUPUESTO!$N$10:$N$262,MATCH($A52,PRESUPUESTO!$A$10:$A$262,0)),""))} | C52: Celda amarilla en FUENTE = el dato viene de un supuesto, no de plano. Hay que confirmarlo antes de cotizar. | J52: {=IF($A52="","",IFERROR(INDEX(PRESUPUESTO!$D$10:$D$174,MATCH($A52&"|"&$B52,PRESUPUESTO!$O$10:$O$174,0)),"⚠"))} | K52: {=IF($A52="","",IFERROR(INDEX(PRESUPUESTO!$C$10:$C$174,MATCH($A52&"|"&$B52,PRESUPUESTO!$O$10:$O$174,0)),""))} | L52: {=IF($A52="","",IFERROR(INDEX(PRESUPUESTO!$B$10:$B$174,MATCH($A52,PRESUPUESTO!$A$10:$A$174,0)),"⚠ clave no existe"))} | M52: {=IF($A52="","",IFERROR(INDEX(PRESUPUESTO!$C$10:$C$262,MATCH($A52,PRESUPUESTO!$A$10:$A$262,0)),""))} | N52: =IF($A52="","",IFERROR(SUMIF($A$10:$A$509,$A52,$I$10:$I$509)-$M52,""))
B53: {=IF($A53="","",IFERROR(INDEX(PRESUPUESTO!$N$10:$N$262,MATCH($A53,PRESUPUESTO!$A$10:$A$262,0)),""))} | J53: {=IF($A53="","",IFERROR(INDEX(PRESUPUESTO!$D$10:$D$174,MATCH($A53&"|"&$B53,PRESUPUESTO!$O$10:$O$174,0)),"⚠"))} | K53: {=IF($A53="","",IFERROR(INDEX(PRESUPUESTO!$C$10:$C$174,MATCH($A53&"|"&$B53,PRESUPUESTO!$O$10:$O$174,0)),""))} | L53: {=IF($A53="","",IFERROR(INDEX(PRESUPUESTO!$B$10:$B$174,MATCH($A53,PRESUPUESTO!$A$10:$A$174,0)),"⚠ clave no existe"))} | M53: {=IF($A53="","",IFERROR(INDEX(PRESUPUESTO!$C$10:$C$262,MATCH($A53,PRESUPUESTO!$A$10:$A$262,0)),""))} | N53: =IF($A53="","",IFERROR(SUMIF($A$10:$A$509,$A53,$I$10:$I$509)-$M53,""))
B54: {=IF($A54="","",IFERROR(INDEX(PRESUPUESTO!$N$10:$N$262,MATCH($A54,PRESUPUESTO!$A$10:$A$262,0)),""))} | J54: {=IF($A54="","",IFERROR(INDEX(PRESUPUESTO!$D$10:$D$174,MATCH($A54&"|"&$B54,PRESUPUESTO!$O$10:$O$174,0)),"⚠"))} | K54: {=IF($A54="","",IFERROR(INDEX(PRESUPUESTO!$C$10:$C$174,MATCH($A54&"|"&$B54,PRESUPUESTO!$O$10:$O$174,0)),""))} | L54: {=IF($A54="","",IFERROR(INDEX(PRESUPUESTO!$B$10:$B$174,MATCH($A54,PRESUPUESTO!$A$10:$A$174,0)),"⚠ clave no existe"))} | M54: {=IF($A54="","",IFERROR(INDEX(PRESUPUESTO!$C$10:$C$262,MATCH($A54,PRESUPUESTO!$A$10:$A$262,0)),""))} | N54: =IF($A54="","",IFERROR(SUMIF($A$10:$A$509,$A54,$I$10:$I$509)-$M54,""))
B55: {=IF($A55="","",IFERROR(INDEX(PRESUPUESTO!$N$10:$N$262,MATCH($A55,PRESUPUESTO!$A$10:$A$262,0)),""))} | J55: {=IF($A55="","",IFERROR(INDEX(PRESUPUESTO!$D$10:$D$174,MATCH($A55&"|"&$B55,PRESUPUESTO!$O$10:$O$174,0)),"⚠"))} | K55: {=IF($A55="","",IFERROR(INDEX(PRESUPUESTO!$C$10:$C$174,MATCH($A55&"|"&$B55,PRESUPUESTO!$O$10:$O$174,0)),""))} | L55: {=IF($A55="","",IFERROR(INDEX(PRESUPUESTO!$B$10:$B$174,MATCH($A55,PRESUPUESTO!$A$10:$A$174,0)),"⚠ clave no existe"))} | M55: {=IF($A55="","",IFERROR(INDEX(PRESUPUESTO!$C$10:$C$262,MATCH($A55,PRESUPUESTO!$A$10:$A$262,0)),""))} | N55: =IF($A55="","",IFERROR(SUMIF($A$10:$A$509,$A55,$I$10:$I$509)-$M55,""))
B56: {=IF($A56="","",IFERROR(INDEX(PRESUPUESTO!$N$10:$N$262,MATCH($A56,PRESUPUESTO!$A$10:$A$262,0)),""))} | J56: {=IF($A56="","",IFERROR(INDEX(PRESUPUESTO!$D$10:$D$174,MATCH($A56&"|"&$B56,PRESUPUESTO!$O$10:$O$174,0)),"⚠"))} | K56: {=IF($A56="","",IFERROR(INDEX(PRESUPUESTO!$C$10:$C$174,MATCH($A56&"|"&$B56,PRESUPUESTO!$O$10:$O$174,0)),""))} | L56: {=IF($A56="","",IFERROR(INDEX(PRESUPUESTO!$B$10:$B$174,MATCH($A56,PRESUPUESTO!$A$10:$A$174,0)),"⚠ clave no existe"))} | M56: {=IF($A56="","",IFERROR(INDEX(PRESUPUESTO!$C$10:$C$262,MATCH($A56,PRESUPUESTO!$A$10:$A$262,0)),""))} | N56: =IF($A56="","",IFERROR(SUMIF($A$10:$A$509,$A56,$I$10:$I$509)-$M56,""))
B57: {=IF($A57="","",IFERROR(INDEX(PRESUPUESTO!$N$10:$N$262,MATCH($A57,PRESUPUESTO!$A$10:$A$262,0)),""))} | J57: {=IF($A57="","",IFERROR(INDEX(PRESUPUESTO!$D$10:$D$174,MATCH($A57&"|"&$B57,PRESUPUESTO!$O$10:$O$174,0)),"⚠"))} | K57: {=IF($A57="","",IFERROR(INDEX(PRESUPUESTO!$C$10:$C$174,MATCH($A57&"|"&$B57,PRESUPUESTO!$O$10:$O$174,0)),""))} | L57: {=IF($A57="","",IFERROR(INDEX(PRESUPUESTO!$B$10:$B$174,MATCH($A57,PRESUPUESTO!$A$10:$A$174,0)),"⚠ clave no existe"))} | M57: {=IF($A57="","",IFERROR(INDEX(PRESUPUESTO!$C$10:$C$262,MATCH($A57,PRESUPUESTO!$A$10:$A$262,0)),""))} | N57: =IF($A57="","",IFERROR(SUMIF($A$10:$A$509,$A57,$I$10:$I$509)-$M57,""))
B58: {=IF($A58="","",IFERROR(INDEX(PRESUPUESTO!$N$10:$N$262,MATCH($A58,PRESUPUESTO!$A$10:$A$262,0)),""))} | J58: {=IF($A58="","",IFERROR(INDEX(PRESUPUESTO!$D$10:$D$174,MATCH($A58&"|"&$B58,PRESUPUESTO!$O$10:$O$174,0)),"⚠"))} | K58: {=IF($A58="","",IFERROR(INDEX(PRESUPUESTO!$C$10:$C$174,MATCH($A58&"|"&$B58,PRESUPUESTO!$O$10:$O$174,0)),""))} | L58: {=IF($A58="","",IFERROR(INDEX(PRESUPUESTO!$B$10:$B$174,MATCH($A58,PRESUPUESTO!$A$10:$A$174,0)),"⚠ clave no existe"))} | M58: {=IF($A58="","",IFERROR(INDEX(PRESUPUESTO!$C$10:$C$262,MATCH($A58,PRESUPUESTO!$A$10:$A$262,0)),""))} | N58: =IF($A58="","",IFERROR(SUMIF($A$10:$A$509,$A58,$I$10:$I$509)-$M58,""))
B59: {=IF($A59="","",IFERROR(INDEX(PRESUPUESTO!$N$10:$N$262,MATCH($A59,PRESUPUESTO!$A$10:$A$262,0)),""))} | J59: {=IF($A59="","",IFERROR(INDEX(PRESUPUESTO!$D$10:$D$174,MATCH($A59&"|"&$B59,PRESUPUESTO!$O$10:$O$174,0)),"⚠"))} | K59: {=IF($A59="","",IFERROR(INDEX(PRESUPUESTO!$C$10:$C$174,MATCH($A59&"|"&$B59,PRESUPUESTO!$O$10:$O$174,0)),""))} | L59: {=IF($A59="","",IFERROR(INDEX(PRESUPUESTO!$B$10:$B$174,MATCH($A59,PRESUPUESTO!$A$10:$A$174,0)),"⚠ clave no existe"))} | M59: {=IF($A59="","",IFERROR(INDEX(PRESUPUESTO!$C$10:$C$262,MATCH($A59,PRESUPUESTO!$A$10:$A$262,0)),""))} | N59: =IF($A59="","",IFERROR(SUMIF($A$10:$A$509,$A59,$I$10:$I$509)-$M59,""))
B60: {=IF($A60="","",IFERROR(INDEX(PRESUPUESTO!$N$10:$N$262,MATCH($A60,PRESUPUESTO!$A$10:$A$262,0)),""))} | J60: {=IF($A60="","",IFERROR(INDEX(PRESUPUESTO!$D$10:$D$174,MATCH($A60&"|"&$B60,PRESUPUESTO!$O$10:$O$174,0)),"⚠"))} | K60: {=IF($A60="","",IFERROR(INDEX(PRESUPUESTO!$C$10:$C$174,MATCH($A60&"|"&$B60,PRESUPUESTO!$O$10:$O$174,0)),""))} | L60: {=IF($A60="","",IFERROR(INDEX(PRESUPUESTO!$B$10:$B$174,MATCH($A60,PRESUPUESTO!$A$10:$A$174,0)),"⚠ clave no existe"))} | M60: {=IF($A60="","",IFERROR(INDEX(PRESUPUESTO!$C$10:$C$262,MATCH($A60,PRESUPUESTO!$A$10:$A$262,0)),""))} | N60: =IF($A60="","",IFERROR(SUMIF($A$10:$A$509,$A60,$I$10:$I$509)-$M60,""))
B61: {=IF($A61="","",IFERROR(INDEX(PRESUPUESTO!$N$10:$N$262,MATCH($A61,PRESUPUESTO!$A$10:$A$262,0)),""))} | J61: {=IF($A61="","",IFERROR(INDEX(PRESUPUESTO!$D$10:$D$174,MATCH($A61&"|"&$B61,PRESUPUESTO!$O$10:$O$174,0)),"⚠"))} | K61: {=IF($A61="","",IFERROR(INDEX(PRESUPUESTO!$C$10:$C$174,MATCH($A61&"|"&$B61,PRESUPUESTO!$O$10:$O$174,0)),""))} | L61: {=IF($A61="","",IFERROR(INDEX(PRESUPUESTO!$B$10:$B$174,MATCH($A61,PRESUPUESTO!$A$10:$A$174,0)),"⚠ clave no existe"))} | M61: {=IF($A61="","",IFERROR(INDEX(PRESUPUESTO!$C$10:$C$262,MATCH($A61,PRESUPUESTO!$A$10:$A$262,0)),""))} | N61: =IF($A61="","",IFERROR(SUMIF($A$10:$A$509,$A61,$I$10:$I$509)-$M61,""))
B62: {=IF($A62="","",IFERROR(INDEX(PRESUPUESTO!$N$10:$N$262,MATCH($A62,PRESUPUESTO!$A$10:$A$262,0)),""))} | J62: {=IF($A62="","",IFERROR(INDEX(PRESUPUESTO!$D$10:$D$174,MATCH($A62&"|"&$B62,PRESUPUESTO!$O$10:$O$174,0)),"⚠"))} | K62: {=IF($A62="","",IFERROR(INDEX(PRESUPUESTO!$C$10:$C$174,MATCH($A62&"|"&$B62,PRESUPUESTO!$O$10:$O$174,0)),""))} | L62: {=IF($A62="","",IFERROR(INDEX(PRESUPUESTO!$B$10:$B$174,MATCH($A62,PRESUPUESTO!$A$10:$A$174,0)),"⚠ clave no existe"))} | M62: {=IF($A62="","",IFERROR(INDEX(PRESUPUESTO!$C$10:$C$262,MATCH($A62,PRESUPUESTO!$A$10:$A$262,0)),""))} | N62: =IF($A62="","",IFERROR(SUMIF($A$10:$A$509,$A62,$I$10:$I$509)-$M62,""))
B63: {=IF($A63="","",IFERROR(INDEX(PRESUPUESTO!$N$10:$N$262,MATCH($A63,PRESUPUESTO!$A$10:$A$262,0)),""))} | J63: {=IF($A63="","",IFERROR(INDEX(PRESUPUESTO!$D$10:$D$174,MATCH($A63&"|"&$B63,PRESUPUESTO!$O$10:$O$174,0)),"⚠"))} | K63: {=IF($A63="","",IFERROR(INDEX(PRESUPUESTO!$C$10:$C$174,MATCH($A63&"|"&$B63,PRESUPUESTO!$O$10:$O$174,0)),""))} | L63: {=IF($A63="","",IFERROR(INDEX(PRESUPUESTO!$B$10:$B$174,MATCH($A63,PRESUPUESTO!$A$10:$A$174,0)),"⚠ clave no existe"))} | M63: {=IF($A63="","",IFERROR(INDEX(PRESUPUESTO!$C$10:$C$262,MATCH($A63,PRESUPUESTO!$A$10:$A$262,0)),""))} | N63: =IF($A63="","",IFERROR(SUMIF($A$10:$A$509,$A63,$I$10:$I$509)-$M63,""))
B64: {=IF($A64="","",IFERROR(INDEX(PRESUPUESTO!$N$10:$N$262,MATCH($A64,PRESUPUESTO!$A$10:$A$262,0)),""))} | J64: {=IF($A64="","",IFERROR(INDEX(PRESUPUESTO!$D$10:$D$174,MATCH($A64&"|"&$B64,PRESUPUESTO!$O$10:$O$174,0)),"⚠"))} | K64: {=IF($A64="","",IFERROR(INDEX(PRESUPUESTO!$C$10:$C$174,MATCH($A64&"|"&$B64,PRESUPUESTO!$O$10:$O$174,0)),""))} | L64: {=IF($A64="","",IFERROR(INDEX(PRESUPUESTO!$B$10:$B$174,MATCH($A64,PRESUPUESTO!$A$10:$A$174,0)),"⚠ clave no existe"))} | M64: {=IF($A64="","",IFERROR(INDEX(PRESUPUESTO!$C$10:$C$262,MATCH($A64,PRESUPUESTO!$A$10:$A$262,0)),""))} | N64: =IF($A64="","",IFERROR(SUMIF($A$10:$A$509,$A64,$I$10:$I$509)-$M64,""))
... B509: {=IF($A509="","",IFERROR(INDEX(PRESUPUESTO!$N$10:$N$262,MATCH($A509,PRESUPUESTO!$A$10:$A$262,0)),""))} | J509: {=IF($A509="","",IFERROR(INDEX(PRESUPUESTO!$D$10:$D$174,MATCH($A509&"|"&$B509,PRESUPUESTO!$O$10:$O$174,0)),"⚠"))} | K509: {=IF($A509="","",IFERROR(INDEX(PRESUPUESTO!$C$10:$C$174,MATCH($A509&"|"&$B509,PRESUPUESTO!$O$10:$O$174,0)),""))} | L509: {=IF($A509="","",IFERROR(INDEX(PRESUPUESTO!$B$10:$B$174,MATCH($A509,PRESUPUESTO!$A$10:$A$174,0)),"⚠ clave no existe"))} | M509: {=IF($A509="","",IFERROR(INDEX(PRESUPUESTO!$C$10:$C$262,MATCH($A509,PRESUPUESTO!$A$10:$A$262,0)),""))} | N509: =IF($A509="","",IFERROR(SUMIF($A$10:$A$509,$A509,$I$10:$I$509)-$M509,""))

Sheet COMPARATIVO V10
A1: REVISIÓN MANUAL DE REDACCIÓN · V10 vs V11 ACTUALIZADO
A2: NADA DE ESTO SE MODIFICÓ. Compara, decide, y escribe tu decisión en la última columna.
A3: Verificación: el V11 ACTUALIZADO conserva íntegras las 157 redacciones de tu V11 REAL. 0 cambios.
A5: CLAVE | B5: MÓD | C5: SIMILITUD | D5: FILA V11 | E5: REDACCIÓN V10 | F5: REDACCIÓN V11 ACTUAL | G5: NOTA QUE TENÍAS EN V10 | H5: TU DECISIÓN
A6: CIM04005 | B6: M2 | C6: 0.44150943 | D6: 53 | E6: SUMINISTRO Y APLICACIÓN DE IMPERMEABILIZANTE EN MUROS COLINDANTES A BASE DE EMULSIÓN ASFÁLTICA FIBRATADA APLICADA CON CEPILLO EN DOS CAPAS EN MUROS COLINDANTES EXISTENTES PREVIOS AL SANGRADO DE HUMEDADES. INCLUYE MATERIAL, HERRAMIENTA MENOR, MANO DE OBRA Y EQUIPO DE PROTECCIÓN PERSONAL. | F6: SUMINISTRO Y APLICACIÓN DE IMPERMEABILIZANTE EN MUROS COLINDANTES EXISTENTES A BASE DE EMULSIÓN ASFÁLTICA FIBRATADA APLICADA FIBRATADA CON CEPILLO EN DOS CAPAS. INCLUYE MATERIAL, HERRAMIENTA MENOR, MANO DE OBRA Y EQUIPO DE PROTECCIÓN PERSONAL. | G6: SE CORRIJE S EQUITA EL CARTON, Y SE BAJA EL P[RECIO, HABRA QUE EXPLICAR POR QUE ESE DISPARO DEL PRECIO SI LO TENIA,MOS DIFERENTE EN EL ULTIMO PRESUPUESTO
A7: ELE12101 | B7: M2 | C7: 0.45372051 | D7: 68 | E7: OPCIÓN B · PREPARACIÓN VERTICAL ELÉCTRICA PARA NIVEL FUTURO: TUBERÍA CONDUIT AHOGADA CON GUÍA DE NYLON Y REGISTRO DE PASO, DEJANDO PUNTA IDENTIFICADA SOBRE EL NIVEL DE LOSA. INCLUYE MATERIAL, HERRAMIENTA MENOR, MANO DE OBRA Y EQUIPO DE PROTECCIÓN PERSONAL. · CLAVE PROVISIONAL — la definitiva la genera bulk-import.mjs al cargar el concepto al catálogo global. | F7: SALIDA ELÉCTRICA PARA CONTACTOS CON TUBERÍA DE POLIFLEX DE 3/4", CABLEADO DEL #10 Y #12, CHALUPA Y CONEXIÓN. INCLUYE MATERIAL, HERRAMIENTA MENOR, MANO DE OBRA Y EQUIPO DE PROTECCIÓN PERSONAL.
A8: ALB08236 | B8: M6 | C8: 0.53621347 | D8: 216 | E8: OPCIÓN B · ARRANQUES DE COLUMNA PARA NIVEL FUTURO: BASTONES DE VARILLA SALIENTES EN CADA COLUMNA A LA LONGITUD DE TRASLAPE DE TABLA, DOBLADOS Y PROTEGIDOS CON LECHADA DE CEMENTO Y FUNDA DE POLIETILENO. INCLUYE HABILITADO, COLOCACIÓN, PROTECCIÓN, HERRAMIENTA MENOR, MANO DE OBRA Y EQUIPO DE PROTECCIÓN PERSONAL. · La estructura está calculada para 3 niveles: el crecimiento NO requiere recálculo. CLAVE PROVISIONAL — la definitiva la genera bulk-import.mjs al cargar el concepto al catálogo global. | F8: OPCIÓN B · ARRANQUES DE COLUMNA Y ESPERAS DE CASTILLO PARA NIVEL FUTURO: BASTONES DE VARILLA SALIENTES A LA LONGITUD DE TRASLAPE DE TABLA, DOBLADOS Y PROTEGIDOS CON LECHADA DE CEMENTO Y FUNDA DE POLIETILENO. INCLUYE MATERIAL, HERRAMIENTA MENOR, MANO DE OBRA Y EQUIPO DE PROTECCIÓN PERSONAL.
A9: ALB08211 | B9: M2 | C9: 0.55291577 | D9: 57 | E9: FIRME DE CONCRETO CON ACABADO ESCOBILLADO Y CON PENDIENTE PARA DESAGUE PLUVIAL DE 0.10 M DE ESPESOR F'C=150 KG/CM², AGREGADO MÁXIMO DE 3/4", CON MALLA ELECTROSOLDADA. INCLUYE CIMBRADO, MATERIAL, REGLEADO, CURADO, HERRAMIENTA MENOR, MANO DE OBRA Y EQUIPO DE PROTECCIÓN PERSONAL. | F9: ACABADO CEPILLADO EN ÁREA DE PATIO DE SERVICIO (ZONA DE BOILER), CON PENDIENTE HACIA LA BAJADA PLUVIAL. INCLUYE MATERIAL, HERRAMIENTA MENOR, MANO DE OBRA Y EQUIPO DE PROTECCIÓN PERSONAL. | G9: ESTE CONCEPTO ES CON OTRA INTENCION SE MODIFICA POR QUE HAUY PARTES DE LA CASA COMO EL PEQUENO PATIO DONDE IRA EL BOILER PARA DAR PENDIENTE A LA BAJADA PLUVIAL, REVISAR EN PLANO SANITARIO REV 3
A10: ALB08219 | B10: M2 | C10: 0.5648855 | D10: 66 | E10: MURO DE BLOCK ESTRUCTURAL DE CONCRETO ASENTADO CON MORTERO 1:2:7 A PLOMO Y NIVEL, CON REFUERZO DE MALLA DE GALLINERO Y MEZCLA RECORTADA POR AMBAS CARAS. INCLUYE MATERIAL, REFUERZO, HERRAMIENTA MENOR, MANO DE OBRA Y EQUIPO DE PROTECCIÓN PERSONAL. | F10: MURO DE BLOCK ESTRUCTURAL DE CONCRETO ASENTADO CON MORTERO A PLOMO Y NIVEL, CON REFUERZO DE MALLA DE GALLINERO POR AMBAS CARAS. INCLUYE MATERIAL, REFUERZO Y HERRAMIENTA MENOR. NO INCLUYE APLANADO. INCLUYE MATERIAL, HERRAMIENTA MENOR, MANO DE OBRA Y EQUIPO DE PROTECCIÓN PERSONAL.
A11: CIM04004 | B11: M2 | C11: 0.64947245 | D11: 52 | E11: CIMENTACION CON LOSA DE 15 CM DE ESPESOR CON PARRILLA DE ACERO EN AMBOS LECHOS, MALLA ELECTROSOLDADA 6X6 4X4 Y BASTONES DE 3/8" @ 20 CM SEGÚN DESPIECE DEL PLANO ESTRUCTURAL, CT-1 CONTRATRABE CENTRAL Y PERIMETRAL DE 20X40 CM, CON CONCRETO F'C=250 KG/CM². INCLUYE HABILITADO Y ARMADO, SILLETAS, CIMBRA PERIMETRAL Y DES CIMBRADO, COLADO, REGLEADO, CURADO, HERRAMIENTA MENOR, MANO DE OBRA Y EQUIPO DE PROTECCIÓN PERSONAL. | F11: LOSA DE CIMENTACIÓN CON CONTRATRABES INTEGRADAS: LOSA DE 15 CM DE ESPESOR CON PARRILLA EN AMBOS LECHOS, MALLA ELECTROSOLDADA 6-6/4-4 Y BASTONES DE 3/8" A CADA 20 CM; CONTRATRABE CENTRAL Y PERIMETRAL DE 20 X 40 CM, TODO CON CONCRETO F'C=250 KG/CM². INCLUYE HABILITADO Y ARMADO DE ACERO, SILLETAS, CIMBRA, DESCIMBRADO, COLADO, REGLEADO, VIBRADO Y CURADO. INCLUYE MATERIAL, HERRAMIENTA MENOR, MANO DE OBRA Y EQUIPO DE PROTECCIÓN PERSONAL. | G11: TODAS LAS NOTAS QUE AGREGASTE A CADA CONCEPTO DEBERAN IR AQUI EN ESTA COLIUMNA, FORMATO CONDICIONAL AQUI NO FUNCIONA
A12: ARR06009 | B12: M1 | C12: 0.6519945 | D12: 41 | E12: VIAJE DE ESCOMBRO A TIRO AUTORIZADO: RETIRO DEL ESCOMBRO EN CAMIÓN DE VOLTEO CON CAPACIDAD DE TOLVA DE 6 M³, HASTA TIRO AUTORIZADO, CON DISPOSICIÓN LEGAL DEL RESIDUO. INCLUYE RENTA DEL CAMIÓN, COMBUSTIBLE, OPERADOR Y DERECHO DE DESCARGA. · No incluye la carga al camión, que está considerada en el concepto de acarreo. Los viajes se estiman con base en el volumen de escombro calculado; en caso de generarse excedentes, se reportarán y facturarán conforme a los viajes realmente ejecutados. | F12: VIAJE DE ESCOMBRO A TIRO AUTORIZADO: RETIRO DEL ESCOMBRO EN CAMIÓN DE VOLTEO CON CAPACIDAD DE TOLVA DE 6 M³, HASTA TIRO AUTORIZADO, CON DISPOSICIÓN LEGAL DEL RESIDUO. INCLUYE RENTA DEL CAMIÓN, COMBUSTIBLE, OPERADOR Y DERECHO DE DESCARGA.
A13: PRE02226 | B13: M2 | C13: 0.65437788 | D13: 50 | E13: SUMINISTRO Y COLOCACIÓN DE CAPA DE POLIETILENO NEGRO CALIBRE 600 A MANERA DE PLANTILLA ENTRE EL TERRENO MEJORADO Y LA LOSA DE CIMENTACIÓN NUEVA, PARA RECIBIR LA PARRILLA Y EL CONCRETO POSTERIOR. INCLUYE MATERIAL, TRASLAPES, HERRAMIENTA MENOR, MANO DE OBRA Y EQUIPO DE PROTECCIÓN PERSONAL. | F13: SUMINISTRO Y COLOCACIÓN DE CAPA DE POLIETILENO NEGRO CALIBRE 600 A MANERA DE PLANTILLA ENTRE EL TERRENO MEJORADO Y LA LOSA DE CIMENTACIÓN NUEVA PARA RECIBIR LA PARRILLA Y EL CONCRETO POSTERIOR, INCLUYE EL FORRADO DE LOS TRES MUROS COLINDANTES HASTA 1.20 M SOBRE EL NIVEL DEL MURO. INCLUYE MATERIAL, HERRAMIENTA MENOR, MANO DE OBRA Y EQUIPO DE PROTECCIÓN PERSONAL. | G13: pu corregido 25 sin utilidad, se considera forrar hasta peralre de plantilla mas 1.20 sobre muro colondante que son tres los dos laterales y el colundante trasero
A14: HRR10003 | B14: M6 | C14: 0.65994236 | D14: 220 | E14: OPCIÓN B · CUBIERTA LIGERA PROVISIONAL DE CUBO DE ESCALERA A BASE DE ESTRUCTURA METÁLICA Y LÁMINA, CON PENDIENTE Y GOTEO. INCLUYE HABILITADO, SOLDADURA, ANCLAJES, LÁMINA, SELLADO, HERRAMIENTA, MANO DE OBRA Y EQUIPO DE PROTECCIÓN PERSONAL. · Superficie pendiente de la lámina AZ2 del arquitectónico REV.03. CLAVE PROVISIONAL — la definitiva la genera bulk-import.mjs al cargar el concepto al catálogo global. | F14: OPCIÓN B · CUBIERTA LIGERA PROVISIONAL DE CUBO DE ESCALERA Y DE CUBO DE LAVANDERÍA A BASE DE ESTRUCTURA METÁLICA Y LÁMINA, CON PENDIENTE Y GOTEO. INCLUYE HABILITADO, SOLDADURA, ANCLAJES, LÁMINA Y SELLADO. INCLUYE MATERIAL, HERRAMIENTA MENOR, MANO DE OBRA Y EQUIPO DE PROTECCIÓN PERSONAL.
A15: ARR06014 | B15: M4 | C15: 0.66774194 | D15: 204 | E15: ACARREO VERTICAL DE MATERIAL A NIVEL SUPERIOR: ELEVACIÓN MANUAL DE MATERIAL A PIE DE OBRA DESDE PLANTA BAJA HASTA EL NIVEL DE TRABAJO. INCLUYE HERRAMIENTA MENOR, ANDAMIO, MANO DE OBRA Y EQUIPO DE PROTECCIÓN PERSONAL. · Este concepto es el que hace que un nivel NO sea idéntico a otro. CLAVE PROVISIONAL — la definitiva la genera bulk-import.mjs al cargar el concepto al catálogo global. | F15: ACARREO VERTICAL DE MATERIAL A NIVEL SUPERIOR: ELEVACIÓN MANUAL DE MATERIAL A PIE DE OBRA DESDE PLANTA BAJA HASTA EL NIVEL DE TRABAJO. INCLUYE ANDAMIO. INCLUYE MATERIAL, HERRAMIENTA MENOR, MANO DE OBRA Y EQUIPO DE PROTECCIÓN PERSONAL. | G15: ESTO DEBERIA AUIDAR A SER REFUERZO PARA CADA CONCEPTO A PARTIR DE 3 METROS DE ALTURA.
A16: ALB08224 | B16: M3 | C16: 0.67332382 | D16: 128 | E16: LOSA DE ENTREPISO DE VIGUETA Y BOVEDILLA C/A DE 25 CM DE PERALTE, CON CAPA DE COMPRESIÓN DE 5 CM, MALLA ELECTROSOLDADA 6-6/8-8 Y CONCRETO F'C=250 KG/CM². INCLUYE VIGUETA ARMADA, BOVEDILLA, APUNTALAMIENTO, CIMBRA DE ORILLA, DES CIMBRADO, ACARREO Y ELEVACIÓN DE MATERIAL, COLADO, CURADO, HERRAMIENTA MENOR, MANO DE OBRA Y EQUIPO DE PROTECCIÓN PERSONAL. | F16: LOSA DE ENTREPISO DE VIGUETA Y BOVEDILLA DE 25 CM DE PERALTE, CON CAPA DE COMPRESIÓN DE 5 CM, MALLA ELECTROSOLDADA 6-6/8-8 Y CONCRETO F'C=250 KG/CM². INCLUYE VIGUETA ARMADA, BOVEDILLA, APUNTALAMIENTO, CIMBRA DE ORILLA, ACARREO Y ELEVACIÓN DE MATERIAL, COLADO Y CURADO. INCLUYE MATERIAL, HERRAMIENTA MENOR, MANO DE OBRA Y EQUIPO DE PROTECCIÓN PERSONAL. | G16: CONCEPTO FINAL
A17: ALB08238 | B17: M6 | C17: 0.67524116 | D17: 217 | E17: GÁRGOLA DE DESAGÜE DE LOSA DE AZOTEA CON SALIDA A BAJADA PLUVIAL, INCLUYE FORMACIÓN DE PENDIENTE LOCAL, PIEZA, SELLADO Y REMATE. INCLUYE MATERIAL, HERRAMIENTA MENOR, MANO DE OBRA Y EQUIPO DE PROTECCIÓN PERSONAL. · BAP1 y BAP2 identificadas en la lámina AZ del arquitectónico REV.03. CLAVE PROVISIONAL — la definitiva la genera bulk-import.mjs al cargar el concepto al catálogo global. | F17: SUMINISTRO Y COLOCACIÓN DE GÁRGOLA DE DESAGÜE DE LOSA DE AZOTEA CON SALIDA A BAJADA PLUVIAL. INCLUYE FORMACIÓN DE PENDIENTE LOCAL, PIEZA, SELLADO Y REMATE. INCLUYE MATERIAL, HERRAMIENTA MENOR, MANO DE OBRA Y EQUIPO DE PROTECCIÓN PERSONAL.
A18: ALB08226 | B18: M3 | C18: 0.69090909 | D18: 129 | E18: LOSA MACIZA DE CONCRETO ARMADO DE 10 CM DE ESPESOR F'C=250 KG/CM², EN ZONA DE DESCANSO DE ESCALERA Y ÁREAS PARTICULARES. INCLUYE HABILITADO Y ARMADO DE ACERO, CIMBRA DE FONDO, APUNTALAMIENTO, COLADO, REGLEADO, CURADO, HERRAMIENTA MENOR, MANO DE OBRA Y EQUIPO DE PROTECCIÓN PERSONAL. · ES-07. CLAVE PROVISIONAL — la definitiva la genera bulk-import.mjs al cargar el concepto al catálogo global. | F18: LOSA MACIZA DE CONCRETO ARMADO DE 10 CM DE ESPESOR CON PARRILLA DEL #3 A CADA 25 CM Y CONCRETO F'C=250 KG/CM², EN ZONA DE DESCANSO DE ESCALERA Y BAÑO. INCLUYE HABILITADO Y ARMADO, CIMBRA DE FONDO, APUNTALAMIENTO, COLADO, REGLEADO Y CURADO. INCLUYE MATERIAL, HERRAMIENTA MENOR, MANO DE OBRA Y EQUIPO DE PROTECCIÓN PERSONAL. | G18: CONCEPTO FINAL
A19: ALB08218 | B19: M2 | C19: 0.69846678 | D19: 65 | E19: MC-2 MURO DE CONCRETO ARMADO COLADO EN SITIO DE 15 CM DE ESPESOR, ARMADO SEGÚN DESPIECE DEL PLANO ESTRUCTURAL, CON CONCRETO F'C=250 KG/CM². INCLUYE HABILITADO Y ARMADO DE ACERO, CIMBRA A DOS CARAS, COLADO, VIBRADO, CURADO, HERRAMIENTA MENOR, MANO DE OBRA Y EQUIPO DE PROTECCIÓN PERSONAL. | F19: MC-2 MURO DE CONCRETO ARMADO DOBLE DE 1.30 X 0.20 M CON DOS COLUMNAS TIPO C Y ACERO DE REFUERZO DE 3/8", CON CONCRETO F'C=250 KG/CM². INCLUYE HABILITADO Y ARMADO DE ACERO, CIMBRA A DOS CARAS, COLADO, VIBRADO Y CURADO. INCLUYE MATERIAL, HERRAMIENTA MENOR, MANO DE OBRA Y EQUIPO DE PROTECCIÓN PERSONAL. | G19: FORMATO CONDICIONAL NO SE POR QUE SE VE TODO ROSA, REVISAR EN TODOS QUE YA ESTAN COMPLETOS POR QUE SE VE ROSA
A20: HRR10001 | B20: M6 | C20: 0.69852105 | D20: 219 | E20: OPCIÓN B · ESTRUCTURA METÁLICA PROVISIONAL PARA BASE DE TINACO SOBRE CUBO DE ESCALERA: BASTIDOR DE PERFIL TUBULAR ESTRUCTURAL CON PLACAS DE APOYO ANCLADAS A LA LOSA, ALTURA DE PROYECTO, CON ACABADO ANTICORROSIVO. INCLUYE HABILITADO, SOLDADURA, ANCLAJES, ELEVACIÓN, MONTAJE, PINTURA, HERRAMIENTA, MANO DE OBRA Y EQUIPO DE PROTECCIÓN PERSONAL. · Desmontable y reutilizable cuando se construya el nivel futuro. CLAVE PROVISIONAL — la definitiva la genera bulk-import.mjs al cargar el concepto al catálogo global. | F20: OPCIÓN B · ESTRUCTURA METÁLICA PROVISIONAL PARA BASE DE TINACO SOBRE CUBO DE ESCALERA Y SOBRE CUBO DE LAVANDERÍA: BASTIDOR DE PERFIL TUBULAR ESTRUCTURAL CON PLACAS DE APOYO ANCLADAS A LA LOSA Y ACABADO ANTICORROSIVO. INCLUYE HABILITADO, SOLDADURA, ANCLAJES, ELEVACIÓN, MONTAJE Y PINTURA. INCLUYE MATERIAL, HERRAMIENTA MENOR, MANO DE OBRA Y EQUIPO DE PROTECCIÓN PERSONAL.
A21: ALB08222 | B21: M3 | C21: 0.70671378 | D21: 126 | E21: T-4 DE FACHADA: TRABE DE SECCIÓN 20 X 25 CM ARMADA SEGÚN DESPIECE DEL PLANO ESTRUCTURAL, CON CONCRETO F'C=250 KG/CM². INCLUYE HABILITADO Y ARMADO DE ACERO, CIMBRA Y DESCIMBRA, APUNTALAMIENTO, COLADO, VIBRADO, CURADO, HERRAMIENTA MENOR, MANO DE OBRA Y EQUIPO DE PROTECCIÓN PERSONAL. | F21: TRABE T-4 DE SECCIÓN 20 X 25 CM CON 4 VARILLAS DE 1/2", TRABE DE FACHADA, CON CONCRETO F'C=250 KG/CM². INCLUYE HABILITADO Y ARMADO DE ACERO, CIMBRA Y DESCIMBRA, APUNTALAMIENTO, COLADO, VIBRADO Y CURADO. INCLUYE MATERIAL, HERRAMIENTA MENOR, MANO DE OBRA Y EQUIPO DE PROTECCIÓN PERSONAL. | G21: ESTA ES EL CONCEPTO FINAL PARA ESTA TRABE TIPO
A22: ARR6013 | B22: M1 | C22: 0.75186104 | D22: 40 | E22: ACARREO DEL ESCOMBRO DESDE EL CENTRO DE ACOPIO DENTRO DEL TAPIAL HASTA EL CAMIÓN DE VOLTEO A PIE DE CALLE, EN UN TRAMO APROXIMADO DE 25 METROS LINEALES POR EL PASO DE SERVIDUMBRE, INCLUYENDO LA CARGA MANUAL AL CAMIÓN. INCLUYE CARRETILLAS, HERRAMIENTA MENOR, MANO DE OBRA Y EQUIPO DE PROTECCIÓN PERSONAL. · Volumen suelto, con factor de abundamiento de 1.35 para demolición y 1.25 para material de excavación. El paso de servidumbre de 3.00 m impide el uso de maquinaria, por lo que el acarreo es manual. | F22: ACARREO DEL ESCOMBRO DESDE EL CENTRO DE ACOPIO DENTRO DEL TAPIAL HASTA EL CAMIÓN DE VOLTEO A PIE DE CALLE, EN UN TRAMO APROXIMADO DE 25 METROS LINEALES POR EL PASO DE SERVIDUMBRE, INCLUYENDO LA CARGA MANUAL AL CAMIÓN. INCLUYE CARRETILLAS, HERRAMIENTA MENOR, MANO DE OBRA Y EQUIPO DE PROTECCIÓN PERSONAL.
A23: EXV3019 | B23: M1 | C23: 0.75494071 | D23: 44 | E23: NIVELACIÓN DEL TERRENO CON MEJORAMIENTO A BASE DE TEPETATE COMPACTADO AL 90% PROCTOR, APISONADO CON BAILARINA, HASTA ALCANZAR EL NIVEL DE DESPLANTE DE PROYECTO. INCLUYE EL TALUD EN CARTABÓN DE LAS CONTRATRABES DE CIMENTACIÓN, SUMINISTRO Y TENDIDO DEL TEPETATE, RENTA DE BAILARINA, COMBUSTIBLE, AGUA PARA COMPACTACIÓN, HERRAMIENTA MENOR, MANO DE OBRA Y EQUIPO DE PROTECCIÓN PERSONAL. · Aplica únicamente en la zona del patio exterior (29.26 m²), donde se demolió el concreto pobre. En la zona de la vivienda no aplica: la losa de cimentación nueva se cuela sobre la losa existente con membrana de polietileno cal. 600 de por medio. | F23: NIVELACIÓN DEL TERRENO CON MEJORAMIENTO A BASE DE TEPETATE COMPACTADO AL 90% PROCTOR, APISONADO CON BAILARINA, HASTA ALCANZAR EL NIVEL DE DESPLANTE DE PROYECTO. INCLUYE EL TALUD EN CARTABÓN DE LAS CONTRATRABES DE CIMENTACIÓN, SUMINISTRO Y TENDIDO DEL TEPETATE, RENTA DE BAILARINA, COMBUSTIBLE, AGUA PARA COMPACTACIÓN, HERRAMIENTA MENOR, MANO DE OBRA Y EQUIPO DE PROTECCIÓN PERSONAL.
A24: ALB08223 | B24: M3 | C24: 0.75638051 | D24: 127 | E24: CADENA DE CERRAMIENTO CR DE SECCIÓN 15 X 27 CM ARMADA CON ARMEX, CON CONCRETO F'C=250 KG/CM². INCLUYE HABILITADO, CIMBRA, COLADO, CURADO, HERRAMIENTA MENOR, MANO DE OBRA Y EQUIPO DE PROTECCIÓN PERSONAL. | F24: CADENA DE CERRAMIENTO CR ARMADA CON ARMEX 15 X 25 MÁS 2 VARILLAS DEL #3, CON CONCRETO F'C=250 KG/CM². INCLUYE HABILITADO, CIMBRA, COLADO Y CURADO. INCLUYE MATERIAL, HERRAMIENTA MENOR, MANO DE OBRA Y EQUIPO DE PROTECCIÓN PERSONAL. | G24: ESTA ES EL CONCEPTO FINAL PARA ESTOS CERRAMIENTOS
A25: ALB08234 | B25: M6 | C25: 0.75974026 | D25: 215 | E25: OPCIÓN B · TAPA PROVISIONAL DE HUECO DE ESCALERA: BASTIDOR DE MADERA ANCLADO AL BORDE DE LOSA CON SELLADO PERIMETRAL, RETIRABLE SIN DAÑAR EL ARMADO DE CONTINUIDAD. INCLUYE MATERIAL, HERRAJES, SELLADOR, HERRAMIENTA MENOR, MANO DE OBRA Y EQUIPO DE PROTECCIÓN PERSONAL. · CLAVE PROVISIONAL — la definitiva la genera bulk-import.mjs al cargar el concepto al catálogo global. | F25: OPCIÓN B · TAPA PROVISIONAL DE HUECO DE ESCALERA: BASTIDOR DE MADERA ANCLADO AL BORDE DE LOSA CON SELLADO PERIMETRAL, RETIRABLE SIN DAÑAR EL ARMADO DE CONTINUIDAD. INCLUYE MATERIAL, HERRAMIENTA MENOR, MANO DE OBRA Y EQUIPO DE PROTECCIÓN PERSONAL.
A26: PRE02225 | B26: M1 | C26: 0.76401565 | D26: 14 | E26: MURETE PROVISIONAL DE OBRA: FABRICACIÓN DE MURETE PROVISIONAL DE MADERA (POSTE, TABLA Y CLAVOS) ADOSADO AL TAPIAL, PARA ALOJAR EL INTERRUPTOR TERMOMAGNÉTICO DE OBRA Y EL RACK DE CONTACTOS DE USO RUDO. INCLUYE MATERIAL ELÉCTRICO, HERRAMIENTA MENOR, MANO DE OBRA Y EQUIPO DE PROTECCIÓN PERSONAL. · Se construye inmediatamente después del corte de la acometida eléctrica existente, como parte de la misma maniobra de desmantelamiento. Es la fuente de energía para toda la obra. | F26: MURETE PROVISIONAL DE OBRA: FABRICACIÓN DE MURETE PROVISIONAL DE MADERA (POSTE, TABLA Y CLAVOS) ADOSADO AL TAPIAL, PARA ALOJAR EL INTERRUPTOR TERMOMAGNÉTICO DE OBRA Y EL RACK DE CONTACTOS DE USO RUDO. INCLUYE MATERIAL ELÉCTRICO, HERRAMIENTA MENOR, MANO DE OBRA Y EQUIPO DE PROTECCIÓN PERSONAL.
A27: ALB08221 | B27: M3 | C27: 0.77031802 | D27: 122 | E27: TRABE T-1 DE SECCIÓN 15 X 25 CM ARMADA SEGÚN DESPIECE DEL PLANO ESTRUCTURAL, CON CONCRETO F'C=250 KG/CM². INCLUYE HABILITADO Y ARMADO DE ACERO, CIMBRA Y DESCIMBRA, APUNTALAMIENTO, COLADO, VIBRADO, CURADO, HERRAMIENTA MENOR, MANO DE OBRA Y EQUIPO DE PROTECCIÓN PERSONAL. | F27: TRABE T-1 DE SECCIÓN 15 X 25 CM CON 4 VARILLAS DEL #3 Y ESTRIBOS DEL #2 A CADA 20 CM, CON CONCRETO F'C=250 KG/CM². INCLUYE HABILITADO Y ARMADO DE ACERO, CIMBRA Y DESCIMBRA, APUNTALAMIENTO, COLADO, VIBRADO Y CURADO. INCLUYE MATERIAL, HERRAMIENTA MENOR, MANO DE OBRA Y EQUIPO DE PROTECCIÓN PERSONAL. | G27: ESTA ES EL CONCEPTO FINAL PARA ESTA TRABE TIPO
A28: DEM5028 | B28: M1 | C28: 0.79958463 | D28: 32 | E28: CORTE DE LA LOSA DE PISO FIRME EXISTENTE, CON CORTADORA DE PISO TIPO WALK-BEHIND Y DISCO DE DIAMANTE PARA CONCRETO, SOBRE EL LÍMITE DE COLINDANCIA Y SOBRE EL TRAZO DE LAS TRINCHERAS CT-1 DE LA CIMENTACIÓN NUEVA. INCLUYE RENTA DE EQUIPO, DISCO DE CORTE, FLETE DE MAQUINARIA, HERRAMIENTA MENOR, MANO DE OBRA Y EQUIPO DE PROTECCIÓN PERSONAL CON PROTECCIÓN OCULAR, AUDITIVA Y RESPIRATORIA. · Se ejecuta en la misma vuelta de renta que el corte de azotea. La losa de piso existente se conserva; el corte solo la independiza de los muros compartidos y abre el trazo de las trincheras. | F28: CORTE DE LA LOSA DE PISO FIRME EXISTENTE, CON CORTADORA DE PISO TIPO WALK-BEHIND Y DISCO DE DIAMANTE PARA CONCRETO, SOBRE EL LÍMITE DE COLINDANCIA Y SOBRE EL TRAZO DE LAS TRINCHERAS CT-1 DE LA CIMENTACIÓN NUEVA. INCLUYE RENTA DE EQUIPO, DISCO DE CORTE, FLETE DE MAQUINARIA, HERRAMIENTA MENOR, MANO DE OBRA Y EQUIPO DE PROTECCIÓN PERSONAL CON PROTECCIÓN OCULAR, AUDITIVA Y RESPIRATORIA.
A29: ALB08216 | B29: M2 | C29: 0.80208333 | D29: 62 | E29: K-1 CASTILLO DE SECCIÓN 15 X 20 CM Y UNA ALTURA DE 2.50 M A NIVEL BAJO LECHO DE LOSA DE ENTREPISO ARMADO CON ARMEX 15-20-4, CON CONCRETO F'C=200 KG/CM². INCLUYE HABILITADO, CIMBRA, COLADO, VIBRADO, CURADO, HERRAMIENTA MENOR, MANO DE OBRA Y EQUIPO DE PROTECCIÓN PERSONAL. | F29: K-1 CASTILLO DE SECCIÓN 15 X 20 CM ARMADO CON ARMEX 15-20-4 MÁS 2 VARILLAS DEL #3, ALTURA DE 2.50 M A NIVEL BAJO LECHO DE LOSA DE ENTREPISO, CON CONCRETO F'C=250 KG/CM². INCLUYE HABILITADO, CIMBRA, COLADO, VIBRADO Y CURADO. INCLUYE MATERIAL, HERRAMIENTA MENOR, MANO DE OBRA Y EQUIPO DE PROTECCIÓN PERSONAL.
A30: ALB8209 | B30: M1 | C30: 0.80763984 | D30: 46 | E30: RELLENO COMPACTADO Y FIRME DE CONCRETO SOBRE LA RANURA DE LA LÍNEA SANITARIA NUEVA, PARA RESTITUIR EL PISO AL NIVEL EXISTENTE. INCLUYE RELLENO CON MATERIAL PRODUCTO DE LA EXCAVACIÓN COMPACTADO EN CAPAS, FIRME DE CONCRETO, MATERIAL, HERRAMIENTA MENOR, MANO DE OBRA Y EQUIPO DE PROTECCIÓN PERSONAL. · Se ejecuta después de probada la línea sanitaria nueva. Restituye el piso del paso de servidumbre para no dejar obstrucción a los vecinos. | F30: RELLENO COMPACTADO Y FIRME DE CONCRETO SOBRE LA RANURA DE LA LÍNEA SANITARIA NUEVA, PARA RESTITUIR EL PISO AL NIVEL EXISTENTE. INCLUYE RELLENO CON MATERIAL PRODUCTO DE LA EXCAVACIÓN COMPACTADO EN CAPAS, FIRME DE CONCRETO, MATERIAL, HERRAMIENTA MENOR, MANO DE OBRA Y EQUIPO DE PROTECCIÓN PERSONAL.
A31: ALB08215 | B31: M2 | C31: 0.81024096 | D31: 61 | E31: C-4 COLUMNA DE SECCIÓN 20 X 40 CM Y UNA ALTURA DE 2.50 M A NIVEL BAJO LECHO DE LOSA DE ENTREPISO ARMADA SEGÚN DESPIECE DEL PLANO ESTRUCTURAL, CON CONCRETO F'C=250 KG/CM². INCLUYE HABILITADO Y ARMADO DE ACERO, CIMBRA Y DESCIMBRA, COLADO, VIBRADO, CURADO, ANDAMIO, HERRAMIENTA MENOR, MANO DE OBRA Y EQUIPO DE PROTECCIÓN PERSONAL. | F31: C-4 COLUMNA DE SECCIÓN 20 X 40 CM CON 8 VARILLAS DEL #4 Y ESTRIBOS DEL #3, ALTURA DE 2.50 M A NIVEL BAJO LECHO DE LOSA DE ENTREPISO, CON CONCRETO F'C=250 KG/CM². INCLUYE HABILITADO Y ARMADO DE ACERO, CIMBRA Y DESCIMBRA, COLADO, VIBRADO, CURADO Y ANDAMIO. INCLUYE MATERIAL, HERRAMIENTA MENOR, MANO DE OBRA Y EQUIPO DE PROTECCIÓN PERSONAL. | G31: FORMATO CONDICIONAL NO SE POR QUE SE VE TODO ROSA, REVISAR EN TODOS QUE YA ESTAN COMPLETOS POR QUE SE VE ROSA
A32: HSI14093 | B32: M1 | C32: 0.81538462 | D32: 28 | E32: REUBICACIÓN Y RECONEXIÓN DE TINACOS DE CASA COLINDANTE: REUBICACIÓN Y RECONEXIÓN DE TINACO DE LA CASA COLINDANTE A LA LÍNEA HIDRÁULICA NUEVA. INCLUYE DESMONTAJE, TRASLADO, MONTAJE SOBRE SU BASE, FIJACIÓN CON ABRAZADERAS, CONEXIÓN FINAL A LA LÍNEA NUEVA, HERRAMIENTA MENOR, MANO DE OBRA Y EQUIPO DE PROTECCIÓN PERSONAL. · Precio unitario por lote. Corresponde a los 2 tinacos de la casa colindante inmediata. Los tinacos de los demás departamentos no se reubican. | F32: REUBICACIÓN Y RECONEXIÓN DE TINACOS DE CASA COLINDANTE: REUBICACIÓN Y RECONEXIÓN DE TINACO DE LA CASA COLINDANTE A LA LÍNEA HIDRÁULICA NUEVA. INCLUYE DESMONTAJE, TRASLADO, MONTAJE SOBRE SU BASE, FIJACIÓN CON ABRAZADERAS, CONEXIÓN FINAL A LA LÍNEA NUEVA, HERRAMIENTA MENOR, MANO DE OBRA Y EQUIPO DE PROTECCIÓN PERSONAL.
A33: HSI14095 | B33: M6 | C33: 0.82550336 | D33: 222 | E33: OPCIÓN B · PREPARACIÓN VERTICAL HIDROSANITARIA PARA NIVEL FUTURO: TRAMOS DE TUBERÍA AHOGADOS CON TAPÓN Y GUÍA, DEJANDO PUNTAS IDENTIFICADAS SOBRE EL NIVEL DE LOSA. INCLUYE MATERIAL, HERRAMIENTA MENOR, MANO DE OBRA Y EQUIPO DE PROTECCIÓN PERSONAL. · CLAVE PROVISIONAL — la definitiva la genera bulk-import.mjs al cargar el concepto al catálogo global. | F33: OPCIÓN B · PREPARACIÓN VERTICAL HIDROSANITARIA PARA NIVEL FUTURO: TRAMOS DE TUBERÍA AHOGADOS CON TAPÓN Y GUÍA, DEJANDO PUNTAS IDENTIFICADAS SOBRE EL NIVEL DE LOSA. INCLUYE MATERIAL, HERRAMIENTA MENOR, MANO DE OBRA Y EQUIPO DE PROTECCIÓN PERSONAL.
A34: DEM5030 | B34: M1 | C34: 0.82564679 | D34: 34 | E34: DEMOLICIÓN DE LA LOSA DE AZOTEA O CUBIERTA DE CONCRETO DE LA VIVIENDA, DE 12 CM DE ESPESOR, PREVIAMENTE CORTADA EN SU PERÍMETRO, CON MARTILLO DEMOLEDOR ELÉCTRICO. TRABAJOS A UNA ALTURA A PARTIR DE 3 METROS. INCLUYE LEVANTADO DEL ESCOMBRO Y SU ACOPIO DENTRO DE LA OBRA, RENTA DE EQUIPO, HERRAMIENTA MENOR, MANO DE OBRA, ANDAMIOS, ARNÉS Y EQUIPO DE PROTECCIÓN PERSONAL. · Se demuele de adentro hacia afuera, dejando intactos los muros compartidos. Corresponde a los 50.43 m² de la huella de la vivienda por 12 cm de espesor. | F34: DEMOLICIÓN DE LA LOSA DE AZOTEA O CUBIERTA DE CONCRETO DE LA VIVIENDA, DE 12 CM DE ESPESOR, PREVIAMENTE CORTADA EN SU PERÍMETRO, CON MARTILLO DEMOLEDOR ELÉCTRICO. TRABAJOS A UNA ALTURA A PARTIR DE 3 METROS. INCLUYE LEVANTADO DEL ESCOMBRO Y SU ACOPIO DENTRO DE LA OBRA, RENTA DE EQUIPO, HERRAMIENTA MENOR, MANO DE OBRA, ANDAMIOS, ARNÉS Y EQUIPO DE PROTECCIÓN PERSONAL.
A35: PRE02223 | B35: M1 | C35: 0.82704811 | D35: 12 | E35: TRAZO Y NIVELACIÓN DEL ÁREA A CONSTRUIR: TRAZO Y NIVELACIÓN DE PLATAFORMA SEGÚN LOS NIVELES DE DESPLANTE DEL PROYECTO, SOBRE LA TOTALIDAD DEL PREDIO DE CASA 2 (81.24 M² DE DESPLANTE). INCLUYE HILO, ESTACAS, CRUCETAS DE MADERA, NIVEL, EQUIPO TOPOGRÁFICO, HERRAMIENTA MENOR, MANO DE OBRA Y EQUIPO DE PROTECCIÓN PERSONAL. · Superficie de desplante del proyecto según cuadro de áreas del plano A-01. Se ejecuta después del tapial y antes de la demolición. | F35: TRAZO Y NIVELACIÓN DEL ÁREA A CONSTRUIR: TRAZO Y NIVELACIÓN DE PLATAFORMA SEGÚN LOS NIVELES DE DESPLANTE DEL PROYECTO, SOBRE LA TOTALIDAD DEL PREDIO DE CASA 2 (81.24 M² DE DESPLANTE). INCLUYE HILO, ESTACAS, CRUCETAS DE MADERA, NIVEL, EQUIPO TOPOGRÁFICO, HERRAMIENTA MENOR, MANO DE OBRA Y EQUIPO DE PROTECCIÓN PERSONAL. | G35: no me acuerdo
A36: ALB08213 | B36: M2 | C36: 0.83024691 | D36: 59 | E36: C-2 COLUMNA DE SECCIÓN 15 X 40 CM Y UNA ALTURA DE 2.50 M A NIVEL BAJO LECHO DE LOSA DE ENTREPISO. ARMADA SEGÚN DESPIECE DEL PLANO ESTRUCTURAL, CON CONCRETO F'C=250 KG/CM². INCLUYE HABILITADO Y ARMADO DE ACERO, CIMBRA Y DESCIMBRA, COLADO, VIBRADO, CURADO, ANDAMIO, HERRAMIENTA MENOR, MANO DE OBRA Y EQUIPO DE PROTECCIÓN PERSONAL. | F36: C-2 COLUMNA DE SECCIÓN 15 X 40 CM CON 4 VARILLAS DEL #4 Y ALTURA DE 2.50 M A NIVEL BAJO LECHO DE LOSA DE ENTREPISO, CON CONCRETO F'C=250 KG/CM². INCLUYE HABILITADO Y ARMADO DE ACERO, CIMBRA Y DESCIMBRA, COLADO, VIBRADO, CURADO Y ANDAMIO. INCLUYE MATERIAL, HERRAMIENTA MENOR, MANO DE OBRA Y EQUIPO DE PROTECCIÓN PERSONAL. | G36: FORMATO CONDICIONAL NO SE POR QUE SE VE TODO ROSA, REVISAR EN TODOS QUE YA ESTAN COMPLETOS POR QUE SE VE ROSA
A37: ALB08214 | B37: M2 | C37: 0.83153014 | D37: 60 | E37: C-3 COLUMNA DE SECCIÓN 20 X 20 CM Y UNA ALTURA DE 2.50 M A NIVEL BAJO LECHO DE LOSA DE ENTREPISO ARMADA SEGÚN DESPIECE DEL PLANO ESTRUCTURAL, CON CONCRETO F'C=250 KG/CM². INCLUYE HABILITADO Y ARMADO DE ACERO, CIMBRA Y DESCIMBRA, COLADO, VIBRADO, CURADO, ANDAMIO, HERRAMIENTA MENOR, MANO DE OBRA Y EQUIPO DE PROTECCIÓN PERSONAL. | F37: C-3 COLUMNA DE SECCIÓN 20 X 20 CM CON 4 VARILLAS DEL #4 Y ALTURA DE 2.50 M A NIVEL BAJO LECHO DE LOSA DE ENTREPISO, CON CONCRETO F'C=250 KG/CM². INCLUYE HABILITADO Y ARMADO DE ACERO, CIMBRA Y DESCIMBRA, COLADO, VIBRADO, CURADO Y ANDAMIO. INCLUYE MATERIAL, HERRAMIENTA MENOR, MANO DE OBRA Y EQUIPO DE PROTECCIÓN PERSONAL. | G37: FORMATO CONDICIONAL NO SE POR QUE SE VE TODO ROSA, REVISAR EN TODOS QUE YA ESTAN COMPLETOS POR QUE SE VE ROSA
A38: DEM5033 | B38: M1 | C38: 0.83705542 | D38: 37 | E38: DEMOLICIÓN Y RETIRO DE TINACOS DE FIBROCEMENTO (ASBESTO) EXISTENTES EN LA AZOTEA DE LA VIVIENDA A DEMOLER, CON HUMECTACIÓN PREVIA DE LA PIEZA PARA ABATIR LA EMISIÓN DE FIBRAS, EMBALAJE DEL RESIDUO EN PLÁSTICO DE CALIBRE GRUESO Y DISPOSICIÓN FINAL EN TIRADERO AUTORIZADO PARA RESIDUOS PELIGROSOS. TRABAJOS A UNA ALTURA A PARTIR DE 3 METROS. INCLUYE MATERIAL DE EMBALAJE, TRANSPORTE A TIRADERO AUTORIZADO, HERRAMIENTA MENOR, MANO DE OBRA, ANDAMIOS Y EQUIPO DE PROTECCIÓN PERSONAL CON PROTECCIÓN RESPIRATORIA. · Corresponde a los 2 tinacos de fibrocemento propios de la vivienda a demoler. Trabajo de riesgo especial: el residuo no puede mezclarse con el escombro común ni disponerse en tiradero municipal. | F38: DEMOLICIÓN Y RETIRO DE TINACOS DE FIBROCEMENTO (ASBESTO) EXISTENTES EN LA AZOTEA DE LA VIVIENDA A DEMOLER, CON HUMECTACIÓN PREVIA DE LA PIEZA PARA ABATIR LA EMISIÓN DE FIBRAS, EMBALAJE DEL RESIDUO EN PLÁSTICO DE CALIBRE GRUESO Y DISPOSICIÓN FINAL EN TIRADERO AUTORIZADO PARA RESIDUOS PELIGROSOS. TRABAJOS A UNA ALTURA A PARTIR DE 3 METROS. INCLUYE MATERIAL DE EMBALAJE, TRANSPORTE A TIRADERO AUTORIZADO, HERRAMIENTA MENOR, MANO DE OBRA, ANDAMIOS Y EQUIPO DE PROTECCIÓN PERSONAL CON PROTECCIÓN RESPIRATORIA.
A39: DEM5032 | B39: M1 | C39: 0.84730803 | D39: 36 | E39: RANURA EN EL PISO DE CONCRETO EXISTENTE EN PATIO, DE 40 CM DE ANCHO POR 60 CM DE PROFUNDIDAD, PARA ALOJAR LA LÍNEA SANITARIA NUEVA DE 4" QUE DA SERVICIO A CASA 2 (EL PROYECTO), CASA 3 Y CASA 4 SEGÚN CROQUIS DEL TÍTULO DE PROPIEDAD, FOLIO CATASTRAL CA 17/022. INCLUYE CORTE PREVIO, DEMOLICIÓN CON MARTILLO DEMOLEDOR ELÉCTRICO, LEVANTADO DEL ESCOMBRO PRODUCTO DEL CORTE Y SU ACOPIO DENTRO DE LA OBRA, RENTA DE EQUIPO, HERRAMIENTA MENOR, MANO DE OBRA Y EQUIPO DE PROTECCIÓN PERSONAL. · La línea sanitaria actual pasa por el frente de la vivienda y es compartida con los departamentos del fondo. La ranura aloja el trayecto nuevo que sustituye al existente. | F39: RANURA EN EL PISO DE CONCRETO EXISTENTE EN PATIO, DE 40 CM DE ANCHO POR 60 CM DE PROFUNDIDAD, PARA ALOJAR LA LÍNEA SANITARIA NUEVA DE 4" QUE DA SERVICIO A CASA 2 (EL PROYECTO), CASA 3 Y CASA 4 SEGÚN CROQUIS DEL TÍTULO DE PROPIEDAD, FOLIO CATASTRAL CA 17/022. INCLUYE CORTE PREVIO, DEMOLICIÓN CON MARTILLO DEMOLEDOR ELÉCTRICO, LEVANTADO DEL ESCOMBRO PRODUCTO DEL CORTE Y SU ACOPIO DENTRO DE LA OBRA, RENTA DE EQUIPO, HERRAMIENTA MENOR, MANO DE OBRA Y EQUIPO DE PROTECCIÓN PERSONAL.
A40: HSI14094 | B40: M1 | C40: 0.85109718 | D40: 29 | E40: SUMINISTRO E INSTALACIÓN DE TUBERÍA PVC SANITARIO DE 4" AHOGADA EN RANURA, CON SUS CONEXIONES, PARA LA LÍNEA SANITARIA NUEVA QUE DA SERVICIO A CASA 2 (EL PROYECTO), CASA 3 Y CASA 4 SEGÚN CROQUIS DEL TÍTULO DE PROPIEDAD, FOLIO CATASTRAL CA 17/022, SUSTITUYENDO EL TRAYECTO EXISTENTE QUE PASA POR EL FRENTE DE LA VIVIENDA. INCLUYE TUBERÍA, CODOS, YEES, TEES, PEGAMENTO, NIVELACIÓN DE PENDIENTE, MATERIAL, HERRAMIENTA MENOR, MANO DE OBRA Y EQUIPO DE PROTECCIÓN PERSONAL. REGISTRO SANITARIO DE 40 X 60 X 100 CM: FABRICACIÓN DE REGISTRO SANITARIO DEL PROYECTO. INCLUYE PLANTILLA DE CONCRETO SIMPLE F'C=150 KG/CM² DE 5 CM DE PERALTE, MUROS DE TABIQUE RECOCIDO DE 7 X 14 X 28 CM JUNTEADOS CON MORTERO CEMENTO-ARENA 1:4, APLANADO CON ACABADO PULIDO AL INTERIOR, VÉRTICES RESUELTOS EN CHAFLÁN A 45 GRADOS, ARENERO DE 5 CM BAJO EL LECHO INFERIOR DE LOS TUBOS DE 4" PARA RETENCIÓN DE SEDIMENTOS, TAPA DE REGISTRO DE LA MISMA CALIDAD QUE LA PLANTILLA, EXCAVACIÓN, MATERIAL, HERRAMIENTA MENOR, MANO DE OBRA Y EQUIPO DE PROTECCIÓN PERSONAL. R E S U M E N P O R PA R T I DAS PREPARACIÓN Y PRELIMINARES · Sustituye el trayecto actual que cruza frente a la vivienda. La pendiente se nivela hacia el registro nuevo. El arenero de 5 cm deja los tubos de 4" elevados respecto del fondo de la plantilla, de modo que los sedimentos se depositen en ese espacio y no obstruyan el lecho inferior interior del tubo. Los chaflanes a 45 grados en los vértices evitan la acumulación en esquinas. | F40: SUMINISTRO E INSTALACIÓN DE TUBERÍA PVC SANITARIO DE 4" AHOGADA EN RANURA, CON SUS CONEXIONES, PARA LA LÍNEA SANITARIA NUEVA QUE DA SERVICIO A CASA 2 (EL PROYECTO), CASA 3 Y CASA 4 SEGÚN CROQUIS DEL TÍTULO DE PROPIEDAD, FOLIO CATASTRAL CA 17/022, SUSTITUYENDO EL TRAYECTO EXISTENTE QUE PASA POR EL FRENTE DE LA VIVIENDA. INCLUYE TUBERÍA, CODOS, YEES, TEES, PEGAMENTO, NIVELACIÓN DE PENDIENTE, MATERIAL, HERRAMIENTA MENOR, MANO DE OBRA Y EQUIPO DE PROTECCIÓN PERSONAL. REGISTRO SANITARIO DE 40 X 60 X 100 CM: FABRICACIÓN DE REGISTRO SANITARIO DEL PROYECTO. INCLUYE PLANTILLA DE CONCRETO SIMPLE F'C=150 KG/CM² DE 5 CM DE PERALTE, MUROS DE TABIQUE RECOCIDO DE 7 X 14 X 28 CM JUNTEADOS CON MORTERO CEMENTO-ARENA 1:4, APLANADO CON ACABADO PULIDO AL INTERIOR, VÉRTICES RESUELTOS EN CHAFLÁN A 45 GRADOS, ARENERO DE 5 CM BAJO EL LECHO INFERIOR DE LOS TUBOS DE 4" PARA RETENCIÓN DE SEDIMENTOS, TAPA DE REGISTRO DE LA MISMA CALIDAD QUE LA PLANTILLA, EXCAVACIÓN, MATERIAL, HERRAMIENTA MENOR, MANO DE OBRA Y EQUIPO DE PROTECCIÓN PERSONAL. R E S U M E N P O R PA R T I DAS PREPARACIÓN Y PRELIMINARES
A41: DEM5029 | B41: M1 | C41: 0.85120532 | D41: 33 | E41: DEMOLICIÓN DE MUROS INTERIORES DE TABICÓN DE 10 CM Y BLOCK DE 15 CM, MÁS EL MURO DE FACHADA DE 20 CM Y EL MURO POSTERIOR DE 16 CM DE LA VIVIENDA, A UNA ALTURA NO MAYOR A 3.40 METROS, CON MARTILLO DEMOLEDOR ELÉCTRICO Y HERRAMIENTA MANUAL. INCLUYE LEVANTADO DEL ESCOMBRO PRODUCTO DE LA DEMOLICIÓN Y SU ACOPIO DENTRO DE LA OBRA, RENTA DE EQUIPO, FLETE DE MAQUINARIA, HERRAMIENTA MENOR, MANO DE OBRA Y EQUIPO DE PROTECCIÓN PERSONAL. NO incluye los dos muros laterales ni el muro posterior del predio, que son compar- · tidos con las propiedades colindantes y se conservan. Los acabados, instalaciones, muebles, puertas y ventanas se demuelen junto con los muros y no se cuantifican por separado. | F41: DEMOLICIÓN DE MUROS INTERIORES DE TABICÓN DE 10 CM Y BLOCK DE 15 CM, MÁS EL MURO DE FACHADA DE 20 CM Y EL MURO POSTERIOR DE 16 CM DE LA VIVIENDA, A UNA ALTURA NO MAYOR A 3.40 METROS, CON MARTILLO DEMOLEDOR ELÉCTRICO Y HERRAMIENTA MANUAL. INCLUYE LEVANTADO DEL ESCOMBRO PRODUCTO DE LA DEMOLICIÓN Y SU ACOPIO DENTRO DE LA OBRA, RENTA DE EQUIPO, FLETE DE MAQUINARIA, HERRAMIENTA MENOR, MANO DE OBRA Y EQUIPO DE PROTECCIÓN PERSONAL. NO incluye los dos muros laterales ni el muro posterior del predio, que son compar-
A42: ALB08217 | B42: M2 | C42: 0.85526316 | D42: 64 | E42: MC-1 MURO DE CONCRETO ARMADO COLADO EN SITIO DE 15 CM DE ESPESOR, ARMADO SEGÚN DESPIECE DEL PLANO ESTRUCTURAL, CON CONCRETO F'C=250 KG/CM². INCLUYE HABILITADO Y ARMADO DE ACERO, CIMBRA A DOS CARAS, COLADO, VIBRADO, CURADO, HERRAMIENTA MENOR, MANO DE OBRA Y EQUIPO DE PROTECCIÓN PERSONAL. | F42: MC-1 MURO DE CONCRETO ARMADO COLADO EN SITIO CON DOBLE MALLA Y CASTILLOS TIPO K, ARMADO SEGÚN DESPIECE DEL PLANO ESTRUCTURAL, CON CONCRETO F'C=250 KG/CM². INCLUYE HABILITADO Y ARMADO DE ACERO, CIMBRA A DOS CARAS, COLADO, VIBRADO Y CURADO. INCLUYE MATERIAL, HERRAMIENTA MENOR, MANO DE OBRA Y EQUIPO DE PROTECCIÓN PERSONAL. | G42: FORMATO CONDICIONAL NO SE POR QUE SE VE TODO ROSA, REVISAR EN TODOS QUE YA ESTAN COMPLETOS POR QUE SE VE ROSA
A43: DEM5027 | B43: M1 | C43: 0.86531365 | D43: 31 | E43: CORTE DE LOSA DE AZOTEA A DEMOLER, CON CORTADORA DE PISO TIPO WALK-BEHIND Y DISCO DE DIAMANTE PARA CONCRETO, SOBRE EL LÍMITE DE COLINDANCIA CON LAS PROPIEDADES VECINAS, PARA DESCONECTAR LA TRANSMISIÓN DE CARGAS ANTES DE LA DEMOLICIÓN. TRABAJOS A UNA ALTURA A PARTIR DE 3 METROS. INCLUYE RENTA DE EQUIPO, DISCO DE CORTE, FLETE DE MAQUINARIA, HERRAMIENTA MENOR, MANO DE OBRA, ANDAMIOS, ARNÉS Y EQUIPO DE PROTECCIÓN PERSONAL CON PROTECCIÓN OCULAR, AUDITIVA Y RESPIRATORIA. · Trabajo en azotea. El corte independiza la losa de cubierta de los dos muros laterales y el muro posterior, que son compartidos y se conservan. | F43: CORTE DE LOSA DE AZOTEA A DEMOLER, CON CORTADORA DE PISO TIPO WALK-BEHIND Y DISCO DE DIAMANTE PARA CONCRETO, SOBRE EL LÍMITE DE COLINDANCIA CON LAS PROPIEDADES VECINAS, PARA DESCONECTAR LA TRANSMISIÓN DE CARGAS ANTES DE LA DEMOLICIÓN. TRABAJOS A UNA ALTURA A PARTIR DE 3 METROS. INCLUYE RENTA DE EQUIPO, DISCO DE CORTE, FLETE DE MAQUINARIA, HERRAMIENTA MENOR, MANO DE OBRA, ANDAMIOS, ARNÉS Y EQUIPO DE PROTECCIÓN PERSONAL CON PROTECCIÓN OCULAR, AUDITIVA Y RESPIRATORIA.
A44: PERS-BBF850C3 | B44: M1 | C44: 0.8731849 | D44: 47 | E44: REGISTRO SANITARIO DE 40 X 60 X 100 CM: FABRICACIÓN DE REGISTRO SANITARIO DEL PROYECTO. INCLUYE PLANTILLA DE CONCRETO SIMPLE F'C=150 KG/CM² DE 5 CM DE PERALTE, MUROS DE TABIQUE ROJO RECOCIDO 7X14X28 JUNTEADO CON MORTERO CEMENTO-ARENA 1:4, APLANADO PULIDO INTERIOR, TAPA DE LA MISMA CALIDAD, VÉRTICES EN CHAFLÁN A 45° Y ARENERO DE 5 CM BAJO EL LECHO DE LOS TUBOS DE 4". INCLUYE MATERIAL, HERRAMIENTA MENOR, MANO DE OBRA Y EQUIPO DE PROTECCIÓN PERSONAL. · ID PROVISIONAL — se creó como concepto personalizado y nunca recibió clave del catálogo. Debe registrarse en conceptos_globales. | F44: REGISTRO SANITARIO DE 40 X 60 X 100 CM: FABRICACIÓN DE REGISTRO SANITARIO DEL PROYECTO. INCLUYE PLANTILLA DE CONCRETO SIMPLE F'C=150 KG/CM² DE 5 CM DE PERALTE, MUROS DE TABIQUE ROJO RECOCIDO 7X14X28 JUNTEADO CON MORTERO CEMENTO-ARENA 1:4, APLANADO PULIDO INTERIOR, TAPA DE LA MISMA CALIDAD, VÉRTICES EN CHAFLÁN A 45° Y ARENERO DE 5 CM BAJO EL LECHO DE LOS TUBOS DE 4". INCLUYE MATERIAL, HERRAMIENTA MENOR, MANO DE OBRA Y EQUIPO DE PROTECCIÓN PERSONAL. | G44: ES UNA ALAÑILERIA
A45: DEM5031 | B45: M1 | C45: 0.87482806 | D45: 35 | E45: DEMOLICIÓN DE LA LOSA DE CONCRETO POBRE EXISTENTE EN EL PATIO EXTERIOR DE LA VIVIENDA, DE 8 CM DE ESPESOR, COMPRENDIDA ENTRE EL EJE POSTERIOR DE LA CONSTRUCCIÓN ACTUAL Y EL LÍMITE DEL PREDIO. INCLUYE LEVANTADO DEL ESCOMBRO Y SU ACOPIO DENTRO DE LA OBRA, HERRAMIENTA MENOR, MANO DE OBRA Y EQUIPO DE PROTECCIÓN PERSONAL. · En esta zona no se conserva piso: se demuele para dar paso a la excavación y nivelación. | F45: DEMOLICIÓN DE LA LOSA DE CONCRETO POBRE EXISTENTE EN EL PATIO EXTERIOR DE LA VIVIENDA, DE 8 CM DE ESPESOR, COMPRENDIDA ENTRE EL EJE POSTERIOR DE LA CONSTRUCCIÓN ACTUAL Y EL LÍMITE DEL PREDIO. INCLUYE LEVANTADO DEL ESCOMBRO Y SU ACOPIO DENTRO DE LA OBRA, HERRAMIENTA MENOR, MANO DE OBRA Y EQUIPO DE PROTECCIÓN PERSONAL.
A46: EXV3018 | B46: M1 | C46: 0.87513572 | D46: 43 | E46: EXCAVACIÓN DE ZANJAS Y TRINCHERAS PARA EL DESPLANTE DE LAS CONTRATRABES CT-1 Y LA LOSA DE CIMENTACIÓN DEL PROYECTO, SEGÚN TRAZO DEL PLANO ESTRUCTURAL ES-02, EN UNA LONGITUD TOTAL DE 89.10 ML DE TRINCHERA DE SECCIÓN 0.20 X 0.40 M. INCLUYE AFINE DE TALUDES, HERRAMIENTA MENOR, MANO DE OBRA Y EQUIPO DE PROTECCIÓN PERSONAL. 48.55 ml de CT-1 en colindancia más 40.55 ml de CT-1 central, según cuantificación · de la hoja ES-7. En la zona de la vivienda actual la trinchera atraviesa la losa existente, previamente cortada. | F46: EXCAVACIÓN DE ZANJAS Y TRINCHERAS PARA EL DESPLANTE DE LAS CONTRATRABES CT-1 Y LA LOSA DE CIMENTACIÓN DEL PROYECTO, SEGÚN TRAZO DEL PLANO ESTRUCTURAL ES-02, EN UNA LONGITUD TOTAL DE 89.10 ML DE TRINCHERA DE SECCIÓN 0.20 X 0.40 M. INCLUYE AFINE DE TALUDES, HERRAMIENTA MENOR, MANO DE OBRA Y EQUIPO DE PROTECCIÓN PERSONAL. 48.55 ml de CT-1 en colindancia más 40.55 ml de CT-1 central, según cuantificación
A47: ELE12100 | B47: M1 | C47: 0.88408304 | D47: 25 | E47: CIRCUITO TRONCAL DE ALIMENTACIÓN ELÉCTRICA PERIMETRAL: TENDIDO DE CIRCUITO TRONCAL DE ALIMENTACIÓN ELÉCTRICA NUEVA POR LA BARDA COLINDANTE AL PASO DE SERVIDUMBRE, CON TUBERÍA CONDUIT PVC DE 3/4" Y ABRAZADERAS DE SUJECIÓN, DESDE EL PUNTO DE HABILITACIÓN EXISTENTE HASTA CADA UNO DE LOS DEPARTAMENTOS DE CASA 2 (EL PROYECTO), CASA 3 Y CASA 4 SEGÚN CROQUIS DEL TÍTULO DE PROPIEDAD, FOLIO CATASTRAL CA 17/022. INCLUYE MATERIAL, HERRAMIENTA MENOR, MANO DE OBRA, ESCALERAS Y ANDAMIOS, Y EQUIPO DE PROTECCIÓN PERSONAL. · Sustituye el trayecto actual que pasa tendido sobre la vivienda a demoler. Corre por la barda al mismo eje del paso de servidumbre. | F47: CIRCUITO TRONCAL DE ALIMENTACIÓN ELÉCTRICA PERIMETRAL: TENDIDO DE CIRCUITO TRONCAL DE ALIMENTACIÓN ELÉCTRICA NUEVA POR LA BARDA COLINDANTE AL PASO DE SERVIDUMBRE, CON TUBERÍA CONDUIT PVC DE 3/4" Y ABRAZADERAS DE SUJECIÓN, DESDE EL PUNTO DE HABILITACIÓN EXISTENTE HASTA CADA UNO DE LOS DEPARTAMENTOS DE CASA 2 (EL PROYECTO), CASA 3 Y CASA 4 SEGÚN CROQUIS DEL TÍTULO DE PROPIEDAD, FOLIO CATASTRAL CA 17/022. INCLUYE MATERIAL, HERRAMIENTA MENOR, MANO DE OBRA, ESCALERAS Y ANDAMIOS, Y EQUIPO DE PROTECCIÓN PERSONAL.
A48: ELE12099 | B48: M1 | C48: 0.88803828 | D48: 24 | E48: SALIDA ELÉCTRICA INDIVIDUAL DE ALIMENTACIÓN PARA DEPARTAMENTO COLINDANTE: SUMINISTRO E INSTALACIÓN DE LA SALIDA ELÉCTRICA FINAL POR DEPARTAMENTO, CON CONDUCTOR DE COBRE THHW CALIBRE 10 O 12 AWG, CHALUPA GALVANIZADA Y CONEXIÓN TERMINAL, PARA CASA 2 (EL PROYECTO), CASA 3 Y CASA 4 SEGÚN CROQUIS DEL TÍTULO DE PROPIEDAD, FOLIO CATASTRAL CA 17/022, A UNA ALTURA NO MAYOR A 3 METROS. INCLUYE MATERIAL, CABLEADO, ACCESORIOS, MANO DE OBRA Y EQUIPO DE PROTECCIÓN PERSONAL. · Una salida por cada departamento afectado. Es el punto de conexión final, distinto del tendido troncal perimetral. | F48: SALIDA ELÉCTRICA INDIVIDUAL DE ALIMENTACIÓN PARA DEPARTAMENTO COLINDANTE: SUMINISTRO E INSTALACIÓN DE LA SALIDA ELÉCTRICA FINAL POR DEPARTAMENTO, CON CONDUCTOR DE COBRE THHW CALIBRE 10 O 12 AWG, CHALUPA GALVANIZADA Y CONEXIÓN TERMINAL, PARA CASA 2 (EL PROYECTO), CASA 3 Y CASA 4 SEGÚN CROQUIS DEL TÍTULO DE PROPIEDAD, FOLIO CATASTRAL CA 17/022, A UNA ALTURA NO MAYOR A 3 METROS. INCLUYE MATERIAL, CABLEADO, ACCESORIOS, MANO DE OBRA Y EQUIPO DE PROTECCIÓN PERSONAL.
A49: DIS07017 | B49: M1 | C49: 0.88888889 | D49: 22 | E49: DESMANTELAMIENTO DE LÍNEA HIDRÁULICA DE ALIMENTACIÓN DE DEPARTAMENTOS COLINDANTES: DESMANTELAMIENTO DE LA LÍNEA HIDRÁULICA DE ALIMENTACIÓN EXISTENTE, TENDIDA EXPUESTA SOBRE EL MURO DE LA VIVIENDA A DEMOLER, QUE DA SERVICIO A CASA 2 (EL PROYECTO), CASA 3 Y CASA 4 SEGÚN CROQUIS DEL TÍTULO DE PROPIEDAD, FOLIO CATASTRAL CA 17/022, A UNA ALTURA NO MAYOR A 3 METROS. INCLUYE INTERRUPCIÓN DESDE LA BOMBA DE LA CISTERNA, VACIADO Y DESCONEXIÓN DE TINACOS, CORTE Y RETIRO DE TUBERÍA VISIBLE, COLOCACIÓN DE TAPÓN PROVISIONAL EN LA SALIDA DE AGUA PROPIA, HERRAMIENTA MENOR, MANO DE OBRA, ESCALERAS Y EQUIPO DE PROTECCIÓN PERSONAL. · El tapón en la salida propia queda colocado antes de la demolición. No incluye la línea nueva ni la reubicación de tinacos, que son conceptos separados. | F49: DESMANTELAMIENTO DE LÍNEA HIDRÁULICA DE ALIMENTACIÓN DE DEPARTAMENTOS COLINDANTES: DESMANTELAMIENTO DE LA LÍNEA HIDRÁULICA DE ALIMENTACIÓN EXISTENTE, TENDIDA EXPUESTA SOBRE EL MURO DE LA VIVIENDA A DEMOLER, QUE DA SERVICIO A CASA 2 (EL PROYECTO), CASA 3 Y CASA 4 SEGÚN CROQUIS DEL TÍTULO DE PROPIEDAD, FOLIO CATASTRAL CA 17/022, A UNA ALTURA NO MAYOR A 3 METROS. INCLUYE INTERRUPCIÓN DESDE LA BOMBA DE LA CISTERNA, VACIADO Y DESCONEXIÓN DE TINACOS, CORTE Y RETIRO DE TUBERÍA VISIBLE, COLOCACIÓN DE TAPÓN PROVISIONAL EN LA SALIDA DE AGUA PROPIA, HERRAMIENTA MENOR, MANO DE OBRA, ESCALERAS Y EQUIPO DE PROTECCIÓN PERSONAL.
A50: DEM5034 | B50: M1 | C50: 0.89015152 | D50: 38 | E50: RETIRO DE LÁMINA DE FIBROCEMENTO (ASBESTO) EN TECHUMBRES DE LA VIVIENDA A DEMOLER, CON HUMECTACIÓN PREVIA PARA ABATIR LA EMISIÓN DE FIBRAS, EMBALAJE DEL RESIDUO EN PLÁSTICO DE CALIBRE GRUESO Y DISPOSICIÓN FINAL EN TIRADERO AUTORIZADO PARA RESIDUOS PELIGROSOS. TRABAJOS A UNA ALTURA A PARTIR DE 3 METROS. INCLUYE MATERIAL DE EMBALAJE, TRANSPORTE A TIRADERO AUTORIZADO, HERRAMIENTA MENOR, MANO DE OBRA, ANDAMIOS Y EQUIPO DE PROTECCIÓN PERSONAL CON PROTECCIÓN RESPIRATORIA. · Mismo tratamiento de riesgo que los tinacos de fibrocemento. El residuo no puede mezclarse con el escombro común. | F50: RETIRO DE LÁMINA DE FIBROCEMENTO (ASBESTO) EN TECHUMBRES DE LA VIVIENDA A DEMOLER, CON HUMECTACIÓN PREVIA PARA ABATIR LA EMISIÓN DE FIBRAS, EMBALAJE DEL RESIDUO EN PLÁSTICO DE CALIBRE GRUESO Y DISPOSICIÓN FINAL EN TIRADERO AUTORIZADO PARA RESIDUOS PELIGROSOS. TRABAJOS A UNA ALTURA A PARTIR DE 3 METROS. INCLUYE MATERIAL DE EMBALAJE, TRANSPORTE A TIRADERO AUTORIZADO, HERRAMIENTA MENOR, MANO DE OBRA, ANDAMIOS Y EQUIPO DE PROTECCIÓN PERSONAL CON PROTECCIÓN RESPIRATORIA.
A51: HSI14089 | B51: M1 | C51: 0.89449955 | D51: 27 | E51: SALIDA HIDRÁULICA NUEVA DE ALIMENTACIÓN PARA DEPARTAMENTO COLINDANTE: SUMINISTRO Y COLOCACIÓN DE SALIDA DE ALIMENTACIÓN NUEVA EN RED HIDRÁULICA CON TUBERÍA PPR DE 3/4" Y ABRAZADERAS DE SUJECIÓN, DESDE LA BOMBA DE LA CISTERNA HASTA EL TINACO DE CADA DEPARTAMENTO DE CASA 2 (EL PROYECTO), CASA 3 Y CASA 4 SEGÚN CROQUIS DEL TÍTULO DE PROPIEDAD, FOLIO CATASTRAL CA 17/022, A UNA ALTURA NO MAYOR A 3 METROS. INCLUYE MATERIAL, MANO DE OBRA, HERRAMIENTA MENOR, ESCALERAS Y EQUIPO DE PROTECCIÓN PERSONAL. · Una salida por cada departamento afectado. Sustituye la línea desmantelada que pasaba sobre la vivienda a demoler. | F51: SALIDA HIDRÁULICA NUEVA DE ALIMENTACIÓN PARA DEPARTAMENTO COLINDANTE: SUMINISTRO Y COLOCACIÓN DE SALIDA DE ALIMENTACIÓN NUEVA EN RED HIDRÁULICA CON TUBERÍA PPR DE 3/4" Y ABRAZADERAS DE SUJECIÓN, DESDE LA BOMBA DE LA CISTERNA HASTA EL TINACO DE CADA DEPARTAMENTO DE CASA 2 (EL PROYECTO), CASA 3 Y CASA 4 SEGÚN CROQUIS DEL TÍTULO DE PROPIEDAD, FOLIO CATASTRAL CA 17/022, A UNA ALTURA NO MAYOR A 3 METROS. INCLUYE MATERIAL, MANO DE OBRA, HERRAMIENTA MENOR, ESCALERAS Y EQUIPO DE PROTECCIÓN PERSONAL.
A52: DEM05035 | B52: M2 | C52: 0.91358025 | D52: 55 | E52: DESTECATADO EN MUROS COLINDANTES EXISTENTES POR MEDIOS MANUALES, SIN AFECTAR LA ESTABILIDAD DEL MURO NI LA PROPIEDAD VECINA. INCLUYE ACARREO INTERNO AL ACOPIO, HERRAMIENTA MENOR, MANO DE OBRA, ANDAMIOS Y EQUIPO DE PROTECCIÓN PERSONAL. | F52: DESTECATADO DE MUROS COLINDANTES EXISTENTES POR MEDIOS MANUALES, SIN AFECTAR LA ESTABILIDAD DEL MURO NI LA PROPIEDAD VECINA. INCLUYE ACARREO INTERNO AL ACOPIO, ANDAMIOS. INCLUYE MATERIAL, HERRAMIENTA MENOR, MANO DE OBRA Y EQUIPO DE PROTECCIÓN PERSONAL.
A53: ALB08212 | B53: M2 | C53: 0.93591654 | D53: 58 | E53: C-1 COLUMNA DE SECCIÓN 15 X 30 CM Y UNA ALTURA DE 2.50 M A NIVEL BAJO LECHO DE LOSA DE ENTREPISO. ARMADA SEGÚN DESPIECE DEL PLANO ESTRUCTURAL, CON CONCRETO F'C=250 KG/CM². INCLUYE HABILITADO Y ARMADO DE ACERO, CIMBRA Y DESCIMBRA, COLADO, VIBRADO, CURADO, ANDAMIO, HERRAMIENTA MENOR, MANO DE OBRA Y EQUIPO DE PROTECCIÓN PERSONAL. | F53: C-1 COLUMNA DE SECCIÓN 15 X 30 CM Y ALTURA DE 2.50 M A NIVEL BAJO LECHO DE LOSA DE ENTREPISO, ARMADA SEGÚN DESPIECE DEL PLANO ESTRUCTURAL, CON CONCRETO F'C=250 KG/CM². INCLUYE HABILITADO Y ARMADO DE ACERO, CIMBRA Y DESCIMBRA, COLADO, VIBRADO, CURADO Y ANDAMIO. INCLUYE MATERIAL, HERRAMIENTA MENOR, MANO DE OBRA Y EQUIPO DE PROTECCIÓN PERSONAL. | G53: SE QUEDA ASI
A56: CLAVES QUE ESTÁN EN V10 Y NO EN V11 · confirma si fue a propósito
A57: CLAVE V10 | B57: MÓD | C57: P.U. V10 | E57: DESCRIPCIÓN V10 | F57: EQUIVALENTE MÁS PARECIDO EN V11 | H57: TU DECISIÓN
A58: ALB08210 | B58: M2 | C58: 69.3 | F58: — sin equivalente —
A59: ALB08220 | B59: M2 | C59: 7094.95 | F59: — sin equivalente —
A60: ALB08225 | B60: M3 | C60: 0 | F60: — sin equivalente —
A61: ALB08227 | B61: M3 | C61: 0 | F61: — sin equivalente —
A62: ALB08229 | B62: M5 | C62: 0 | E62: RAMPA DE ESCALERA DE CONCRETO ARMADO F'C=250 KG/CM², ESPESOR Y ARMADO DE PROYECTO, MEDIDA EN DESARROLLO INCLINADO. INCLUYE HABILITADO Y ARMADO DE ACERO, CIMBRA Y DES CIMBRADE FONDO Y COSTADOS, APUNTALAMIENTO, COLADO, CURADO, HERRAMIENTA MENOR, MANO DE OBRA Y EQUIPO DE PROTECCIÓN PERSONAL. PELDAÑEADO DE ESCALERA CON HUELLA Y PERALTE DE PROYECTO, COLADO MONOLÍTICO SOBRE RAMPA. INCLUYE CIMBRA DE CONTRAHUELLA, COLADO, REGLEADO, CURADO, HERRAMIENTA MENOR, MANO DE OBRA Y EQUIPO DE PROTECCIÓN PERSONAL. MEDIDO POR METRO LINEAL DE ESCALÓN.DESCANSO DE ESCALERA: LOSA MACIZA DE CONCRETO ARMADO F'C=250 KG/CM² DEL ESPESOR DE PROYECTO. INCLUYE HABILITADO Y ARMADO, CIMBRA, APUNTALAMIENTO, COLADO, CURADO, HERRAMIENTA MENOR, MANO DE OBRA Y EQUIPO DE PROTECCIÓN PERSONAL. | F62: — sin equivalente —
A63: ALB08230 | B63: M5 | C63: 0 | F63: — sin equivalente —
A64: ALB08231 | B64: M5 | C64: 0 | F64: — sin equivalente —
A65: ALB08232 | B65: M6 | C65: 0 | E65: OPCIÓN B · COLADO DE LOSA CON PENDIENTE INTEGRADA PARA USO PROVISIONAL COMO AZOTEA: SOBRECOSTO POR DAR PENDIENTE MÍNIMA DEL 2% HACIA BAJADAS PLUVIALES DESDE EL COLADO DE LA CAPA DE COMPRESIÓN, EVITANDO EL ENTORTADO. INCLUYE TRAZO DE NIVELES, REGLAS Y MAESTREADO, REGLEADO EN PENDIENTE, CURADO, HERRAMIENTA MENOR, MANO DE OBRA Y EQUIPO DE PROTECCIÓN PERSONAL. · La Opción B se arma colocando el MÓDULO 3 completo más este paquete provisional. CLAVE PROVISIONAL — la definitiva la genera bulk-import.mjs al cargar el concepto al catálogo global. | F65: ALB08243 (69%) OPCIÓN B · COLADO DE LOSA CON PENDIENTE INTEGRADA PARA USO PROVISIONAL COMO AZOTEA: SOBRECOSTO POR DAR PENDIEN
A66: ALB08233 | B66: M6 | C66: 0 | E66: OPCIÓN B · PRETIL PROVISIONAL DE BLOCK SIN APLANAR DE 45 CM DE ALTURA CON CASTILLO DE 15 X 15, EN EL PERÍMETRO EXPUESTO. INCLUYE MATERIAL, CIMBRADO, HERRAMIENTA MENOR, MANO DE OBRA Y EQUIPO DE PROTECCIÓN PERSONAL. · Pendiente definir grosor: el plano REV.03 pregunta si será de 15 o 20 cm. CLAVE PROVISIONAL — la definitiva la genera bulk-import.mjs al cargar el concepto al catálogo global. | F66: — sin equivalente —
A67: ALB08235 | B67: M6 | C67: 0 | E67: OPCIÓN B · IMPERMEABILIZACIÓN PROVISIONAL DE LOSA CON MEMBRANA DE USO TEMPORAL SOBRE LA SUPERFICIE QUE RECIBIRÁ EL NIVEL FUTURO. INCLUYE MATERIAL, HERRAMIENTA MENOR, MANO DE OBRA Y EQUIPO DE PROTECCIÓN PERSONAL. · CLAVE PROVISIONAL — la definitiva la genera bulk-import.mjs al cargar el concepto al catálogo global. | F67: HSI14113 (50%) OPCIÓN A · SUMINISTRO Y COLOCACIÓN DE BOILER DE PASO DE 12 L CON SUS CONEXIONES. INCLUYE MATERIAL, HERRAMIENTA
A68: ALB08237 | B68: M6 | C68: 0 | E68: OPCIÓN B · ESPERAS DE CASTILLO PARA NIVEL FUTURO: BASTONES SALIENTES EN CASTILLOS DE ARRANQUE, DOBLADOS Y PROTEGIDOS. INCLUYE HABILITADO, COLOCACIÓN, PROTECCIÓN, HERRAMIENTA MENOR, MANO DE OBRA Y EQUIPO DE PROTECCIÓN PERSONAL. · CLAVE PROVISIONAL — la definitiva la genera bulk-import.mjs al cargar el concepto al catálogo global. | F68: — sin equivalente —
A69: CIM04001 | B69: M2 | C69: 0 | E69: PUNTO DE CONEXIÓN DE LA CIMENTACIÓN NUEVA AL TERRENO MEJORADO: DADO DE CONCRETO ARMADO F'C=250 KG/CM² ALOJADO EN RANURA EXISTENTE, CON ANCLAS DE VARILLA DEL #4 A LA LONGITUD DE DESARROLLO DE TABLA, PARA AMARRE DE CONTRATRABE Y LOSA DE CIMENTACIÓN AL FIRME EXISTENTE. INCLUYE LIMPIEZA Y MARTELINADO DE JUNTA FRÍA, HABILITADO Y COLOCACIÓN DE ANCLAS, CIMBRA, COLADO, CURADO, HERRAMIENTA MENOR, MANO DE OBRA Y EQUIPO DE PROTECCIÓN PERSONAL. | F69: — sin equivalente —
A70: CIM04002 | B70: M2 | C70: 0 | E70: CT-1 CONTRATRABE APERALTADA DE COLINDANCIA DE SECCIÓN 15 X 47 CM, ARMADA SEGÚN DESPIECE DEL PLANO ESTRUCTURAL, CON CONCRETO F'C=250 KG/CM². INCLUYE HABILITADO Y ARMADO DE ACERO, CIMBRA Y DESCIMBRA, COLADO, VIBRADO, CURADO, HERRAMIENTA MENOR, MANO DE OBRA Y EQUIPO DE PROTECCIÓN PERSONAL. · Sección deducida de ES-07 (área 0.07 m²). CLAVE PROVISIONAL — la definitiva la genera bulk-import.mjs al cargar el concepto al catálogo global. | F70: ALB08212 (64%) C-1 COLUMNA DE SECCIÓN 15 X 30 CM Y ALTURA DE 2.50 M A NIVEL BAJO LECHO DE LOSA DE ENTREPISO, ARMADA SEGÚN DES
A71: DEM05036 | B71: M2 | C71: 0 | E71: SANGRADO DE MURO COLINDANTE: PERFORACIONES PARCIALES EN RETÍCULA PARA LIBERAR LA HUMEDAD RETENIDA DURANTE LOS TRABAJOS DE CIMENTACIÓN. INCLUYE TRAZO DE RETÍCULA, PERFORACIÓN, LIMPIEZA, HERRAMIENTA MENOR, MANO DE OBRA Y EQUIPO DE PROTECCIÓN PERSONAL. · CLAVE PROVISIONAL — la definitiva la genera bulk-import.mjs al cargar el concepto al catálogo global. | F71: — sin equivalente —
A72: DEM05037 | B72: M2 | C72: 0 | E72: ESCARIFICADO SUPERFICIAL DE MURO POSTERIOR DE MAMPOSTERÍA DE PIEDRA: RETIRO DEL APLANADO FINO CON CARDA Y RANURADO DE ADHERENCIA, CONSERVANDO EL REVOQUE ESTRUCTURAL DEL MURO. INCLUYE HERRAMIENTA MENOR, MANO DE OBRA, ANDAMIOS Y EQUIPO DE PROTECCIÓN PERSONAL. · CLAVE PROVISIONAL — la definitiva la genera bulk-import.mjs al cargar el concepto al catálogo global. | F72: — sin equivalente —
A73: HRR10002 | B73: M6 | C73: 0 | E73: OPCIÓN B · ESTRUCTURA METÁLICA PROVISIONAL PARA BASE DE TINACO SOBRE CUBO DE LAVANDERÍA: BASTIDOR DE PERFIL TUBULAR ESTRUCTURAL CON PLACAS DE APOYO ANCLADAS A LA LOSA, ALTURA DE PROYECTO, CON ACABADO ANTICORROSIVO. INCLUYE HABILITADO, SOLDADURA, ANCLAJES, ELEVACIÓN, MONTAJE, PINTURA, HERRAMIENTA, MANO DE OBRA Y EQUIPO DE PROTECCIÓN PERSONAL. · CLAVE PROVISIONAL — la definitiva la genera bulk-import.mjs al cargar el concepto al catálogo global. | F73: HRR10001 (76%) OPCIÓN B · ESTRUCTURA METÁLICA PROVISIONAL PARA BASE DE TINACO SOBRE CUBO DE ESCALERA Y SOBRE CUBO DE LAVANDER
A74: HRR10004 | B74: M6 | C74: 0 | E74: OPCIÓN B · CUBIERTA LIGERA PROVISIONAL DE CUBO DE LAVANDERÍA A BASE DE ESTRUCTURA METÁLICA Y LÁMINA, CON PENDIENTE Y GOTEO. INCLUYE HABILITADO, SOLDADURA, ANCLAJES, LÁMINA, SELLADO, HERRAMIENTA, MANO DE OBRA Y EQUIPO DE PROTECCIÓN PERSONAL. · Superficie pendiente de la lámina AZ2 del arquitectónico REV.03. CLAVE PROVISIONAL — la definitiva la genera bulk-import.mjs al cargar el concepto al catálogo global. | F74: HRR10003 (66%) OPCIÓN B · CUBIERTA LIGERA PROVISIONAL DE CUBO DE ESCALERA Y DE CUBO DE LAVANDERÍA A BASE DE ESTRUCTURA METÁLI
A75: NUEVO | B75: M4 | C75: 0 | E75: C-1 COLUMNA DE SECCIÓN 15 X 30 CM Y UNA ALTURA DE 2.50 M A NIVEL BAJO LECHO DE LOSA DE ENTREPISO. ARMADA SEGÚN DESPIECE DEL PLANO ESTRUCTURAL, CON CONCRETO F'C=250 KG/CM². INCLUYE HABILITADO Y ARMADO DE ACERO, CIMBRA Y DESCIMBRA, COLADO, VIBRADO, CURADO, ANDAMIO, HERRAMIENTA MENOR, MANO DE OBRA Y EQUIPO DE PROTECCIÓN PERSONAL.TRABAJO DESDE 3 HASTA 6M DE ALTURA. | F75: ALB08212 (89%) C-1 COLUMNA DE SECCIÓN 15 X 30 CM Y ALTURA DE 2.50 M A NIVEL BAJO LECHO DE LOSA DE ENTREPISO, ARMADA SEGÚN DES

Sheet TPU
A1: TARJETAS DE PRECIOS UNITARIOS
A2: PROYECTO | C2: =CARATULA!$C$10
A3: CLIENTE | C3: =CARATULA!$C$12
A4: UBICACIÓN | C4: =CARATULA!$C$14
A5: EMPRESA | C5: =CARATULA!$C$19
A6: Un renglón por insumo. importe = (cantidad ÷ rendimiento) × costo unitario × (1 + % desperdicio)
A7: El COSTO DIRECTO de cada concepto se acumula abajo y es lo que debe capturarse como P.U. BASE en el PRESUPUESTO.
A8: CLAVE CONCEPTO | B8: TIPO | C8: ID INSUMO | D8: DESCRIPCIÓN DEL INSUMO | E8: UNIDAD | F8: CANTIDAD | G8: RENDIMIENTO | H8: COSTO UNITARIO | I8: DESPERD. % | J8: IMPORTE | K8: NOTAS
A9: DEM5029 | B9: mano_obra | C9: MO-002 | D9: {=IFERROR(INDEX(INSUMOS!$C$9:$C$508,MATCH(C9,INSUMOS!$A$9:$A$508,0)),"")} | E9: {=IFERROR(INDEX(INSUMOS!$D$9:$D$508,MATCH(C9,INSUMOS!$A$9:$A$508,0)),"")} | F9: 1 | G9: 3.5 | H9: {=IFERROR(INDEX(INSUMOS!$E$9:$E$508,MATCH(C9,INSUMOS!$A$9:$A$508,0)),0)} | I9: 0 | J9: =IF($C9="","",F9/IF(G9=0,1,G9)*H9*(1+I9)) | K9: 1 oficial · 3.5 m² por jornada
A10: DEM5029 | B10: mano_obra | C10: MO-004 | D10: {=IFERROR(INDEX(INSUMOS!$C$9:$C$508,MATCH(C10,INSUMOS!$A$9:$A$508,0)),"")} | E10: {=IFERROR(INDEX(INSUMOS!$D$9:$D$508,MATCH(C10,INSUMOS!$A$9:$A$508,0)),"")} | F10: 1 | G10: 3.5 | H10: {=IFERROR(INDEX(INSUMOS!$E$9:$E$508,MATCH(C10,INSUMOS!$A$9:$A$508,0)),0)} | I10: 0 | J10: =IF($C10="","",F10/IF(G10=0,1,G10)*H10*(1+I10)) | K10: 1 ayudante · misma cuadrilla
A11: DEM5029 | B11: herramienta | C11: HER-0002 | D11: {=IFERROR(INDEX(INSUMOS!$C$9:$C$508,MATCH(C11,INSUMOS!$A$9:$A$508,0)),"")} | E11: {=IFERROR(INDEX(INSUMOS!$D$9:$D$508,MATCH(C11,INSUMOS!$A$9:$A$508,0)),"")} | F11: 1 | G11: 3.5 | H11: {=IFERROR(INDEX(INSUMOS!$E$9:$E$508,MATCH(C11,INSUMOS!$A$9:$A$508,0)),0)} | I11: 0 | J11: =IF($C11="","",F11/IF(G11=0,1,G11)*H11*(1+I11)) | K11: martillo demoledor
A12: DEM5029 | B12: indirecto | C12: IND-001 | D12: {=IFERROR(INDEX(INSUMOS!$C$9:$C$508,MATCH(C12,INSUMOS!$A$9:$A$508,0)),"")} | E12: {=IFERROR(INDEX(INSUMOS!$D$9:$D$508,MATCH(C12,INSUMOS!$A$9:$A$508,0)),"")} | F12: 1 | G12: 1 | H12: {=IFERROR(INDEX(INSUMOS!$E$9:$E$508,MATCH(C12,INSUMOS!$A$9:$A$508,0)),0)} | I12: 0 | J12: =IF($C12="","",F12/IF(G12=0,1,G12)*H12*(1+I12)) | K12: EPP al 3% de la mano de obra
D13: {=IFERROR(INDEX(INSUMOS!$C$9:$C$508,MATCH(C13,INSUMOS!$A$9:$A$508,0)),"")} | E13: {=IFERROR(INDEX(INSUMOS!$D$9:$D$508,MATCH(C13,INSUMOS!$A$9:$A$508,0)),"")} | H13: {=IFERROR(INDEX(INSUMOS!$E$9:$E$508,MATCH(C13,INSUMOS!$A$9:$A$508,0)),0)} | J13: =IF($C13="","",F13/IF(G13=0,1,G13)*H13*(1+I13))
D14: {=IFERROR(INDEX(INSUMOS!$C$9:$C$508,MATCH(C14,INSUMOS!$A$9:$A$508,0)),"")} | E14: {=IFERROR(INDEX(INSUMOS!$D$9:$D$508,MATCH(C14,INSUMOS!$A$9:$A$508,0)),"")} | H14: {=IFERROR(INDEX(INSUMOS!$E$9:$E$508,MATCH(C14,INSUMOS!$A$9:$A$508,0)),0)} | J14: =IF($C14="","",F14/IF(G14=0,1,G14)*H14*(1+I14))
D15: {=IFERROR(INDEX(INSUMOS!$C$9:$C$508,MATCH(C15,INSUMOS!$A$9:$A$508,0)),"")} | E15: {=IFERROR(INDEX(INSUMOS!$D$9:$D$508,MATCH(C15,INSUMOS!$A$9:$A$508,0)),"")} | H15: {=IFERROR(INDEX(INSUMOS!$E$9:$E$508,MATCH(C15,INSUMOS!$A$9:$A$508,0)),0)} | J15: =IF($C15="","",F15/IF(G15=0,1,G15)*H15*(1+I15))
D16: {=IFERROR(INDEX(INSUMOS!$C$9:$C$508,MATCH(C16,INSUMOS!$A$9:$A$508,0)),"")} | E16: {=IFERROR(INDEX(INSUMOS!$D$9:$D$508,MATCH(C16,INSUMOS!$A$9:$A$508,0)),"")} | H16: {=IFERROR(INDEX(INSUMOS!$E$9:$E$508,MATCH(C16,INSUMOS!$A$9:$A$508,0)),0)} | J16: =IF($C16="","",F16/IF(G16=0,1,G16)*H16*(1+I16))
D17: {=IFERROR(INDEX(INSUMOS!$C$9:$C$508,MATCH(C17,INSUMOS!$A$9:$A$508,0)),"")} | E17: {=IFERROR(INDEX(INSUMOS!$D$9:$D$508,MATCH(C17,INSUMOS!$A$9:$A$508,0)),"")} | H17: {=IFERROR(INDEX(INSUMOS!$E$9:$E$508,MATCH(C17,INSUMOS!$A$9:$A$508,0)),0)} | J17: =IF($C17="","",F17/IF(G17=0,1,G17)*H17*(1+I17))
D18: {=IFERROR(INDEX(INSUMOS!$C$9:$C$508,MATCH(C18,INSUMOS!$A$9:$A$508,0)),"")} | E18: {=IFERROR(INDEX(INSUMOS!$D$9:$D$508,MATCH(C18,INSUMOS!$A$9:$A$508,0)),"")} | H18: {=IFERROR(INDEX(INSUMOS!$E$9:$E$508,MATCH(C18,INSUMOS!$A$9:$A$508,0)),0)} | J18: =IF($C18="","",F18/IF(G18=0,1,G18)*H18*(1+I18))
D19: {=IFERROR(INDEX(INSUMOS!$C$9:$C$508,MATCH(C19,INSUMOS!$A$9:$A$508,0)),"")} | E19: {=IFERROR(INDEX(INSUMOS!$D$9:$D$508,MATCH(C19,INSUMOS!$A$9:$A$508,0)),"")} | H19: {=IFERROR(INDEX(INSUMOS!$E$9:$E$508,MATCH(C19,INSUMOS!$A$9:$A$508,0)),0)} | J19: =IF($C19="","",F19/IF(G19=0,1,G19)*H19*(1+I19))
D20: {=IFERROR(INDEX(INSUMOS!$C$9:$C$508,MATCH(C20,INSUMOS!$A$9:$A$508,0)),"")} | E20: {=IFERROR(INDEX(INSUMOS!$D$9:$D$508,MATCH(C20,INSUMOS!$A$9:$A$508,0)),"")} | H20: {=IFERROR(INDEX(INSUMOS!$E$9:$E$508,MATCH(C20,INSUMOS!$A$9:$A$508,0)),0)} | J20: =IF($C20="","",F20/IF(G20=0,1,G20)*H20*(1+I20))
D21: {=IFERROR(INDEX(INSUMOS!$C$9:$C$508,MATCH(C21,INSUMOS!$A$9:$A$508,0)),"")} | E21: {=IFERROR(INDEX(INSUMOS!$D$9:$D$508,MATCH(C21,INSUMOS!$A$9:$A$508,0)),"")} | H21: {=IFERROR(INDEX(INSUMOS!$E$9:$E$508,MATCH(C21,INSUMOS!$A$9:$A$508,0)),0)} | J21: =IF($C21="","",F21/IF(G21=0,1,G21)*H21*(1+I21))
D22: {=IFERROR(INDEX(INSUMOS!$C$9:$C$508,MATCH(C22,INSUMOS!$A$9:$A$508,0)),"")} | E22: {=IFERROR(INDEX(INSUMOS!$D$9:$D$508,MATCH(C22,INSUMOS!$A$9:$A$508,0)),"")} | H22: {=IFERROR(INDEX(INSUMOS!$E$9:$E$508,MATCH(C22,INSUMOS!$A$9:$A$508,0)),0)} | J22: =IF($C22="","",F22/IF(G22=0,1,G22)*H22*(1+I22))
D23: {=IFERROR(INDEX(INSUMOS!$C$9:$C$508,MATCH(C23,INSUMOS!$A$9:$A$508,0)),"")} | E23: {=IFERROR(INDEX(INSUMOS!$D$9:$D$508,MATCH(C23,INSUMOS!$A$9:$A$508,0)),"")} | H23: {=IFERROR(INDEX(INSUMOS!$E$9:$E$508,MATCH(C23,INSUMOS!$A$9:$A$508,0)),0)} | J23: =IF($C23="","",F23/IF(G23=0,1,G23)*H23*(1+I23))
D24: {=IFERROR(INDEX(INSUMOS!$C$9:$C$508,MATCH(C24,INSUMOS!$A$9:$A$508,0)),"")} | E24: {=IFERROR(INDEX(INSUMOS!$D$9:$D$508,MATCH(C24,INSUMOS!$A$9:$A$508,0)),"")} | H24: {=IFERROR(INDEX(INSUMOS!$E$9:$E$508,MATCH(C24,INSUMOS!$A$9:$A$508,0)),0)} | J24: =IF($C24="","",F24/IF(G24=0,1,G24)*H24*(1+I24))
... D228: {=IFERROR(INDEX(INSUMOS!$C$9:$C$508,MATCH(C228,INSUMOS!$A$9:$A$508,0)),"")} | E228: {=IFERROR(INDEX(INSUMOS!$D$9:$D$508,MATCH(C228,INSUMOS!$A$9:$A$508,0)),"")} | H228: {=IFERROR(INDEX(INSUMOS!$E$9:$E$508,MATCH(C228,INSUMOS!$A$9:$A$508,0)),0)} | J228: =IF($C228="","",F228/IF(G228=0,1,G228)*H228*(1+I228))
J229: =IF($C229="","",F229/IF(G229=0,1,G229)*H229*(1+I229))
A230: COSTO DIRECTO POR CONCEPTO · este número es el que va al P.U. BASE del PRESUPUESTO | J230: =IF($C230="","",F230/IF(G230=0,1,G230)*H230*(1+I230))
A231: CLAVE | D231: DESCRIPCIÓN DEL CONCEPTO | F231: RENGLONES | H231: COSTO DIRECTO | J231: =IF($C231="","",F231/IF(G231=0,1,G231)*H231*(1+I231)) | K231: DIFERENCIA
A232: DEM5029 | D232: {=IF($A232="","",IFERROR(INDEX(PRESUPUESTO!$B$10:$B$174,MATCH($A232,PRESUPUESTO!$A$10:$A$174,0)),"⚠ clave no existe"))} | F232: =IF($A232="","",COUNTIF($A$9:$A$228,$A232)) | H232: =IF($A232="","",SUMIF($A$9:$A$228,$A232,$J$9:$J$228)) | J232: {=IF($A232="","",IFERROR(INDEX(PRESUPUESTO!$M$10:$M$174,MATCH($A232,PRESUPUESTO!$A$10:$A$174,0)),0))} | K232: =IF($A232="","",N(J232)-N(H232))
D233: {=IF($A233="","",IFERROR(INDEX(PRESUPUESTO!$B$10:$B$174,MATCH($A233,PRESUPUESTO!$A$10:$A$174,0)),"⚠ clave no existe"))} | F233: =IF($A233="","",COUNTIF($A$9:$A$228,$A233)) | H233: =IF($A233="","",SUMIF($A$9:$A$228,$A233,$J$9:$J$228)) | J233: {=IF($A233="","",IFERROR(INDEX(PRESUPUESTO!$M$10:$M$174,MATCH($A233,PRESUPUESTO!$A$10:$A$174,0)),0))} | K233: =IF($A233="","",N(J233)-N(H233))
D234: {=IF($A234="","",IFERROR(INDEX(PRESUPUESTO!$B$10:$B$174,MATCH($A234,PRESUPUESTO!$A$10:$A$174,0)),"⚠ clave no existe"))} | F234: =IF($A234="","",COUNTIF($A$9:$A$228,$A234)) | H234: =IF($A234="","",SUMIF($A$9:$A$228,$A234,$J$9:$J$228)) | J234: {=IF($A234="","",IFERROR(INDEX(PRESUPUESTO!$M$10:$M$174,MATCH($A234,PRESUPUESTO!$A$10:$A$174,0)),0))} | K234: =IF($A234="","",N(J234)-N(H234))
D235: {=IF($A235="","",IFERROR(INDEX(PRESUPUESTO!$B$10:$B$174,MATCH($A235,PRESUPUESTO!$A$10:$A$174,0)),"⚠ clave no existe"))} | F235: =IF($A235="","",COUNTIF($A$9:$A$228,$A235)) | H235: =IF($A235="","",SUMIF($A$9:$A$228,$A235,$J$9:$J$228)) | J235: {=IF($A235="","",IFERROR(INDEX(PRESUPUESTO!$M$10:$M$174,MATCH($A235,PRESUPUESTO!$A$10:$A$174,0)),0))} | K235: =IF($A235="","",N(J235)-N(H235))
D236: {=IF($A236="","",IFERROR(INDEX(PRESUPUESTO!$B$10:$B$174,MATCH($A236,PRESUPUESTO!$A$10:$A$174,0)),"⚠ clave no existe"))} | F236: =IF($A236="","",COUNTIF($A$9:$A$228,$A236)) | H236: =IF($A236="","",SUMIF($A$9:$A$228,$A236,$J$9:$J$228)) | J236: {=IF($A236="","",IFERROR(INDEX(PRESUPUESTO!$M$10:$M$174,MATCH($A236,PRESUPUESTO!$A$10:$A$174,0)),0))} | K236: =IF($A236="","",N(J236)-N(H236))
D237: {=IF($A237="","",IFERROR(INDEX(PRESUPUESTO!$B$10:$B$174,MATCH($A237,PRESUPUESTO!$A$10:$A$174,0)),"⚠ clave no existe"))} | F237: =IF($A237="","",COUNTIF($A$9:$A$228,$A237)) | H237: =IF($A237="","",SUMIF($A$9:$A$228,$A237,$J$9:$J$228)) | J237: {=IF($A237="","",IFERROR(INDEX(PRESUPUESTO!$M$10:$M$174,MATCH($A237,PRESUPUESTO!$A$10:$A$174,0)),0))} | K237: =IF($A237="","",N(J237)-N(H237))
D238: {=IF($A238="","",IFERROR(INDEX(PRESUPUESTO!$B$10:$B$174,MATCH($A238,PRESUPUESTO!$A$10:$A$174,0)),"⚠ clave no existe"))} | F238: =IF($A238="","",COUNTIF($A$9:$A$228,$A238)) | H238: =IF($A238="","",SUMIF($A$9:$A$228,$A238,$J$9:$J$228)) | J238: {=IF($A238="","",IFERROR(INDEX(PRESUPUESTO!$M$10:$M$174,MATCH($A238,PRESUPUESTO!$A$10:$A$174,0)),0))} | K238: =IF($A238="","",N(J238)-N(H238))
D239: {=IF($A239="","",IFERROR(INDEX(PRESUPUESTO!$B$10:$B$174,MATCH($A239,PRESUPUESTO!$A$10:$A$174,0)),"⚠ clave no existe"))} | F239: =IF($A239="","",COUNTIF($A$9:$A$228,$A239)) | H239: =IF($A239="","",SUMIF($A$9:$A$228,$A239,$J$9:$J$228)) | J239: {=IF($A239="","",IFERROR(INDEX(PRESUPUESTO!$M$10:$M$174,MATCH($A239,PRESUPUESTO!$A$10:$A$174,0)),0))} | K239: =IF($A239="","",N(J239)-N(H239))
D240: {=IF($A240="","",IFERROR(INDEX(PRESUPUESTO!$B$10:$B$174,MATCH($A240,PRESUPUESTO!$A$10:$A$174,0)),"⚠ clave no existe"))} | F240: =IF($A240="","",COUNTIF($A$9:$A$228,$A240)) | H240: =IF($A240="","",SUMIF($A$9:$A$228,$A240,$J$9:$J$228)) | J240: {=IF($A240="","",IFERROR(INDEX(PRESUPUESTO!$M$10:$M$174,MATCH($A240,PRESUPUESTO!$A$10:$A$174,0)),0))} | K240: =IF($A240="","",N(J240)-N(H240))
D241: {=IF($A241="","",IFERROR(INDEX(PRESUPUESTO!$B$10:$B$174,MATCH($A241,PRESUPUESTO!$A$10:$A$174,0)),"⚠ clave no existe"))} | F241: =IF($A241="","",COUNTIF($A$9:$A$228,$A241)) | H241: =IF($A241="","",SUMIF($A$9:$A$228,$A241,$J$9:$J$228)) | J241: {=IF($A241="","",IFERROR(INDEX(PRESUPUESTO!$M$10:$M$174,MATCH($A241,PRESUPUESTO!$A$10:$A$174,0)),0))} | K241: =IF($A241="","",N(J241)-N(H241))
D242: {=IF($A242="","",IFERROR(INDEX(PRESUPUESTO!$B$10:$B$174,MATCH($A242,PRESUPUESTO!$A$10:$A$174,0)),"⚠ clave no existe"))} | F242: =IF($A242="","",COUNTIF($A$9:$A$228,$A242)) | H242: =IF($A242="","",SUMIF($A$9:$A$228,$A242,$J$9:$J$228)) | J242: {=IF($A242="","",IFERROR(INDEX(PRESUPUESTO!$M$10:$M$174,MATCH($A242,PRESUPUESTO!$A$10:$A$174,0)),0))} | K242: =IF($A242="","",N(J242)-N(H242))
D243: {=IF($A243="","",IFERROR(INDEX(PRESUPUESTO!$B$10:$B$174,MATCH($A243,PRESUPUESTO!$A$10:$A$174,0)),"⚠ clave no existe"))} | F243: =IF($A243="","",COUNTIF($A$9:$A$228,$A243)) | H243: =IF($A243="","",SUMIF($A$9:$A$228,$A243,$J$9:$J$228)) | J243: {=IF($A243="","",IFERROR(INDEX(PRESUPUESTO!$M$10:$M$174,MATCH($A243,PRESUPUESTO!$A$10:$A$174,0)),0))} | K243: =IF($A243="","",N(J243)-N(H243))
D244: {=IF($A244="","",IFERROR(INDEX(PRESUPUESTO!$B$10:$B$174,MATCH($A244,PRESUPUESTO!$A$10:$A$174,0)),"⚠ clave no existe"))} | F244: =IF($A244="","",COUNTIF($A$9:$A$228,$A244)) | H244: =IF($A244="","",SUMIF($A$9:$A$228,$A244,$J$9:$J$228)) | J244: {=IF($A244="","",IFERROR(INDEX(PRESUPUESTO!$M$10:$M$174,MATCH($A244,PRESUPUESTO!$A$10:$A$174,0)),0))} | K244: =IF($A244="","",N(J244)-N(H244))
... D519: {=IF($A519="","",IFERROR(INDEX(PRESUPUESTO!$B$10:$B$174,MATCH($A519,PRESUPUESTO!$A$10:$A$174,0)),"⚠ clave no existe"))} | F519: =IF($A519="","",COUNTIF($A$9:$A$228,$A519)) | H519: =IF($A519="","",SUMIF($A$9:$A$228,$A519,$J$9:$J$228)) | J519: {=IF($A519="","",IFERROR(INDEX(PRESUPUESTO!$M$10:$M$174,MATCH($A519,PRESUPUESTO!$A$10:$A$174,0)),0))} | K519: =IF($A519="","",N(J519)-N(H519))

Sheet INSUMOS
A1: CATÁLOGO DE INSUMOS
A2: PROYECTO | C2: =CARATULA!$C$10
A3: CLIENTE | C3: =CARATULA!$C$12
A4: UBICACIÓN | C4: =CARATULA!$C$14
A5: EMPRESA | C5: =CARATULA!$C$19
A6: Materiales, mano de obra, herramienta e indirectos. Cambiar un precio aquí recalcula TODAS las tarjetas que lo usan.
A8: ID | B8: TIPO | C8: DESCRIPCIÓN | D8: UNIDAD | E8: COSTO UNITARIO | F8: PROVEEDOR | G8: ÚLTIMA ACTUALIZ. | H8: NOTAS
A9: MAT-0001 | B9: material | C9: Cemento gris tipo I, saco de 50 kg | D9: bulto
A10: MAT-0002 | B10: material | C10: Arena de río | D10: m³
A11: MAT-0003 | B11: material | C11: Grava de 3/4" | D11: m³
A12: MAT-0004 | B12: material | C12: Varilla corrugada #3 (3/8") | D12: kg
A13: MAT-0005 | B13: material | C13: Varilla corrugada #4 (1/2") | D13: kg
A14: MAT-0006 | B14: material | C14: Alambrón #2 para estribos | D14: kg
A15: MAT-0007 | B15: material | C15: Armex 15-20-4 | D15: ml
A16: MAT-0008 | B16: material | C16: Armex 15-25-4 | D16: ml
A17: MAT-0009 | B17: material | C17: Malla electrosoldada 6-6/10-10 | D17: m²
A18: MAT-0010 | B18: material | C18: Block Novaceramic Tabimax | D18: pza
A19: MAT-0011 | B19: material | C19: Vigueta armada | D19: ml
A20: MAT-0012 | B20: material | C20: Bovedilla de poliestireno H=25 | D20: pza
... A26: MAT-0018 | B26: material | C26: Tubería CPVC 3/4" | D26: ml
A27: MO-001 | B27: mano_obra | C27: Maestro albañil | D27: jornada | E27: 666.67 | H27: $4,000 por semana · FASAR 1.00
A28: MO-002 | B28: mano_obra | C28: Oficial albañil | D28: jornada | E28: 583.33 | H28: $3,500 por semana
A29: MO-003 | B29: mano_obra | C29: Fierrero | D29: jornada | E29: 583.33 | H29: $3,500 por semana
A30: MO-004 | B30: mano_obra | C30: Ayudante | D30: jornada | E30: 466.67 | H30: $2,800 por semana · actualizado 27-jul
A31: MO-005 | B31: mano_obra | C31: Plomero / electricista | D31: jornada | H31: Maestro Jorge
A32: HER-0001 | B32: herramienta | C32: Cortadora de piso walk-behind | D32: día | F32: Renta Maq. Rivas | H32: Precio SIN IVA
A33: HER-0002 | B33: herramienta | C33: Martillo demoledor eléctrico 30 kg | D33: día | F33: Renta Maq. Rivas | H33: Precio SIN IVA
A34: HER-0003 | B34: herramienta | C34: Revolvedora de 1 saco | D34: día
A35: HER-0004 | B35: herramienta | C35: Vibrador de concreto | D35: día
A36: HER-0005 | B36: herramienta | C36: Andamio tubular, cuerpo | D36: día
A37: HER-0006 | B37: herramienta | C37: Bailarina compactadora | D37: día
A38: IND-001 | B38: indirecto | C38: EPP de cuadrilla | D38: % | E38: 3 | H38: Factor: % mano de obra
A39: IND-002 | B39: indirecto | C39: Trabajo en altura mayor a 3 m | D39: % | H39: Factor: % mano de obra
A40: IND-003 | B40: indirecto | C40: Derecho de tiro de escombro | D40: lote | H40: Factor: por concepto
A41: IND-004 | B41: indirecto | C41: Desgaste de vehículo y suministro | D41: % | H41: Factor: % total
A42: IND-005 | B42: indirecto | C42: Agua para obra | D42: día | H42: Factor: por día
C44: Renglón en rojo = insumo sin costo capturado. Se tolera, pero el concepto que lo use saldrá barato.

Sheet CARATULA
D2: PRESUPUESTO Y CONTROL DE OBRA
D4: DEPARTAMENTOS F-19 · OPCIÓN A · PLANTA BAJA
B8: DATOS GENERALES DEL PROYECTO · se capturan AQUÍ · las demás pestañas los llaman por fórmula | F8: PARÁMETROS ECONÓMICOS
B9: ID BIM / PROYECTO | C9: PRY-0001 | F9: % UTILIDAD | H9: 0.2
B10: NOMBRE DEL PROYECTO | C10: DEPARTAMENTOS F-19 | F10: % IVA | H10: 0
B11: CONTENEDOR / PRESUPUESTO | C11: Presupuesto General · OPCIÓN A · SOLO PLANTA BAJA | F11: % ANTICIPO | H11: 0.75
B12: CLIENTE | C12: FELIPE ORTEGA MUÑOZ | F12: % FINIQUITO | H12: 0.25
B13: REPRESENTANTE DEL CLIENTE | C13: Felipe Ortega Muñoz — PROPIEDAD | F13: VIGENCIA (días naturales) | H13: 7
B14: UBICACIÓN | C14: Av. 19 Poniente 705, Centro Histórico, Puebla | F14: SEMANAS DE PROGRAMA | H14: 27
B15: FOLIO CATASTRAL | C15: CA 17/022
B16: SUPERFICIE DEL PREDIO (m²) | C16: 81.24 | F16: Cambiar % UTILIDAD o % IVA recalcula TODOS los precios unitarios.
B17: SUPERFICIE CONSTRUIDA (m²) | C17: 81.24 | F17: La fecha de inicio DEBE ser lunes: de ella depende el corte semanal.
B18: NIVELES A CONSTRUIR (N) | C18: 1
B19: EMPRESA | C19: DRAVYA ESTUDIO DE ARQUITECTURA | F19: Precios vigentes 7 días naturales desde la fecha de emisión. Pasado ese plazo los precios de materiales y mano de obra se revisan antes de contratar.
B20: ELABORÓ | C20: MARIA FERNANDA GARCIA | F20: ROLES Y AUTORIZACIONES
B21: REVISÓ | C21: SERGIO GARCIA | F21: ROL | H21: NOMBRE | J21: QUÉ AUTORIZA
B22: APROBÓ | C22: STEFANNO PASCUALLI | F22: Residente de obra | H22: =$C$23 | J22: Levanta la requisición
B23: RESIDENTE DE OBRA | C23: STEFANNO PASCUALLI | F23: Supervisor de obra | J23: Valida la requisición
B24: VERSIÓN DE PRESUPUESTO | C24: V11 | F24: Coordinador de proyectos | H24: =$C$21 | J24: Solicitada → Aprobada
B25: REVISIÓN DE PROYECTO | C25: REV.04 | F25: Administrador de finanzas | J25: Aprobada → Pagada
B26: FECHA DE EMISIÓN | C26: 46238 | F26: ETAPA BIM ACTUAL | H26: OB · Obra en ejecución
B27: FECHA DE INICIO DE OBRA | C27: 46244
B28: FECHA DE CORTE DEL CONTROL | C28: 46238
F29: ESQUEMA DE COBRANZA · los tramos los define el cronograma, no una fecha
B30: RESUMEN EJECUTIVO · se calcula solo desde las demás pestañas | F30: PAGO | G30: % | H30: MONTO | I30: SEMANA DE CORTE | J30: COBRADO | K30: SALDO
B31: SUBTOTAL COSTO DIRECTO | D31: =PRESUPUESTO!$C$197 | F31: ANTICIPO DE OBRA | G31: 0.6 | H31: =$D$33*$G31 | I31: =IFERROR(MATCH($D$33*SUM($G$31:$G31),'FLUJO SEMANAL'!$D$148:$AD$148,1)+1,"—") | J31: =SUMIF($H$38:$H$49,$F31,$G$38:$G$49) | K31: =$H31-$J31
B32: IVA APLICADO | D32: =PRESUPUESTO!$C$198 | F32: SEGUNDO PAGO | G32: 0.2 | H32: =$D$33*$G32 | I32: =IFERROR(MATCH($D$33*SUM($G$31:$G32),'FLUJO SEMANAL'!$D$148:$AD$148,1)+1,"—") | J32: =SUMIF($H$38:$H$49,$F32,$G$38:$G$49) | K32: =$H32-$J32
B33: TOTAL DEL PRESUPUESTO | D33: =PRESUPUESTO!$E$197 | F33: FINIQUITO | G33: 0.2 | H33: =$D$33*$G33 | I33: =IFERROR(MATCH($D$33*SUM($G$31:$G33),'FLUJO SEMANAL'!$D$148:$AD$148,1)+1,"—") | J33: =SUMIF($H$38:$H$49,$F33,$G$38:$G$49) | K33: =$H33-$J33
B34: ANTICIPO A SOLICITAR | D34: =$D$33*$H$11 | F34: SUMA DE PORCENTAJES | G34: =SUM($G$31:$G$33) | H34: =IF(ROUND($G$34,4)=1,"CORRECTO","⚠ DEBE SUMAR 100%") | J34: =SUM($J$31:$J$33) | K34: =SUM($K$31:$K$33)
B35: FINIQUITO | D35: =$D$33*$H$12
B36: PRECIO POR m² CONSTRUIDO | D36: =IFERROR($D$33/$C$17,0) | F36: PARCIALIDADES RECIBIDAS · el cliente casi nunca paga el tramo completo de una vez
B37: VIGENCIA DE LA COTIZACIÓN | D37: =$C$26+$H$13 | F37: FECHA | G37: MONTO | H37: SE APLICA A | I37: FORMA DE PAGO | J37: FOLIO MOVIMIENTO | K37: NOTAS
B38: AVANCE PONDERADO DE OBRA | D38: =CRONOGRAMA!$I$148 | G38: =IF($F38="","",INT(($F38-$C$27)/7)+1)
B39: IMPORTE EJECUTADO | D39: ='CONTROL DE OBRA'!$H$147 | G39: =IF($F39="","",INT(($F39-$C$27)/7)+1)
B40: IMPORTE POR EJECUTAR | D40: ='CONTROL DE OBRA'!$K$147 | G40: =IF($F40="","",INT(($F40-$C$27)/7)+1)
B41: CONCEPTOS EN EL CATÁLOGO | D41: =COUNTIF(PRESUPUESTO!$C$10:$C$174,">0") | G41: =IF($F41="","",INT(($F41-$C$27)/7)+1)
G42: =IF($F42="","",INT(($F42-$C$27)/7)+1)
B43: RESUMEN POR PARTIDAS | G43: =IF($F43="","",INT(($F43-$C$27)/7)+1)
B44: PARTIDA | C44: IMPORTE | D44: % | G44: =IF($F44="","",INT(($F44-$C$27)/7)+1)
B45: =PRESUPUESTO!$A$10 | C45: =PRESUPUESTO!$G$10 | D45: =IFERROR($C45/$D$31,0) | G45: =IF($F45="","",INT(($F45-$C$27)/7)+1)
B46: =" "&PRESUPUESTO!$A$11 | C46: =PRESUPUESTO!$G$11 | D46: =IFERROR($C46/$D$31,0) | G46: =IF($F46="","",INT(($F46-$C$27)/7)+1)
B47: =" "&PRESUPUESTO!$A$20 | C47: =PRESUPUESTO!$G$20 | D47: =IFERROR($C47/$D$31,0) | G47: =IF($F47="","",INT(($F47-$C$27)/7)+1)
B48: =" "&PRESUPUESTO!$A$23 | C48: =PRESUPUESTO!$G$23 | D48: =IFERROR($C48/$D$31,0) | G48: =IF($F48="","",INT(($F48-$C$27)/7)+1)
B49: =" "&PRESUPUESTO!$A$26 | C49: =PRESUPUESTO!$G$26 | D49: =IFERROR($C49/$D$31,0) | G49: =IF($F49="","",INT(($F49-$C$27)/7)+1)
B50: =" "&PRESUPUESTO!$A$30 | C50: =PRESUPUESTO!$G$30 | D50: =IFERROR($C50/$D$31,0) | F50: TOTAL RECIBIDO | G50: =SUM($G$38:$G$49)
B51: =" "&PRESUPUESTO!$A$39 | C51: =PRESUPUESTO!$G$39 | D51: =IFERROR($C51/$D$31,0)
B52: =" "&PRESUPUESTO!$A$42 | C52: =PRESUPUESTO!$G$42 | D52: =IFERROR($C52/$D$31,0) | F52: HITOS DEL PROYECTO · el hito que marca la diferencia siempre es cuándo nos pagan
B53: =" "&PRESUPUESTO!$A$45 | C53: =PRESUPUESTO!$G$45 | D53: =IFERROR($C53/$D$31,0) | F53: HITO | H53: ETAPA | I53: MONTO | J53: ESTADO | K53: FECHA
B54: =PRESUPUESTO!$A$48 | C54: =PRESUPUESTO!$G$48 | D54: =IFERROR($C54/$D$31,0) | F54: Anticipo de proyecto arquitectónico | H54: AP | J54: Cobrado
B55: =" "&PRESUPUESTO!$A$49 | C55: =PRESUPUESTO!$G$49 | D55: =IFERROR($C55/$D$31,0) | F55: Finiquito arquitectónico + parciales de ejecutivo y estructural | H55: PE | J55: Cobrado
B56: =" "&PRESUPUESTO!$A$51 | C56: =PRESUPUESTO!$G$51 | D56: =IFERROR($C56/$D$31,0) | F56: ANTICIPO DE OBRA | H56: OB | J56: Pendiente
B57: =" "&PRESUPUESTO!$A$54 | C57: =PRESUPUESTO!$G$54 | D57: =IFERROR($C57/$D$31,0) | F57: Segundo pago de obra | H57: OB | J57: Pendiente
B58: =" "&PRESUPUESTO!$A$56 | C58: =PRESUPUESTO!$G$56 | D58: =IFERROR($C58/$D$31,0) | F58: Finiquito de obra | H58: OB | J58: Pendiente
B59: =" "&PRESUPUESTO!$A$67 | C59: =PRESUPUESTO!$G$67 | D59: =IFERROR($C59/$D$31,0) | F59: Carta entrega y cierre | H59: AS | J59: Pendiente
B60: =" "&PRESUPUESTO!$A$80 | C60: =PRESUPUESTO!$G$80 | D60: =IFERROR($C60/$D$31,0)
B61: =" "&PRESUPUESTO!$A$100 | C61: =PRESUPUESTO!$G$100 | D61: =IFERROR($C61/$D$31,0)
B62: =" "&PRESUPUESTO!$A$102 | C62: =PRESUPUESTO!$G$102 | D62: =IFERROR($C62/$D$31,0) | F62: POSICIÓN FINANCIERA DEL PROYECTO
B63: =" "&PRESUPUESTO!$A$114 | C63: =PRESUPUESTO!$G$114 | D63: =IFERROR($C63/$D$31,0) | F63: COBRADO A LA FECHA | H63: =SUMIFS(MOVIMIENTOS!$H$9:$H$508,MOVIMIENTOS!$D$9:$D$508,"Ingreso")
B64: =" "&PRESUPUESTO!$A$119 | C64: =PRESUPUESTO!$G$119 | D64: =IFERROR($C64/$D$31,0) | F64: POR COBRAR | H64: =$D$33-$H$63
B65: =PRESUPUESTO!$A$123 | C65: =PRESUPUESTO!$G$123 | D65: =IFERROR($C65/$D$31,0) | F65: GASTADO A LA FECHA | H65: =SUMIFS(MOVIMIENTOS!$H$9:$H$508,MOVIMIENTOS!$D$9:$D$508,"Egreso")
B66: =" "&PRESUPUESTO!$A$124 | C66: =PRESUPUESTO!$G$124 | D66: =IFERROR($C66/$D$31,0) | F66: CAJA DEL PROYECTO | H66: =$H$63-$H$65
B67: =PRESUPUESTO!$A$127 | C67: =PRESUPUESTO!$G$127 | D67: =IFERROR($C67/$D$31,0) | F67: % DE AVANCE COBRADO | H67: =IFERROR($H$63/$D$33,0)
B68: =" "&PRESUPUESTO!$A$128 | C68: =PRESUPUESTO!$G$128 | D68: =IFERROR($C68/$D$31,0)
B69: =" "&PRESUPUESTO!$A$136 | C69: =PRESUPUESTO!$G$136 | D69: =IFERROR($C69/$D$31,0) | F69: La caja en rojo significa que la obra la estás financiando tú.
B70: =" "&PRESUPUESTO!$A$138 | C70: =PRESUPUESTO!$G$138 | D70: =IFERROR($C70/$D$31,0)
B71: =" "&PRESUPUESTO!$A$140 | C71: =PRESUPUESTO!$G$140 | D71: =IFERROR($C71/$D$31,0)
B72: =PRESUPUESTO!$A$142 | C72: =PRESUPUESTO!$G$142 | D72: =IFERROR($C72/$D$31,0)
B73: =" "&PRESUPUESTO!$A$143 | C73: =PRESUPUESTO!$G$143 | D73: =IFERROR($C73/$D$31,0)
B74: =" "&PRESUPUESTO!$A$159 | C74: =PRESUPUESTO!$G$159 | D74: =IFERROR($C74/$D$31,0)
B75: SUBTOTAL COSTO DIRECTO | C75: =$D$31

Sheet PRESUPUESTO
A1: =CARATULA!C11 | M1: Ambos se capturan en la CARÁTULA y afectan TODOS los precios unitarios.
A3: =CARATULA!$C$10 | M3: % UTILIDAD | O3: =CARATULA!H9
A4: UBICACIÓN | B4: =CARATULA!$C$14 | M4: % IVA | O4: =CARATULA!H10
M6: AQUI SE EDITAN LOS PRECIOS UNITARIOS
A7: CLIENTE | B7: =CARATULA!$C$12 | C7: =CARATULA!B9 | D7: =CARATULA!C9 | E7: FECHA | F7: =TODAY()
A9: CLAVE | B9: DESCRIPCIÓN DEL CONCEPTO | C9: CANTIDAD | D9: UNIDAD | E9: P. UNITARIO | F9: IVA | G9: TOTAL | I9: NOTAS | K9: NOTASAS REV-01 | M9: P.U. BASE | N9: MÓDULO | O9: LLAVE
A10: PRELIMINARES, DESMANTELAMIENTOS Y DEMOLICIONES | G10: =G11+G20+G23+G26+G30+G39+G42+G45
A11: PRELIMINARES | G11: =SUM(G12:G19)
A12: PRE02233 | B12: TRAZO Y NIVELACIÓN DEL ÁREA A CONSTRUIR: TRAZO Y NIVELACIÓN DE PLATAFORMA SEGÚN LOS NIVELES DE DESPLANTE DEL PROYECTO, SOBRE LA TOTALIDAD DEL PREDIO DE CASA 2 (81.24 M² DE DESPLANTE). INCLUYE HILO, ESTACAS, CRUCETAS DE MADERA, NIVEL, EQUIPO TOPOGRÁFICO, HERRAMIENTA MENOR, MANO DE OBRA Y EQUIPO DE PROTECCIÓN PERSONAL. | C12: 81.24 | D12: m² | E12: =IF($M12="","",$M12*(1+$O$3)) | F12: =IF($E12="","",$E12*$O$4) | G12: =IF(OR($C12="",$E12=""),"",$C12*$E12) | I12: Superficie de desplante del proyecto según cuadro de áreas del plano A-01. Se ejecuta después del tapial y antes de la demolición. | M12: 28 | N12: M1 | O12: =A12&"|"&N12
A13: PRE02234 | B13: TAPIAL PROVISIONAL PERIMETRAL: SUMINISTRO Y COLOCACIÓN DE TAPIAL PROVISIONAL A BASE DE POLÍN DE MADERA, FORRADO CON MALLA ELECTROSOLDADA (ARMEX) Y CORTINA DE PLÁSTICO NEGRO CALIBRE 600, CON PUERTA DE ACCESO DE MADERA Y CANDADO, PARA DELIMITAR LA ZONA DE OBRA DE CASA 2 SOBRE EL PASO DE SERVIDUMBRE DE LA VECINDAD. INCLUYE MATERIAL, HERRAMIENTA MENOR, MANO DE OBRA Y EQUIPO DE PROTECCIÓN PERSONAL. 12 ml sobre el frente que da al paso de servidumbre de 3.00 m de ancho. | C13: 13 | D13: ml | E13: =IF($M13="","",$M13*(1+$O$3)) | F13: =IF($E13="","",$E13*$O$4) | G13: =IF(OR($C13="",$E13=""),"",$C13*$E13) | M13: 300 | N13: M1 | O13: =A13&"|"&N13
A14: PRE02235 | B14: MURETE PROVISIONAL DE OBRA: FABRICACIÓN DE MURETE PROVISIONAL DE MADERA (POSTE, TABLA Y CLAVOS) ADOSADO AL TAPIAL, PARA ALOJAR EL INTERRUPTOR TERMOMAGNÉTICO DE OBRA Y EL RACK DE CONTACTOS DE USO RUDO. INCLUYE MATERIAL ELÉCTRICO, HERRAMIENTA MENOR, MANO DE OBRA Y EQUIPO DE PROTECCIÓN PERSONAL. | C14: 1 | D14: pza | E14: =IF($M14="","",$M14*(1+$O$3)) | F14: =IF($E14="","",$E14*$O$4) | G14: =IF(OR($C14="",$E14=""),"",$C14*$E14) | I14: Se construye inmediatamente después del corte de la acometida eléctrica existente, como parte de la misma maniobra de desmantelamiento. Es la fuente de energía para toda la obra. | M14: 1000 | N14: M1 | O14: =A14&"|"&N14
A15: PRE02227 | B15: TRÁMITE Y OBTENCIÓN DE AUTORIZACIÓN MUNICIPAL PARA DERRIBO DE ARBOL: INTEGRACIÓN DE EXPEDIENTE, LEVANTAMIENTO FOTOGRÁFICO, DICTAMEN, INGRESO ANTE LA AUTORIDAD Y SEGUIMIENTO HASTA LA RESOLUCIÓN. NO INCLUYE EL PAGO DE DERECHOS NI LA COMPENSACIÓN AMBIENTAL QUE FIJE LA AUTORIDAD. INCLUYE MATERIAL, HERRAMIENTA MENOR, MANO DE OBRA Y EQUIPO DE PROTECCIÓN PERSONAL. | C15: 1 | D15: lote | E15: =IF($M15="","",$M15*(1+$O$3)) | F15: =IF($E15="","",$E15*$O$4) | G15: =IF(OR($C15="",$E15=""),"",$C15*$E15) | I15: CONCEPTO NUEVO REVISAR | M15: 1 | N15: M1 | O15: =A15&"|"&N15
A16: PRE02228 | B16: DERRIBO CONTROLADO DE ÁRBOL POR SECCIONES: DESRAME PROGRESIVO DE ARRIBA HACIA ABAJO, CORTE DEL FUSTE EN TRAMOS CON DESCUELGUE CONTROLADO POR CUERDA, PROTECCIÓN DE MUROS COLINDANTES Y DE LAS PROPIEDADES VECINAS. INCLUYE MOTOSIERRA, CUERDAS, ARNÉS, ESCALERA O ANDAMIO Y SEÑALIZACIÓN. INCLUYE MATERIAL, HERRAMIENTA MENOR, MANO DE OBRA Y EQUIPO DE PROTECCIÓN PERSONAL. | C16: 1 | D16: pza | E16: =IF($M16="","",$M16*(1+$O$3)) | F16: =IF($E16="","",$E16*$O$4) | G16: =IF(OR($C16="",$E16=""),"",$C16*$E16) | I16: CONCEPTO NUEVO REVISAR | M16: 1000 | N16: M1 | O16: =A16&"|"&N16
A17: PRE02229 | B17: DESTOCONADO Y EXTRACCIÓN DE RAÍZ: EXCAVACIÓN PERIMETRAL, CORTE DE RAÍZ PRINCIPAL Y SECUNDARIA, EXTRACCIÓN DEL TOCÓN Y LIMPIEZA DEL HUECO. INCLUYE MATERIAL, HERRAMIENTA MENOR, MANO DE OBRA Y EQUIPO DE PROTECCIÓN PERSONAL. | C17: 1 | D17: pza | E17: =IF($M17="","",$M17*(1+$O$3)) | F17: =IF($E17="","",$E17*$O$4) | G17: =IF(OR($C17="",$E17=""),"",$C17*$E17) | I17: CONCEPTO NUEVO REVISAR | M17: 1500 | N17: M1 | O17: =A17&"|"&N17
A18: PRE02230 | B18: RELLENO Y COMPACTACIÓN DEL HUECO DE TOCÓN CON MATERIAL DE BANCO EN CAPAS HÚMEDAS DE 20 CM, HASTA ALCANZAR EL NIVEL DE DESPLANTE DE PROYECTO. INCLUYE MATERIAL, HERRAMIENTA MENOR, MANO DE OBRA Y EQUIPO DE PROTECCIÓN PERSONAL. | C18: 4 | D18: m³ | E18: =IF($M18="","",$M18*(1+$O$3)) | F18: =IF($E18="","",$E18*$O$4) | G18: =IF(OR($C18="",$E18=""),"",$C18*$E18) | I18: CONCEPTO NUEVO REVISAR | M18: 320 | N18: M1 | O18: =A18&"|"&N18
A19: PRE02231 | B19: TROCEADO, CARGA Y RETIRO DE RESIDUO VEGETAL A TIRO AUTORIZADO: TRONCO, RAMA Y FOLLAJE, CON ACARREO MANUAL HASTA PIE DE CALLE Y VIAJE EN CAMIÓN. INCLUYE MATERIAL, HERRAMIENTA MENOR, MANO DE OBRA Y EQUIPO DE PROTECCIÓN PERSONAL. | C19: 1 | D19: viaje | E19: =IF($M19="","",$M19*(1+$O$3)) | F19: =IF($E19="","",$E19*$O$4) | G19: =IF(OR($C19="",$E19=""),"",$C19*$E19) | I19: CONCEPTO NUEVO REVISAR | M19: 900 | N19: M1 | O19: =A19&"|"&N19
A20: DESMANTELACIONES | G20: =SUM(G21:G22)
A21: DIS07123 | B21: DESMANTELAMIENTO DE LÍNEA ELÉCTRICA DE ALIMENTACIÓN DE DEPARTAMENTOS COLINDANTES: DESMANTELAMIENTO DE LA LÍNEA ELÉCTRICA DE ALIMENTACIÓN EXISTENTE, TENDIDA EXPUESTA SOBRE EL MURO DE LA VIVIENDA A DEMOLER, QUE DA SERVICIO A CASA 2 (EL PROYECTO), CASA 3 Y CASA 4 SEGÚN CROQUIS DEL TÍTULO DE PROPIEDAD, FOLIO CATASTRAL CA 17/022, A UNA ALTURA NO MAYOR A 3 METROS. INCLUYE CORTE DE PUNTAS EN EL PUNTO DE HABILITACIÓN, RETIRO DE CABLEADO Y TUBERÍA VISIBLE, CANCELACIÓN DE LA ACOMETIDA PROPIA, HERRAMIENTA MENOR, MANO DE OBRA, ESCALERAS Y EQUIPO DE PROTECCIÓN PERSONAL. | C21: 1 | D21: lote | E21: =IF($M21="","",$M21*(1+$O$3)) | F21: =IF($E21="","",$E21*$O$4) | G21: =IF(OR($C21="",$E21=""),"",$C21*$E21) | M21: 2800.27 | N21: M1 | O21: =A21&"|"&N21
A22: DIS07124 | B22: DESMANTELAMIENTO DE LÍNEA HIDRÁULICA DE ALIMENTACIÓN DE DEPARTAMENTOS COLINDANTES: DESMANTELAMIENTO DE LA LÍNEA HIDRÁULICA DE ALIMENTACIÓN EXISTENTE, TENDIDA EXPUESTA SOBRE EL MURO DE LA VIVIENDA A DEMOLER, QUE DA SERVICIO A CASA 2 (EL PROYECTO), CASA 3 Y CASA 4 SEGÚN CROQUIS DEL TÍTULO DE PROPIEDAD, FOLIO CATASTRAL CA 17/022, A UNA ALTURA NO MAYOR A 3 METROS. INCLUYE INTERRUPCIÓN DESDE LA BOMBA DE LA CISTERNA, VACIADO Y DESCONEXIÓN DE TINACOS, CORTE Y RETIRO DE TUBERÍA VISIBLE, COLOCACIÓN DE TAPÓN PROVISIONAL EN LA SALIDA DE AGUA PROPIA, HERRAMIENTA MENOR, MANO DE OBRA, ESCALERAS Y EQUIPO DE PROTECCIÓN PERSONAL. | C22: 1 | D22: lote | E22: =IF($M22="","",$M22*(1+$O$3)) | F22: =IF($E22="","",$E22*$O$4) | G22: =IF(OR($C22="",$E22=""),"",$C22*$E22) | I22: El tapón en la salida propia queda colocado antes de la demolición. No incluye la línea nueva ni la reubicación de tinacos, que son conceptos separados. | M22: 2500.11 | N22: M1 | O22: =A22&"|"&N22
A23: INSTALACIONES ELÉCTRICAS | G23: =SUM(G24:G25)
A24: ELE12299 | B24: SALIDA ELÉCTRICA INDIVIDUAL DE ALIMENTACIÓN PARA DEPARTAMENTO COLINDANTE: SUMINISTRO E INSTALACIÓN DE LA SALIDA ELÉCTRICA FINAL POR DEPARTAMENTO, CON CONDUCTOR DE COBRE THHW CALIBRE 10 O 12 AWG, CHALUPA GALVANIZADA Y CONEXIÓN TERMINAL, PARA CASA 2 (EL PROYECTO), CASA 3 Y CASA 4 SEGÚN CROQUIS DEL TÍTULO DE PROPIEDAD, FOLIO CATASTRAL CA 17/022, A UNA ALTURA NO MAYOR A 3 METROS. INCLUYE MATERIAL, CABLEADO, ACCESORIOS, MANO DE OBRA Y EQUIPO DE PROTECCIÓN PERSONAL. | C24: 3 | D24: sal | E24: =IF($M24="","",$M24*(1+$O$3)) | F24: =IF($E24="","",$E24*$O$4) | G24: =IF(OR($C24="",$E24=""),"",$C24*$E24) | I24: Una salida por cada departamento afectado. Es el punto de conexión final, distinto del tendido troncal perimetral. | M24: 2600.26 | N24: M1 | O24: =A24&"|"&N24
A25: ELE12300 | B25: CIRCUITO TRONCAL DE ALIMENTACIÓN ELÉCTRICA PERIMETRAL: TENDIDO DE CIRCUITO TRONCAL DE ALIMENTACIÓN ELÉCTRICA NUEVA POR LA BARDA COLINDANTE AL PASO DE SERVIDUMBRE, CON TUBERÍA CONDUIT PVC DE 3/4" Y ABRAZADERAS DE SUJECIÓN, DESDE EL PUNTO DE HABILITACIÓN EXISTENTE HASTA CADA UNO DE LOS DEPARTAMENTOS DE CASA 2 (EL PROYECTO), CASA 3 Y CASA 4 SEGÚN CROQUIS DEL TÍTULO DE PROPIEDAD, FOLIO CATASTRAL CA 17/022. INCLUYE MATERIAL, HERRAMIENTA MENOR, MANO DE OBRA, ESCALERAS Y ANDAMIOS, Y EQUIPO DE PROTECCIÓN PERSONAL. | C25: 1 | D25: lote | E25: =IF($M25="","",$M25*(1+$O$3)) | F25: =IF($E25="","",$E25*$O$4) | G25: =IF(OR($C25="",$E25=""),"",$C25*$E25) | I25: Sustituye el trayecto actual que pasa tendido sobre la vivienda a demoler. Corre por la barda al mismo eje del paso de servidumbre. | M25: 3469.88 | N25: M1 | O25: =A25&"|"&N25
A26: INSTALACIONES HIDROSANITARIAS | G26: =SUM(G27:G29)
A27: HSI14089 | B27: SALIDA HIDRÁULICA NUEVA DE ALIMENTACIÓN PARA DEPARTAMENTO COLINDANTE: SUMINISTRO Y COLOCACIÓN DE SALIDA DE ALIMENTACIÓN NUEVA EN RED HIDRÁULICA CON TUBERÍA PPR DE 3/4" Y ABRAZADERAS DE SUJECIÓN, DESDE LA BOMBA DE LA CISTERNA HASTA EL TINACO DE CADA DEPARTAMENTO DE CASA 2 (EL PROYECTO), CASA 3 Y CASA 4 SEGÚN CROQUIS DEL TÍTULO DE PROPIEDAD, FOLIO CATASTRAL CA 17/022, A UNA ALTURA NO MAYOR A 3 METROS. INCLUYE MATERIAL, MANO DE OBRA, HERRAMIENTA MENOR, ESCALERAS Y EQUIPO DE PROTECCIÓN PERSONAL. | C27: 3 | D27: pza | E27: =IF($M27="","",$M27*(1+$O$3)) | F27: =IF($E27="","",$E27*$O$4) | G27: =IF(OR($C27="",$E27=""),"",$C27*$E27) | I27: Una salida por cada departamento afectado. Sustituye la línea desmantelada que pasaba sobre la vivienda a demoler. | M27: 1500.1 | N27: M1 | O27: =A27&"|"&N27
A28: HSI14093 | B28: REUBICACIÓN Y RECONEXIÓN DE TINACOS DE CASA COLINDANTE: REUBICACIÓN Y RECONEXIÓN DE TINACO DE LA CASA COLINDANTE A LA LÍNEA HIDRÁULICA NUEVA. INCLUYE DESMONTAJE, TRASLADO, MONTAJE SOBRE SU BASE, FIJACIÓN CON ABRAZADERAS, CONEXIÓN FINAL A LA LÍNEA NUEVA, HERRAMIENTA MENOR, MANO DE OBRA Y EQUIPO DE PROTECCIÓN PERSONAL. | C28: 1 | D28: lote | E28: =IF($M28="","",$M28*(1+$O$3)) | F28: =IF($E28="","",$E28*$O$4) | G28: =IF(OR($C28="",$E28=""),"",$C28*$E28) | I28: Precio unitario por lote. Corresponde a los 2 tinacos de la casa colindante inmediata. Los tinacos de los demás departamentos no se reubican. | M28: 600.09 | N28: M1 | O28: =A28&"|"&N28
A29: HSI14094 | B29: SUMINISTRO E INSTALACIÓN DE TUBERÍA PVC SANITARIO DE 4" AHOGADA EN RANURA, CON SUS CONEXIONES, PARA LA LÍNEA SANITARIA NUEVA QUE DA SERVICIO A CASA 2 (EL PROYECTO), CASA 3 Y CASA 4 SEGÚN CROQUIS DEL TÍTULO DE PROPIEDAD, FOLIO CATASTRAL CA 17/022, SUSTITUYENDO EL TRAYECTO EXISTENTE QUE PASA POR EL FRENTE DE LA VIVIENDA. INCLUYE TUBERÍA, CODOS, YEES, TEES, PEGAMENTO, NIVELACIÓN DE PENDIENTE, MATERIAL, HERRAMIENTA MENOR, MANO DE OBRA Y EQUIPO DE PROTECCIÓN PERSONAL. REGISTRO SANITARIO DE 40 X 60 X 100 CM: FABRICACIÓN DE REGISTRO SANITARIO DEL PROYECTO. INCLUYE PLANTILLA DE CONCRETO SIMPLE F'C=150 KG/CM² DE 5 CM DE PERALTE, MUROS DE TABIQUE RECOCIDO DE 7 X 14 X 28 CM JUNTEADOS CON MORTERO CEMENTO-ARENA 1:4, APLANADO CON ACABADO PULIDO AL INTERIOR, VÉRTICES RESUELTOS EN CHAFLÁN A 45 GRADOS, ARENERO DE 5 CM BAJO EL LECHO INFERIOR DE LOS TUBOS DE 4" PARA RETENCIÓN DE SEDIMENTOS, TAPA DE REGISTRO DE LA MISMA CALIDAD QUE LA PLANTILLA, EXCAVACIÓN, MATERIAL, HERRAMIENTA MENOR, MANO DE OBRA Y EQUIPO DE PROTECCIÓN PERSONAL. | C29: 18 | D29: ml | E29: =IF($M29="","",$M29*(1+$O$3)) | F29: =IF($E29="","",$E29*$O$4) | G29: =IF(OR($C29="",$E29=""),"",$C29*$E29) | I29: Sustituye el trayecto actual que cruza frente a la vivienda. La pendiente se nivela hacia el registro nuevo. El arenero de 5 cm deja los tubos de 4" elevados respecto del fondo de la plantilla, de modo que los sedimentos se depositen en ese espacio y no obstruyan el lecho inferior interior del tubo. Los chaflanes a 45 grados en los vértices evitan la acumulación en esquinas. | M29: 300 | N29: M1 | O29: =A29&"|"&N29
A30: DEMOLICIONES | G30: =SUM(G31:G38)
A31: DEM5027 | B31: CORTE DE LOSA DE AZOTEA A DEMOLER, CON CORTADORA DE PISO TIPO WALK-BEHIND Y DISCO DE DIAMANTE PARA CONCRETO, SOBRE EL LÍMITE DE COLINDANCIA CON LAS PROPIEDADES VECINAS, PARA DESCONECTAR LA TRANSMISIÓN DE CARGAS ANTES DE LA DEMOLICIÓN. TRABAJOS A UNA ALTURA A PARTIR DE 3 METROS. INCLUYE RENTA DE EQUIPO, DISCO DE CORTE, FLETE DE MAQUINARIA, HERRAMIENTA MENOR, MANO DE OBRA, ANDAMIOS, ARNÉS Y EQUIPO DE PROTECCIÓN PERSONAL CON PROTECCIÓN OCULAR, AUDITIVA Y RESPIRATORIA. | C31: 1 | D31: lote | E31: =IF($M31="","",$M31*(1+$O$3)) | F31: =IF($E31="","",$E31*$O$4) | G31: =IF(OR($C31="",$E31=""),"",$C31*$E31) | I31: Trabajo en azotea. El corte independiza la losa de cubierta de los dos muros laterales y el muro posterior, que son compartidos y se conservan. | M31: 2500 | N31: M1 | O31: =A31&"|"&N31
A32: DEM5028 | B32: CORTE DE LA LOSA DE PISO FIRME EXISTENTE, CON CORTADORA DE PISO TIPO WALK-BEHIND Y DISCO DE DIAMANTE PARA CONCRETO, SOBRE EL LÍMITE DE COLINDANCIA Y SOBRE EL TRAZO DE LAS TRINCHERAS CT-1 DE LA CIMENTACIÓN NUEVA. INCLUYE RENTA DE EQUIPO, DISCO DE CORTE, FLETE DE MAQUINARIA, HERRAMIENTA MENOR, MANO DE OBRA Y EQUIPO DE PROTECCIÓN PERSONAL CON PROTECCIÓN OCULAR, AUDITIVA Y RESPIRATORIA. | C32: 1 | D32: lote | E32: =IF($M32="","",$M32*(1+$O$3)) | F32: =IF($E32="","",$E32*$O$4) | G32: =IF(OR($C32="",$E32=""),"",$C32*$E32) | I32: Se ejecuta en la misma vuelta de renta que el corte de azotea. La losa de piso existente se conserva; el corte solo la independiza de los muros compartidos y abre el trazo de las trincheras. | M32: 1500 | N32: M1 | O32: =A32&"|"&N32
A33: DEM5029 | B33: DEMOLICIÓN DE MUROS INTERIORES DE TABICÓN DE 10 CM Y BLOCK DE 15 CM, MÁS EL MURO DE FACHADA DE 20 CM Y EL MURO POSTERIOR DE 16 CM DE LA VIVIENDA, A UNA ALTURA NO MAYOR A 3.40 METROS, CON MARTILLO DEMOLEDOR ELÉCTRICO Y HERRAMIENTA MANUAL. INCLUYE LEVANTADO DEL ESCOMBRO PRODUCTO DE LA DEMOLICIÓN Y SU ACOPIO DENTRO DE LA OBRA, RENTA DE EQUIPO, FLETE DE MAQUINARIA, HERRAMIENTA MENOR, MANO DE OBRA Y EQUIPO DE PROTECCIÓN PERSONAL. NO incluye los dos muros laterales ni el muro posterior del predio, que son compar- | C33: 76.06 | D33: m² | E33: =IF($M33="","",$M33*(1+$O$3)) | F33: =IF($E33="","",$E33*$O$4) | G33: =IF(OR($C33="",$E33=""),"",$C33*$E33) | I33: tidos con las propiedades colindantes y se conservan. Los acabados, instalaciones, muebles, puertas y ventanas se demuelen junto con los muros y no se cuantifican por separado. | M33: 80 | N33: M1 | O33: =A33&"|"&N33
A34: DEM5030 | B34: DEMOLICIÓN DE LA LOSA DE AZOTEA O CUBIERTA DE CONCRETO DE LA VIVIENDA, DE 12 CM DE ESPESOR, PREVIAMENTE CORTADA EN SU PERÍMETRO, CON MARTILLO DEMOLEDOR ELÉCTRICO. TRABAJOS A UNA ALTURA A PARTIR DE 3 METROS. INCLUYE LEVANTADO DEL ESCOMBRO Y SU ACOPIO DENTRO DE LA OBRA, RENTA DE EQUIPO, HERRAMIENTA MENOR, MANO DE OBRA, ANDAMIOS, ARNÉS Y EQUIPO DE PROTECCIÓN PERSONAL. | C34: 46.45 | D34: m² | E34: =IF($M34="","",$M34*(1+$O$3)) | F34: =IF($E34="","",$E34*$O$4) | G34: =IF(OR($C34="",$E34=""),"",$C34*$E34) | I34: Se demuele de adentro hacia afuera, dejando intactos los muros compartidos. Corresponde a los 50.43 m² de la huella de la vivienda por 12 cm de espesor. | M34: 80 | N34: M1 | O34: =A34&"|"&N34
A35: DEM5031 | B35: DEMOLICIÓN DE LA LOSA DE CONCRETO POBRE EXISTENTE EN EL PATIO EXTERIOR DE LA VIVIENDA, DE 8 CM DE ESPESOR, COMPRENDIDA ENTRE EL EJE POSTERIOR DE LA CONSTRUCCIÓN ACTUAL Y EL LÍMITE DEL PREDIO. INCLUYE LEVANTADO DEL ESCOMBRO Y SU ACOPIO DENTRO DE LA OBRA, HERRAMIENTA MENOR, MANO DE OBRA Y EQUIPO DE PROTECCIÓN PERSONAL. | C35: 29.26 | D35: m² | E35: =IF($M35="","",$M35*(1+$O$3)) | F35: =IF($E35="","",$E35*$O$4) | G35: =IF(OR($C35="",$E35=""),"",$C35*$E35) | I35: En esta zona no se conserva piso: se demuele para dar paso a la excavación y nivelación. | M35: 80 | N35: M1 | O35: =A35&"|"&N35
A36: DEM5032 | B36: RANURA EN EL PISO DE CONCRETO EXISTENTE EN PATIO, DE 40 CM DE ANCHO POR 60 CM DE PROFUNDIDAD, PARA ALOJAR LA LÍNEA SANITARIA NUEVA DE 4" QUE DA SERVICIO A CASA 2 (EL PROYECTO), CASA 3 Y CASA 4 SEGÚN CROQUIS DEL TÍTULO DE PROPIEDAD, FOLIO CATASTRAL CA 17/022. INCLUYE CORTE PREVIO, DEMOLICIÓN CON MARTILLO DEMOLEDOR ELÉCTRICO, LEVANTADO DEL ESCOMBRO PRODUCTO DEL CORTE Y SU ACOPIO DENTRO DE LA OBRA, RENTA DE EQUIPO, HERRAMIENTA MENOR, MANO DE OBRA Y EQUIPO DE PROTECCIÓN PERSONAL. | C36: 18.72 | D36: ml | E36: =IF($M36="","",$M36*(1+$O$3)) | F36: =IF($E36="","",$E36*$O$4) | G36: =IF(OR($C36="",$E36=""),"",$C36*$E36) | I36: La línea sanitaria actual pasa por el frente de la vivienda y es compartida con los departamentos del fondo. La ranura aloja el trayecto nuevo que sustituye al existente. | M36: 80 | N36: M1 | O36: =A36&"|"&N36
A37: DEM5033 | B37: DEMOLICIÓN Y RETIRO DE TINACOS DE FIBROCEMENTO (ASBESTO) EXISTENTES EN LA AZOTEA DE LA VIVIENDA A DEMOLER, CON HUMECTACIÓN PREVIA DE LA PIEZA PARA ABATIR LA EMISIÓN DE FIBRAS, EMBALAJE DEL RESIDUO EN PLÁSTICO DE CALIBRE GRUESO Y DISPOSICIÓN FINAL EN TIRADERO AUTORIZADO PARA RESIDUOS PELIGROSOS. TRABAJOS A UNA ALTURA A PARTIR DE 3 METROS. INCLUYE MATERIAL DE EMBALAJE, TRANSPORTE A TIRADERO AUTORIZADO, HERRAMIENTA MENOR, MANO DE OBRA, ANDAMIOS Y EQUIPO DE PROTECCIÓN PERSONAL CON PROTECCIÓN RESPIRATORIA. | C37: 2 | D37: pza | E37: =IF($M37="","",$M37*(1+$O$3)) | F37: =IF($E37="","",$E37*$O$4) | G37: =IF(OR($C37="",$E37=""),"",$C37*$E37) | I37: Corresponde a los 2 tinacos de fibrocemento propios de la vivienda a demoler. Trabajo de riesgo especial: el residuo no puede mezclarse con el escombro común ni disponerse en tiradero municipal. | M37: 800.43 | N37: M1 | O37: =A37&"|"&N37
A38: DEM5034 | B38: RETIRO DE LÁMINA DE FIBROCEMENTO (ASBESTO) EN TECHUMBRES DE LA VIVIENDA A DEMOLER, CON HUMECTACIÓN PREVIA PARA ABATIR LA EMISIÓN DE FIBRAS, EMBALAJE DEL RESIDUO EN PLÁSTICO DE CALIBRE GRUESO Y DISPOSICIÓN FINAL EN TIRADERO AUTORIZADO PARA RESIDUOS PELIGROSOS. TRABAJOS A UNA ALTURA A PARTIR DE 3 METROS. INCLUYE MATERIAL DE EMBALAJE, TRANSPORTE A TIRADERO AUTORIZADO, HERRAMIENTA MENOR, MANO DE OBRA, ANDAMIOS Y EQUIPO DE PROTECCIÓN PERSONAL CON PROTECCIÓN RESPIRATORIA. | C38: 4.73 | D38: m² | E38: =IF($M38="","",$M38*(1+$O$3)) | F38: =IF($E38="","",$E38*$O$4) | G38: =IF(OR($C38="",$E38=""),"",$C38*$E38) | I38: Mismo tratamiento de riesgo que los tinacos de fibrocemento. El residuo no puede mezclarse con el escombro común. | M38: 228.15 | N38: M1 | O38: =A38&"|"&N38
A39: ACARREOS | G39: =SUM(G40:G41)
A40: ARR6013 | B40: ACARREO DE ESCOMBRO DESDE EL CENTRO DE ACOPIO DENTRO DEL TAPIAL HASTA EL CAMIÓN DE VOLTEO A PIE DE CALLE, EN UN TRAMO APROXIMADO DE 25 METROS LINEALES POR EL PASO DE SERVIDUMBRE, INCLUYENDO LA CARGA MANUAL AL CAMIÓN. INCLUYE CARRETILLAS, HERRAMIENTA MENOR, MANO DE OBRA Y EQUIPO DE PROTECCIÓN PERSONAL. | C40: 38.97 | D40: m³ | E40: =IF($M40="","",$M40*(1+$O$3)) | F40: =IF($E40="","",$E40*$O$4) | G40: =IF(OR($C40="",$E40=""),"",$C40*$E40) | I40: Volumen suelto, con factor de abundamiento de 1.35 para demolición y 1.25 para material de excavación. El paso de servidumbre de 3.00 m impide el uso de maquinaria, por lo que el acarreo es manual. | M40: 150 | N40: M1 | O40: =A40&"|"&N40
A41: ARR06009 | B41: VIAJE DE ESCOMBRO A TIRO AUTORIZADO: RETIRO DEL ESCOMBRO EN CAMIÓN DE VOLTEO CON CAPACIDAD DE TOLVA DE 6 M³, HASTA TIRO AUTORIZADO, CON DISPOSICIÓN LEGAL DEL RESIDUO. INCLUYE RENTA DEL CAMIÓN, COMBUSTIBLE, OPERADOR Y DERECHO DE DESCARGA. | C41: 6 | D41: viaje | E41: =IF($M41="","",$M41*(1+$O$3)) | F41: =IF($E41="","",$E41*$O$4) | G41: =IF(OR($C41="",$E41=""),"",$C41*$E41) | I41: No incluye la carga al camión, que está considerada en el concepto de acarreo. Los viajes se estiman con base en el volumen de escombro calculado; en caso de generarse excedentes, se reportarán y facturarán conforme a los viajes realmente ejecutados. | M41: 1500 | N41: M1 | O41: =A41&"|"&N41
A42: EXCAVACIONES | G42: =SUM(G43:G44)
A43: EXV3018 | B43: EXCAVACIÓN DE ZANJAS Y TRINCHERAS PARA EL DESPLANTE DE LAS CONTRATRABES CT-1 Y LA LOSA DE CIMENTACIÓN DEL PROYECTO, SEGÚN TRAZO DEL PLANO ESTRUCTURAL ES-02, EN UNA LONGITUD TOTAL DE 89.10 ML DE TRINCHERA DE SECCIÓN 0.20 X 0.40 M. INCLUYE AFINE DE TALUDES, HERRAMIENTA MENOR, MANO DE OBRA Y EQUIPO DE PROTECCIÓN PERSONAL. 48.55 ml de CT-1 en colindancia más 40.55 ml de CT-1 central, según cuantificación | C43: 10.7 | D43: m³ | E43: =IF($M43="","",$M43*(1+$O$3)) | F43: =IF($E43="","",$E43*$O$4) | G43: =IF(OR($C43="",$E43=""),"",$C43*$E43) | I43: de la hoja ES-7. En la zona de la vivienda actual la trinchera atraviesa la losa existente, previamente cortada. | M43: 250.01 | N43: M1 | O43: =A43&"|"&N43
A44: EXV3019 | B44: NIVELACIÓN DEL TERRENO CON MEJORAMIENTO A BASE DE TEPETATE COMPACTADO AL 90% PROCTOR, APISONADO CON BAILARINA, HASTA ALCANZAR EL NIVEL DE DESPLANTE DE PROYECTO. INCLUYE EL TALUD EN CARTABÓN DE LAS CONTRATRABES DE CIMENTACIÓN, SUMINISTRO Y TENDIDO DEL TEPETATE, RENTA DE BAILARINA, COMBUSTIBLE, AGUA PARA COMPACTACIÓN, HERRAMIENTA MENOR, MANO DE OBRA Y EQUIPO DE PROTECCIÓN PERSONAL. | C44: 7.85 | D44: m³ | E44: =IF($M44="","",$M44*(1+$O$3)) | F44: =IF($E44="","",$E44*$O$4) | G44: =IF(OR($C44="",$E44=""),"",$C44*$E44) | I44: Aplica únicamente en la zona del patio exterior (29.26 m²), donde se demolió el concreto pobre. En la zona de la vivienda no aplica: la losa de cimentación nueva se cuela sobre la losa existente con membrana de polietileno cal. 600 de por medio. | M44: 400.26 | N44: M1 | O44: =A44&"|"&N44
A45: ALBAÑILERÍAS | G45: =SUM(G46:G47)
A46: ALB8209 | B46: RELLENO COMPACTADO Y FIRME DE CONCRETO SOBRE LA RANURA DE LA LÍNEA SANITARIA NUEVA, PARA RESTITUIR EL PISO AL NIVEL EXISTENTE. INCLUYE RELLENO CON MATERIAL PRODUCTO DE LA EXCAVACIÓN COMPACTADO EN CAPAS, FIRME DE CONCRETO, MATERIAL, HERRAMIENTA MENOR, MANO DE OBRA Y EQUIPO DE PROTECCIÓN PERSONAL. | C46: 10 | D46: ml | E46: =IF($M46="","",$M46*(1+$O$3)) | F46: =IF($E46="","",$E46*$O$4) | G46: =IF(OR($C46="",$E46=""),"",$C46*$E46) | I46: Se ejecuta después de probada la línea sanitaria nueva. Restituye el piso del paso de servidumbre para no dejar obstrucción a los vecinos. | M46: 250 | N46: M1 | O46: =A46&"|"&N46
A47: ALB08251 | B47: REGISTRO SANITARIO DE 40 X 60 X 100 CM: FABRICACIÓN DE REGISTRO SANITARIO DEL PROYECTO. INCLUYE PLANTILLA DE CONCRETO SIMPLE F'C=150 KG/CM² DE 5 CM DE PERALTE, MUROS DE TABIQUE ROJO RECOCIDO 7X14X28 JUNTEADO CON MORTERO CEMENTO-ARENA 1:4, APLANADO PULIDO INTERIOR, TAPA DE LA MISMA CALIDAD, VÉRTICES EN CHAFLÁN A 45° Y ARENERO DE 5 CM BAJO EL LECHO DE LOS TUBOS DE 4". INCLUYE MATERIAL, HERRAMIENTA MENOR, MANO DE OBRA Y EQUIPO DE PROTECCIÓN PERSONAL. | C47: 1 | D47: pza | E47: =IF($M47="","",$M47*(1+$O$3)) | F47: =IF($E47="","",$E47*$O$4) | G47: =IF(OR($C47="",$E47=""),"",$C47*$E47) | I47: Reclasificado a ALBAÑILERÍAS. ID provisional: se creó como concepto personalizado y nunca recibió clave del catálogo. | M47: 2000 | N47: M1 | O47: =A47&"|"&N47
A48: CIMENTACIÓN Y PLANTA BAJA | G48: =G49+G51+G54+G56+G67+G80+G100+G102+G114+G119
A49: PRELIMINARES | G49: =SUM(G50:G50)
A50: PRE02226 | B50: SUMINISTRO Y COLOCACIÓN DE CAPA DE POLIETILENO NEGRO CALIBRE 600 A MANERA DE PLANTILLA ENTRE EL TERRENO MEJORADO Y LA LOSA DE CIMENTACIÓN NUEVA PARA RECIBIR LA PARRILLA Y EL CONCRETO POSTERIOR, INCLUYE EL FORRADO DE LOS TRES MUROS COLINDANTES HASTA 1.20 M SOBRE EL NIVEL DEL MURO. INCLUYE MATERIAL, HERRAMIENTA MENOR, MANO DE OBRA Y EQUIPO DE PROTECCIÓN PERSONAL. | C50: 151.21 | D50: m² | E50: =IF($M50="","",$M50*(1+$O$3)) | F50: =IF($E50="","",$E50*$O$4) | G50: =IF(OR($C50="",$E50=""),"",$C50*$E50) | I50: Volumen corregido: incluye peralte de plantilla más 1.20 m sobre los dos muros laterales y el colindante trasero. Precio a costo directo, sin utilidad. | M50: 25 | N50: M2 | O50: =A50&"|"&N50
A51: CIMENTACIONES | G51: =SUM(G52:G53)
A52: CIM04004 | B52: LOSA DE CIMENTACIÓN CON CONTRATRABES INTEGRADAS: LOSA DE 15 CM DE ESPESOR CON PARRILLA EN AMBOS LECHOS, MALLA ELECTROSOLDADA 6-6/4-4 Y BASTONES DE 3/8" A CADA 20 CM; CONTRATRABE CENTRAL Y PERIMETRAL DE 20 X 40 CM, TODO CON CONCRETO F'C=250 KG/CM². INCLUYE HABILITADO Y ARMADO DE ACERO, SILLETAS, CIMBRA, DESCIMBRADO, COLADO, REGLEADO, VIBRADO Y CURADO. INCLUYE MATERIAL, HERRAMIENTA MENOR, MANO DE OBRA Y EQUIPO DE PROTECCIÓN PERSONAL. | C52: 75.65 | D52: m² | E52: =IF($M52="","",$M52*(1+$O$3)) | F52: =IF($E52="","",$E52*$O$4) | G52: =IF(OR($C52="",$E52=""),"",$C52*$E52) | I52: Concepto UNIFICADO: absorbe las contratrabes CT-1 de colindancia y central, que se eliminan como conceptos independientes. Se elimina también el punto de conexión al terreno mejorado: se decidió independizar la cimentación nueva de la existente para evitar quiebre y jalón. | M52: 1741.92 | N52: M2 | O52: =A52&"|"&N52
A53: CIM04005 | B53: SUMINISTRO Y APLICACIÓN DE IMPERMEABILIZANTE EN MUROS COLINDANTES EXISTENTES A BASE DE EMULSIÓN ASFÁLTICA FIBRATADA APLICADA FIBRATADA CON CEPILLO EN DOS CAPAS. INCLUYE MATERIAL, HERRAMIENTA MENOR, MANO DE OBRA Y EQUIPO DE PROTECCIÓN PERSONAL. | C53: =72.42*1.05 | D53: m² | E53: =IF($M53="","",$M53*(1+$O$3)) | F53: =IF($E53="","",$E53*$O$4) | G53: =IF(OR($C53="",$E53=""),"",$C53*$E53) | I53: Se elimina el cartón asfáltico del concepto y baja el precio. Solo aplica en muros colindantes, no bajo la losa. Volumen con 5% de desperdicio. | M53: 60 | N53: M2 | O53: =A53&"|"&N53
A54: DEMOLICIONES | G54: =SUM(G55:G55)
A55: DEM05035 | B55: DESTECATADO DE MUROS COLINDANTES EXISTENTES POR MEDIOS MANUALES, SIN AFECTAR LA ESTABILIDAD DEL MURO NI LA PROPIEDAD VECINA. INCLUYE ACARREO INTERNO AL ACOPIO, ANDAMIOS. INCLUYE MATERIAL, HERRAMIENTA MENOR, MANO DE OBRA Y EQUIPO DE PROTECCIÓN PERSONAL. | C55: 76.04 | D55: m² | E55: =IF($M55="","",$M55*(1+$O$3)) | F55: =IF($E55="","",$E55*$O$4) | G55: =IF(OR($C55="",$E55=""),"",$C55*$E55) | I55: Se eliminan las perforaciones de sangrado de humedad y el escarificado del muro de mampostería: no se ejecutan. | M55: 26 | N55: M2 | O55: =A55&"|"&N55
A56: ALBAÑILERÍAS | G56: =SUM(G57:G66)
A57: ALB08211 | B57: ACABADO CON MARMOLINA LAVADA EN ÁREA DE PATIO DE SERVICIO (ZONA DE BOILER), CON PENDIENTE HACIA LA BAJADA PLUVIAL. INCLUYE MATERIAL, HERRAMIENTA MENOR, MANO DE OBRA Y EQUIPO DE PROTECCIÓN PERSONAL. | C57: =1.45+2.73 | D57: m² | E57: =IF($M57="","",$M57*(1+$O$3)) | F57: =IF($E57="","",$E57*$O$4) | G57: =IF(OR($C57="",$E57=""),"",$C57*$E57) | I57: Concepto reorientado: da pendiente a la bajada pluvial del pequeño patio y patio de recámaras donde va el boiler. Verificar contra el plano sanitario REV.03. | K57: MODIFICADO | M57: 323.4 | N57: M2 | O57: =A57&"|"&N57
A58: ALB08212 | B58: C-1 COLUMNA DE SECCIÓN 15 X 30 CM Y ALTURA DE 2.50 M A NIVEL BAJO LECHO DE LOSA DE ENTREPISO, ARMADA SEGÚN DESPIECE DEL PLANO ESTRUCTURAL, CON CONCRETO F'C=250 KG/CM². INCLUYE HABILITADO Y ARMADO DE ACERO, CIMBRA Y DESCIMBRA, COLADO, VIBRADO, CURADO Y ANDAMIO. INCLUYE MATERIAL, HERRAMIENTA MENOR, MANO DE OBRA Y EQUIPO DE PROTECCIÓN PERSONAL. | C58: =4*2.5 | D58: ml | E58: =IF($M58="","",$M58*(1+$O$3)) | F58: =IF($E58="","",$E58*$O$4) | G58: =IF(OR($C58="",$E58=""),"",$C58*$E58) | I58: FALTA PRECIO: esta sección no aparece en la lista de precios acordada del 4-ago. Confirmar con el estructurista. | K58: PRECIO AGREGADO | M58: 569.38 | N58: M2 | O58: =A58&"|"&N58
A59: ALB08213 | B59: C-2 COLUMNA DE SECCIÓN 15 X 40 CM CON 4 VARILLAS DEL #4 Y ALTURA DE 2.50 M A NIVEL BAJO LECHO DE LOSA DE ENTREPISO, CON CONCRETO F'C=250 KG/CM². INCLUYE HABILITADO Y ARMADO DE ACERO, CIMBRA Y DESCIMBRA, COLADO, VIBRADO, CURADO Y ANDAMIO. INCLUYE MATERIAL, HERRAMIENTA MENOR, MANO DE OBRA Y EQUIPO DE PROTECCIÓN PERSONAL. | C59: 2.5 | D59: ml | E59: =IF($M59="","",$M59*(1+$O$3)) | F59: =IF($E59="","",$E59*$O$4) | G59: =IF(OR($C59="",$E59=""),"",$C59*$E59) | I59: FORMATO CONDICIONAL NO SE POR QUE SE VE TODO ROSA, REVISAR EN TODOS QUE YA ESTAN COMPLETOS POR QUE SE VE ROSA | M59: 782.5 | N59: M2 | O59: =A59&"|"&N59
A60: ALB08214 | B60: C-3 COLUMNA DE SECCIÓN 20 X 20 CM CON 4 VARILLAS DEL #4 Y ALTURA DE 2.50 M A NIVEL BAJO LECHO DE LOSA DE ENTREPISO, CON CONCRETO F'C=250 KG/CM². INCLUYE HABILITADO Y ARMADO DE ACERO, CIMBRA Y DESCIMBRA, COLADO, VIBRADO, CURADO Y ANDAMIO. INCLUYE MATERIAL, HERRAMIENTA MENOR, MANO DE OBRA Y EQUIPO DE PROTECCIÓN PERSONAL. | C60: 5 | D60: ml | E60: =IF($M60="","",$M60*(1+$O$3)) | F60: =IF($E60="","",$E60*$O$4) | G60: =IF(OR($C60="",$E60=""),"",$C60*$E60) | I60: FORMATO CONDICIONAL NO SE POR QUE SE VE TODO ROSA, REVISAR EN TODOS QUE YA ESTAN COMPLETOS POR QUE SE VE ROSA | M60: 622.12 | N60: M2 | O60: =A60&"|"&N60
A61: ALB08215 | B61: C-4 COLUMNA DE SECCIÓN 20 X 40 CM CON 8 VARILLAS DEL #4 Y ESTRIBOS DEL #3, ALTURA DE 2.50 M A NIVEL BAJO LECHO DE LOSA DE ENTREPISO, CON CONCRETO F'C=250 KG/CM². INCLUYE HABILITADO Y ARMADO DE ACERO, CIMBRA Y DESCIMBRA, COLADO, VIBRADO, CURADO Y ANDAMIO. INCLUYE MATERIAL, HERRAMIENTA MENOR, MANO DE OBRA Y EQUIPO DE PROTECCIÓN PERSONAL. | C61: 7.5 | D61: ml | E61: =IF($M61="","",$M61*(1+$O$3)) | F61: =IF($E61="","",$E61*$O$4) | G61: =IF(OR($C61="",$E61=""),"",$C61*$E61) | I61: FORMATO CONDICIONAL NO SE POR QUE SE VE TODO ROSA, REVISAR EN TODOS QUE YA ESTAN COMPLETOS POR QUE SE VE ROSA | M61: 820.5 | N61: M2 | O61: =A61&"|"&N61
A62: ALB08216 | B62: K-1 CASTILLO DE SECCIÓN 15 X 20 CM ARMADO CON ARMEX 15-20-4 MÁS 2 VARILLAS DEL #3, ALTURA DE 2.50 M A NIVEL BAJO LECHO DE LOSA DE ENTREPISO, CON CONCRETO F'C=250 KG/CM². INCLUYE HABILITADO, CIMBRA, COLADO, VIBRADO Y CURADO. INCLUYE MATERIAL, HERRAMIENTA MENOR, MANO DE OBRA Y EQUIPO DE PROTECCIÓN PERSONAL. | C62: =17*2.5 | D62: ml | E62: =IF($M62="","",$M62*(1+$O$3)) | F62: =IF($E62="","",$E62*$O$4) | G62: =IF(OR($C62="",$E62=""),"",$C62*$E62) | I62: El concreto se unifica a f'c=250 en todos los castillos, aunque el plano indique 200 en algunos. | M62: 520.65 | N62: M2 | O62: =A62&"|"&N62
A63: ALB08239 | B63: K-ESP CASTILLO ESPECIAL PARA BAJADAS SANITARIAS Y PLUVIALES, DE SECCIÓN 15 X 20 CM Y ALTURA DE 2.50 M A NIVEL BAJO LECHO DE LOSA DE ENTREPISO, ARMADO CON ARMEX 15-20-4 Y CONCRETO F'C=250 KG/CM², CON TUBO DE 4" AHOGADO EN SU INTERIOR. INCLUYE HABILITADO, CIMBRA, COLADO, VIBRADO Y CURADO. INCLUYE MATERIAL, HERRAMIENTA MENOR, MANO DE OBRA Y EQUIPO DE PROTECCIÓN PERSONAL. | C63: 7.5 | D63: ml | E63: =IF($M63="","",$M63*(1+$O$3)) | F63: =IF($E63="","",$E63*$O$4) | G63: =IF(OR($C63="",$E63=""),"",$C63*$E63) | I63: En el plano estas bajadas no traen nomenclatura: son las dos que van entre cada bajada BAN y BAP. Solo uno de esos castillos aloja el tubo de 4". | M63: 454.65 | N63: M2 | O63: =A63&"|"&N63
A64: ALB08217 | B64: MC-1 MURO DE CONCRETO ARMADO COLADO EN SITIO CON DOBLE MALLA Y CASTILLOS TIPO K, ARMADO SEGÚN DESPIECE DEL PLANO ESTRUCTURAL, CON CONCRETO F'C=250 KG/CM². INCLUYE HABILITADO Y ARMADO DE ACERO, CIMBRA A DOS CARAS, COLADO, VIBRADO Y CURADO. INCLUYE MATERIAL, HERRAMIENTA MENOR, MANO DE OBRA Y EQUIPO DE PROTECCIÓN PERSONAL. | C64: 2.5 | D64: ml | E64: =IF($M64="","",$M64*(1+$O$3)) | F64: =IF($E64="","",$E64*$O$4) | G64: =IF(OR($C64="",$E64=""),"",$C64*$E64) | I64: FORMATO CONDICIONAL NO SE POR QUE SE VE TODO ROSA, REVISAR EN TODOS QUE YA ESTAN COMPLETOS POR QUE SE VE ROSA | M64: 1249.72 | N64: M2 | O64: =A64&"|"&N64
A65: ALB08218 | B65: MC-2 MURO DE CONCRETO ARMADO DOBLE DE 1.30 X 0.20 M CON DOS COLUMNAS TIPO C Y ACERO DE REFUERZO DE 3/8", CON CONCRETO F'C=250 KG/CM². INCLUYE HABILITADO Y ARMADO DE ACERO, CIMBRA A DOS CARAS, COLADO, VIBRADO Y CURADO. INCLUYE MATERIAL, HERRAMIENTA MENOR, MANO DE OBRA Y EQUIPO DE PROTECCIÓN PERSONAL. | C65: 2.5 | D65: ml | E65: =IF($M65="","",$M65*(1+$O$3)) | F65: =IF($E65="","",$E65*$O$4) | G65: =IF(OR($C65="",$E65=""),"",$C65*$E65) | I65: FORMATO CONDICIONAL NO SE POR QUE SE VE TODO ROSA, REVISAR EN TODOS QUE YA ESTAN COMPLETOS POR QUE SE VE ROSA | M65: 1920.51 | N65: M2 | O65: =A65&"|"&N65
A66: ALB08219 | B66: MURO DE TABIQUE RECOCIDO ESTRUCTURAL DE CONCRETO ASENTADO CON MORTERO A PLOMO Y NIVEL, CON REFUERZO DE MALLA DE GALLINERO POR AMBAS CARAS. INCLUYE MATERIAL, REFUERZO Y HERRAMIENTA MENOR. NO INCLUYE APLANADO. INCLUYE MATERIAL, HERRAMIENTA MENOR, MANO DE OBRA Y EQUIPO DE PROTECCIÓN PERSONAL. | C66: 126.46 | D66: m² | E66: =IF($M66="","",$M66*(1+$O$3)) | F66: =IF($E66="","",$E66*$O$4) | G66: =IF(OR($C66="",$E66=""),"",$C66*$E66) | I66: Block estructural de concreto, no cerámico: confirmado por el estructurista. La malla de gallinero la recomendó él para controlar cuarteaduras por sismo. El aplanado se cobra por separado. | M66: 400 | N66: M2 | O66: =A66&"|"&N66
A67: INSTALACIONES ELÉCTRICAS | G67: =SUM(G68:G79)
A68: ELE12101 | B68: SALIDA ELÉCTRICA PARA CONTACTOS: COLOCACION DE TUBERÍA DE POLIFLEX DE 3/4", CABLEADO DEL #10 Y #12, CHALUPA, Y PONCHADO DE PUNTAS CONEXIÓN. INCLUYE CINTAS, TERMINALES, PONCHADOR, SOLDADURA DE ESTAÑO, HERRAMIENTA MENOR, MANO DE OBRA Y EQUIPO DE PROTECCIÓN PERSONAL. | C68: 16 | D68: sal | E68: =IF($M68="","",$M68*(1+$O$3)) | F68: =IF($E68="","",$E68*$O$4) | G68: =IF(OR($C68="",$E68=""),"",$C68*$E68) | I68: Precio de referencia ELE12083 · CASA 256. Falta cuantificar del plano eléctrico REV.03. | M68: 500 | N68: M2 | O68: =A68&"|"&N68
A69: ELE12102 | B69: SALIDA ELÉCTRICA PARA LUMINARIAS: COLOCACION DE TUBERÍA DE POLIFLEX DE 3/4", CABLEADO DEL #12 Y #14. INCLUYE CINTAS, TERMINALES, PONCHADOR, SOLDADURA DE ESTAÑO, HERRAMIENTA MENOR, MANO DE OBRA Y EQUIPO DE PROTECCIÓN PERSONAL. | C69: 18 | D69: sal | E69: =IF($M69="","",$M69*(1+$O$3)) | F69: =IF($E69="","",$E69*$O$4) | G69: =IF(OR($C69="",$E69=""),"",$C69*$E69) | I69: Precio de referencia ELE12087 · CASA 256. Falta cuantificar. | M69: 500 | N69: M2 | O69: =A69&"|"&N69
A70: ELE12103 | B70: SALIDA ELÉCTRICA PARA APAGADORES: COLOCACION DE TUBERÍA DE POLIFLEX DE 3/4", CABLEADO DEL #12 Y #14. INCLUYE CINTAS, TERMINALES, PONCHADOR, SOLDADURA DE ESTAÑO, HERRAMIENTA MENOR, MANO DE OBRA Y EQUIPO DE PROTECCIÓN PERSONAL. | C70: 9 | D70: sal | E70: =IF($M70="","",$M70*(1+$O$3)) | F70: =IF($E70="","",$E70*$O$4) | G70: =IF(OR($C70="",$E70=""),"",$C70*$E70) | I70: Precio de referencia ELE12088 · CASA 256. Falta cuantificar. | M70: 500 | N70: M2 | O70: =A70&"|"&N70
A71: ELE12104 | B71: SUMINSITRO E INSTALACION DE TABLERO QO2 EN MURETE DE MEDICION INCLUYE PASTILLAS TERMOMAGENTICAS, BALANCEO DE CARGAS, PRUEBAS DE CONTINUIDAD, MATERIAL, HERRAMIENTA MENOR, MANO DE OBRA Y EQUIPO DE PROTECCION PERSONAL EPP. | C71: 1 | D71: PZA | E71: =IF($M71="","",$M71*(1+$O$3)) | F71: =IF($E71="","",$E71*$O$4) | G71: =IF(OR($C71="",$E71=""),"",$C71*$E71) | M71: 800 | N71: M2 | O71: =A71&"|"&N71
A72: ELE12105 | B72: SUMINISTRO Y COLOCACIÓN DE RECEPTACULO PARA CONTACTO. INCLUYE MATERIAL, HERRAMIENTA MENOR, MANO DE OBRA Y EQUIPO DE PROTECCIÓN PERSONAL. | C72: =C68 | D72: pza | E72: =IF($M72="","",$M72*(1+$O$3)) | F72: =IF($E72="","",$E72*$O$4) | G72: =IF(OR($C72="",$E72=""),"",$C72*$E72) | I72: Precio ELE12085 · CASA 256. | M72: 140 | N72: M2 | O72: =A72&"|"&N72
A73: ELE12106 | B73: SUMINISTRO Y COLOCACIÓN DE APAGADOR. INCLUYE MATERIAL, HERRAMIENTA MENOR, MANO DE OBRA Y EQUIPO DE PROTECCIÓN PERSONAL. | C73: =C70 | D73: pza | E73: =IF($M73="","",$M73*(1+$O$3)) | F73: =IF($E73="","",$E73*$O$4) | G73: =IF(OR($C73="",$E73=""),"",$C73*$E73) | I73: Precio ELE12086 · CASA 256. | M73: 140 | N73: M2 | O73: =A73&"|"&N73
A74: ELE12107 | B74: COLOCACIÓN DE LUMINARIAS. INCLUYE ESCALERA, MATERIAL Y HERRAMIENTA. NO INCLUYE EL SUMINISTRO DE LA LUMINARIA. INCLUYE MATERIAL, HERRAMIENTA MENOR, MANO DE OBRA Y EQUIPO DE PROTECCIÓN PERSONAL. | C74: =C69 | D74: pza | E74: =IF($M74="","",$M74*(1+$O$3)) | F74: =IF($E74="","",$E74*$O$4) | G74: =IF(OR($C74="",$E74=""),"",$C74*$E74) | I74: Precio ELE12089 · CASA 256. El suministro de la luminaria lo define el cliente. | M74: 160 | N74: M2 | O74: =A74&"|"&N74
A75: ELE12108 | B75: INSTALACIÓN DE CIRCUITOS ELÉCTRICOS. COLOCACION DE CABRE CALIBRE INDICADO EN CUADRO DE CARGAS PARA CIRCUITO Y CABLE DESNUDO DE COBRE PARA TIERRA FISICA, PONCHADO, TERMINAL, IDENTIFICADO, INCLUYE CINTAS, CONSUMIBLES, FIJACION, BALANCEO, HERRAMIENTA MENOR, MANO DE OBRA Y EQUIPO DE PROTECCIÓN PERSONAL. | C75: 4 | D75: pza | E75: =IF($M75="","",$M75*(1+$O$3)) | F75: =IF($E75="","",$E75*$O$4) | G75: =IF(OR($C75="",$E75=""),"",$C75*$E75) | I75: Precio ELE12093 · CASA 256. | M75: 300 | N75: M2 | O75: =A75&"|"&N75
A76: ELE12109 | B76: SUMINISTRO E INSTALACIÓN DE TABLERO QO4 PARA ILUMINACIÓN Y CONTACTOS, CON PASTILLAS TERMOMAGNÉTICAS POR CIRCUITO, BALANCEO DE CARGAS, IDENTIFICACIÓN Y DIRECTORIO. INCLUYE PRUEBAS DE CONTINUIDAD. INCLUYE MATERIAL, HERRAMIENTA MENOR, MANO DE OBRA Y EQUIPO DE PROTECCIÓN PERSONAL. | C76: 1 | D76: pza | E76: =IF($M76="","",$M76*(1+$O$3)) | F76: =IF($E76="","",$E76*$O$4) | G76: =IF(OR($C76="",$E76=""),"",$C76*$E76) | I76: Precio ELE12090 · CASA 256. Un tablero por departamento. | M76: 800 | N76: M2 | O76: =A76&"|"&N76
A77: ELE12110 | B77: RE ACONDICIONAMIENTO DE ACOMETIDA DE BAJA TENSIÓN DEL MURETE DE MEDICIÓN AL TABLERO DEL DEPARTAMENTO APROX 36 M, CON TUBERÍA CONDUIT Y CABLE NUEVO DE CALIBRE SEGÚN CARGA. INCLUYE SOPORTERÍA, REGISTROS DE PASO Y AHOGADO EN LOSA Y MURO. SE CONSIDERAN 6 METROS DE COCA. INCLUYE MATERIAL, HERRAMIENTA MENOR, MANO DE OBRA Y EQUIPO DE PROTECCIÓN PERSONAL. | C77: 36 | D77: ml | E77: =IF($M77="","",$M77*(1+$O$3)) | F77: =IF($E77="","",$E77*$O$4) | G77: =IF(OR($C77="",$E77=""),"",$C77*$E77) | I77: Precio de referencia ELE12082 · CASA 256. Longitud estimada de 25 m del murete al tablero. | K77: SE MODIFICA EL PRECIO UNITARIO POR QUE NO SE SUMINISTRARA CABLE NUEVO HASTA NO VER LA CALIDAD DEL EXISTENTE | M77: 100 | N77: M2 | O77: =A77&"|"&N77
A78: ELE12111 | B78: ADECUACION Y MEJORAMIENTO DE BASE DE MEDICIÓN: BALANCE DE CARGAS DEL TABLERO, ANEXION DE TIERRA FÍSICA CON VARILLA COPPERWELD Y CONECTOR, INCLUYE PRUEBAS. INCLUYE MATERIAL, HERRAMIENTA MENOR, MANO DE OBRA Y EQUIPO DE PROTECCIÓN PERSONAL. | C78: 0.2 | D78: pza | E78: =IF($M78="","",$M78*(1+$O$3)) | F78: =IF($E78="","",$E78*$O$4) | G78: =IF(OR($C78="",$E78=""),"",$C78*$E78) | K78: SE CONSIDERA ESA FRACCION POR REVISION DE BALANCE DE CARGAS | M78: 3465 | N78: M2 | O78: =A78&"|"&N78
A79: ELE12197 | B79: SUMINISTRO DE LUMINARIAS MODELO COLGANTE, TIRA LED, EMPTORABLE Y ARBOTANTE LINEA DOMESTICA ECONOMICA, INCLUYE LAMPARA CON FOCO, MANO DE OBRA Y EPP. | C79: 1 | D79: LOTE | E79: =IF($M79="","",$M79*(1+$O$3)) | F79: =IF($E79="","",$E79*$O$4) | G79: =IF(OR($C79="",$E79=""),"",$C79*$E79) | M79: =18*120 | N79: M2 | O79: =A79&"|"&N79
A80: INSTALACIONES HIDROSANITARIAS | G80: =SUM(G81:G99)
A81: HSI14101 | B81: SUMINISTRO Y TENDIDO DE TUBERÍA DE PPR DE 1" PARA LÍNEA DE ALIMENTACIÓN Y DISTRIBUCION HIDRÁULICA HASTA LLEGADA A DEPARTAMENTO. INCLUYE MATERIAL, HERRAMIENTA MENOR, MANO DE OBRA Y EQUIPO DE PROTECCIÓN PERSONAL. | C81: 19.85 | D81: ml | E81: =IF($M81="","",$M81*(1+$O$3)) | F81: =IF($E81="","",$E81*$O$4) | G81: =IF(OR($C81="",$E81=""),"",$C81*$E81) | I81: Precio HSI14059 · CASA 256. Falta cuantificar del plano hidráulico REV.03. | K81: SE AUMENTARAN 3 METROS DE ACUERDO AL INCREMENTO DE NIVEL NUEVO | M81: 153.95 | N81: M2 | O81: =A81&"|"&N81
A82: HSI14102 | B82: SUMINISTRO Y TENDIDO DE TUBERÍA DE PPR DE 3/4" DE LÍNEA DE DISTRIBUCIÓN DE AGUA FRÍA Y CALIENTE A MUEBLES. INCLUYE MATERIAL, HERRAMIENTA MENOR, MANO DE OBRA Y EQUIPO DE PROTECCIÓN PERSONAL. | C82: =22.86 | D82: ml | E82: =IF($M82="","",$M82*(1+$O$3)) | F82: =IF($E82="","",$E82*$O$4) | G82: =IF(OR($C82="",$E82=""),"",$C82*$E82) | I82: Precio HSI14065 · CASA 256. | M82: 109.3 | N82: M2 | O82: =A82&"|"&N82
A83: HSI14103 | B83: SUMINISTRO Y COLOCACIÓN DE CONEXIONES DE PPR (CODOS, TEES Y REDUCCIONES) PARA LA RED HIDRÁULICA. INCLUYE MATERIAL, HERRAMIENTA MENOR, MANO DE OBRA Y EQUIPO DE PROTECCIÓN PERSONAL. | C83: 29 | D83: pza | E83: =IF($M83="","",$M83*(1+$O$3)) | F83: =IF($E83="","",$E83*$O$4) | G83: =IF(OR($C83="",$E83=""),"",$C83*$E83) | I83: Precio promedio HSI14060/14063/14066 · CASA 256. | M83: 67.75 | N83: M2 | O83: =A83&"|"&N83
A84: HSI14104 | B84: SUMINISTRO Y COLOCACIÓN DE VÁLVULA DE PASO DE 1". INCLUYE MATERIAL, HERRAMIENTA MENOR, MANO DE OBRA Y EQUIPO DE PROTECCIÓN PERSONAL. | C84: 2 | D84: pza | E84: =IF($M84="","",$M84*(1+$O$3)) | F84: =IF($E84="","",$E84*$O$4) | G84: =IF(OR($C84="",$E84=""),"",$C84*$E84) | I84: Precio HSI14064 · CASA 256. | M84: 161.7 | N84: M2 | O84: =A84&"|"&N84
A85: HSI14105 | B85: DISPARO DE AGUA FRÍA Y CALIENTE DE LÍNEA DE DISTRIBUCIÓN A RAMAL DE MUEBLE. INCLUYE MATERIAL, HERRAMIENTA MENOR, MANO DE OBRA Y EQUIPO DE PROTECCIÓN PERSONAL. | C85: 12 | D85: sal | E85: =IF($M85="","",$M85*(1+$O$3)) | F85: =IF($E85="","",$E85*$O$4) | G85: =IF(OR($C85="",$E85=""),"",$C85*$E85) | I85: Precio HSI14068 · CASA 256. | M85: 577.5 | N85: M2 | O85: =A85&"|"&N85
A86: HSI14106 | B86: SUMINISTRO Y TENDIDO DE TUBERÍA SANITARIA DE PVC RD26 DE 2". INCLUYE MATERIAL, HERRAMIENTA MENOR, MANO DE OBRA Y EQUIPO DE PROTECCIÓN PERSONAL. | C86: =6.97+8.27 | D86: ml | E86: =IF($M86="","",$M86*(1+$O$3)) | F86: =IF($E86="","",$E86*$O$4) | G86: =IF(OR($C86="",$E86=""),"",$C86*$E86) | I86: EN VOL INCLUYE EL VENTEO | M86: 46.2 | N86: M2 | O86: =A86&"|"&N86
A87: HSI14107 | B87: SUMINISTRO Y TENDIDO DE TUBERÍA SANITARIA DE PVC RD26 DE 4". INCLUYE MATERIAL, HERRAMIENTA MENOR, MANO DE OBRA Y EQUIPO DE PROTECCIÓN PERSONAL. | C87: =12.4+1.94+1.03+4.41+6+3+3+3+3 | D87: ml | E87: =IF($M87="","",$M87*(1+$O$3)) | F87: =IF($E87="","",$E87*$O$4) | G87: =IF(OR($C87="",$E87=""),"",$C87*$E87) | I87: Precio HSI14082 · CASA 256. | M87: 86.63 | N87: M2 | O87: =A87&"|"&N87
A88: HSI14108 | B88: SUMINISTRO Y COLOCACIÓN DE CONEXIONES SANITARIAS DE PVC (CODOS, YEES Y TEES) DE 2" Y 4". INCLUYE MATERIAL, HERRAMIENTA MENOR, MANO DE OBRA Y EQUIPO DE PROTECCIÓN PERSONAL. | C88: 28 | D88: pza | E88: =IF($M88="","",$M88*(1+$O$3)) | F88: =IF($E88="","",$E88*$O$4) | G88: =IF(OR($C88="",$E88=""),"",$C88*$E88) | I88: Precio promedio HSI14079/14083/14084 · CASA 256. | M88: 69.3 | N88: M2 | O88: =A88&"|"&N88
A89: HSI14109 | B89: SUMINISTRO Y COLOCACIÓN DE SALIDA DE DRENAJE, INCLUYE CONEXIONES Y TRAMPAS DE OLOR. INCLUYE MATERIAL, HERRAMIENTA MENOR, MANO DE OBRA Y EQUIPO DE PROTECCIÓN PERSONAL. | C89: 9 | D89: sal | E89: =IF($M89="","",$M89*(1+$O$3)) | F89: =IF($E89="","",$E89*$O$4) | G89: =IF(OR($C89="",$E89=""),"",$C89*$E89) | I89: Precio HSI14085 · CASA 256. | M89: =M85 | N89: M2 | O89: =A89&"|"&N89
A90: HSI14110 | B90: SUMINISTRO Y COLOCACIÓN DE COLADERA. INCLUYE MATERIAL, HERRAMIENTA MENOR, MANO DE OBRA Y EQUIPO DE PROTECCIÓN PERSONAL. | C90: 4 | D90: pza | E90: =IF($M90="","",$M90*(1+$O$3)) | F90: =IF($E90="","",$E90*$O$4) | G90: =IF(OR($C90="",$E90=""),"",$C90*$E90) | I90: Precio HSI14086 · CASA 256. | M90: 404.25 | N90: M2 | O90: =A90&"|"&N90
A91: HSI14111 | B91: SUMINISTRO Y COLOCACIÓN DE BOMBA SUMERGIBLE DE 1 HP CON SU CIRCUITO ELÉCTRICO DEDICADO DESDE EL TABLERO DEL DEPARTAMENTO HASTA LA CISTERNA EXISTENTE, CON PROTECCIÓN TERMOMAGNÉTICA PROPIA. INCLUYE MATERIAL, HERRAMIENTA MENOR, MANO DE OBRA Y EQUIPO DE PROTECCIÓN PERSONAL. | C91: 1 | D91: lote | E91: =IF($M91="","",$M91*(1+$O$3)) | F91: =IF($E91="","",$E91*$O$4) | G91: =IF(OR($C91="",$E91=""),"",$C91*$E91) | I91: Precio HSI14070 · CASA 256. Una bomba por departamento: la cisterna existente se independiza. | M91: 4212 | N91: M2 | O91: =A91&"|"&N91
A92: HSI14112 | B92: SUMINISTRO Y COLOCACIÓN DE TINACO VERTICAL DE 1,200 LITROS CON ACCESORIOS. INCLUYE MATERIAL, HERRAMIENTA MENOR, MANO DE OBRA Y EQUIPO DE PROTECCIÓN PERSONAL. | C92: 1 | D92: pza | E92: =IF($M92="","",$M92*(1+$O$3)) | F92: =IF($E92="","",$E92*$O$4) | G92: =IF(OR($C92="",$E92=""),"",$C92*$E92) | I92: Precio HSI14072 · CASA 256. | M92: 4242.5 | N92: M2 | O92: =A92&"|"&N92
A93: HSI14113 | B93: SUMINISTRO Y COLOCACIÓN DE BOILER DE PASO DE 12 L CON SUS CONEXIONES Y SOPORTE. INCLUYE MATERIAL, HERRAMIENTA MENOR, MANO DE OBRA Y EQUIPO DE PROTECCIÓN PERSONAL. | C93: 1 | D93: pza | E93: =IF($M93="","",$M93*(1+$O$3)) | F93: =IF($E93="","",$E93*$O$4) | G93: =IF(OR($C93="",$E93=""),"",$C93*$E93) | I93: Precio HSI14071 · CASA 256. Alterno de la opción B, calentador solar. | K93: HAY QUE REVISAR PRECIO | M93: 5800.25 | N93: M2 | O93: =A93&"|"&N93
A94: HSI14115 | B94: SUMINISTRO Y COLOCACIÓN DE WC CON ASIENTO, TAPA, MANGUERA Y LLAVE ANGULAR LINEA ECONOMICA. INCLUYE MATERIAL, HERRAMIENTA MENOR, MANO DE OBRA Y EQUIPO DE PROTECCIÓN PERSONAL. | C94: 1 | D94: pza | E94: =IF($M94="","",$M94*(1+$O$3)) | F94: =IF($E94="","",$E94*$O$4) | G94: 3825.35 | I94: Precio HSI14076 · CASA 256. | M94: 4042.5 | N94: M2 | O94: =A94&"|"&N94
A95: HSI14116 | B95: SUMINISTRO Y COLOCACIÓN DE LAVABO CON MANGUERA COFLEX Y LLAVE ANGULAR LINEA ECONOMICA. INCLUYE MATERIAL, HERRAMIENTA MENOR, SOPORTE, MANO DE OBRA Y EQUIPO DE PROTECCIÓN PERSONAL. | C95: 1 | D95: pza | E95: =IF($M95="","",$M95*(1+$O$3)) | F95: =IF($E95="","",$E95*$O$4) | G95: =IF(OR($C95="",$E95=""),"",$C95*$E95) | I95: Precio HSI14077 · CASA 256. | M95: 2800 | N95: M2 | O95: =A95&"|"&N95
A96: HSI14117 | B96: SUMINISTRO Y COLOCACIÓN DE REGADERA Y MANERALES. INCLUYE MATERIAL, HERRAMIENTA MENOR, MANO DE OBRA Y EQUIPO DE PROTECCIÓN PERSONAL. | C96: 1 | D96: pza | E96: =IF($M96="","",$M96*(1+$O$3)) | F96: =IF($E96="","",$E96*$O$4) | G96: =IF(OR($C96="",$E96=""),"",$C96*$E96) | I96: Precio HSI14075 · CASA 256. | M96: 1039.5 | N96: M2 | O96: =A96&"|"&N96
A97: HSI14118 | B97: SUMINISTRO Y COLOCACIÓN DE LLAVE DE NARIZ. INCLUYE MATERIAL, HERRAMIENTA MENOR, MANO DE OBRA Y EQUIPO DE PROTECCIÓN PERSONAL. | C97: 2 | D97: pza | E97: =IF($M97="","",$M97*(1+$O$3)) | F97: =IF($E97="","",$E97*$O$4) | G97: =IF(OR($C97="",$E97=""),"",$C97*$E97) | I97: Precio HSI14073 · CASA 256. | M97: 231 | N97: M2 | O97: =A97&"|"&N97
A98: HSI14268 | B98: SUMINISTRO Y COLOCACION DE TARJA SENCILLA DE ACERO INOXIDABLE CON ESCURRIDERO,MONOMANDO CON CUELLO GIRATORIO, LOTE DE EMPAQUES Y ACCESORIOS DE TARJA: CÉSPOL, CONTRACANASTA, MANGUERAS DE ABASTO, LLAVES ANGULARES, REJILLA Y SELLADORCALIBRE Y MEDIDAS DE PROYECTO. INCLUYE MATERIAL, HERRAMIENTA MENOR, MANO DE OBRA Y EQUIPO DE PROTECCIÓN PERSONAL. | C98: 1 | D98: pza | E98: =IF($M98="","",$M98*(1+$O$3)) | F98: =IF($E98="","",$E98*$O$4) | G98: =IF(OR($C98="",$E98=""),"",$C98*$E98) | M98: =700+2570 | N98: M2 | O98: =A98&"|"&N98
A99: HSI14255 | B99: SUMINISTRO Y COLOCACION DE FREGADERO DE CEMENTO : MONTAJE SOBRE MUEBLE, SELLADO PERIMETRAL, CONEXIÓN A LÍNEAS DE AGUA FRÍA Y CALIENTE, CONEXIÓN AL DRENAJE Y PRUEBA DE HERMETICIDAD. INCLUYE MATERIAL, HERRAMIENTA MENOR, MANO DE OBRA Y EQUIPO DE PROTECCIÓN PERSONAL. | C99: 1 | D99: pza | E99: =IF($M99="","",$M99*(1+$O$3)) | F99: =IF($E99="","",$E99*$O$4) | G99: =IF(OR($C99="",$E99=""),"",$C99*$E99) | M99: 1400 | N99: M2 | O99: =A99&"|"&N99
A100: INSTALACION DE GAS | G100: =SUM(G101:G101)
A101: GAS09167 | B101: SUMINISTRO E INSTALACION DE LINEA DE GAS: COLOCACION DE TUBERIA DE COBRE DE 3/4" PARED GRUESA PARA GAS EN RED DE DISTRIBUCION DE CILINDRO DE GAS DE 20 O 30 K HACIA BOILER Y ESTUFA. INCLUYE TUBERIA, CONEXIONES, REGULADOR, VALVULAS DE SEGURIDAD, MANGERAS DE BAJA PRESION, MANO DE OBRA, HERRAMIENTA MENOR. | C101: 1 | D101: LOTE | E101: =IF($M101="","",$M101*(1+$O$3)) | F101: =IF($E101="","",$E101*$O$4) | G101: =IF(OR($C101="",$E101=""),"",$C101*$E101) | M101: =22*320 | N101: M2 | O101: =A101&"|"&N101
A102: ACABADOS | G102: =SUM(G103:G113)
A103: ACA09101 | B103: APLANADO FINO EN MUROS INTERIORES Y EXTERIORES HASTA 3.00 M DE ALTURA CON MORTERO CEMENTO-ARENA, A PLOMO Y REGLA. INCLUYE ANDAMIOS. INCLUYE MATERIAL, HERRAMIENTA MENOR, MANO DE OBRA Y EQUIPO DE PROTECCIÓN PERSONAL. | C103: 197.607 | D103: m² | E103: =IF($M103="","",$M103*(1+$O$3)) | F103: =IF($E103="","",$E103*$O$4) | G103: =IF(OR($C103="",$E103=""),"",$C103*$E103) | M103: 220 | N103: M2 | O103: =A103&"|"&N103
...

Sheet CRONOGRAMA
A1: Cronograma
A2: FECHA | B2: =TODAY()
A3: =CARATULA!$C$10
A4: UBICACIÓN | B4: =CARATULA!$C$14
A5: CLIENTE | B5: =CARATULA!$C$12
J7: MES | K7: =CHOOSE(MONTH(K10),"ENERO","FEBRERO","MARZO","ABRIL","MAYO","JUNIO","JULIO","AGOSTO","SEPTIEMBRE","OCTUBRE","NOVIEMBRE","DICIEMBRE")&" "&YEAR(K10) | AG7: =IF(MONTH(AG10)<>MONTH(AF10),CHOOSE(MONTH(AG10),"ENERO","FEBRERO","MARZO","ABRIL","MAYO","JUNIO","JULIO","AGOSTO","SEPTIEMBRE","OCTUBRE","NOVIEMBRE","DICIEMBRE")&" "&YEAR(AG10),"") | BK7: =IF(MONTH(BK10)<>MONTH(BJ10),CHOOSE(MONTH(BK10),"ENERO","FEBRERO","MARZO","ABRIL","MAYO","JUNIO","JULIO","AGOSTO","SEPTIEMBRE","OCTUBRE","NOVIEMBRE","DICIEMBRE")&" "&YEAR(BK10),"") | CP7: =IF(MONTH(CP10)<>MONTH(CO10),CHOOSE(MONTH(CP10),"ENERO","FEBRERO","MARZO","ABRIL","MAYO","JUNIO","JULIO","AGOSTO","SEPTIEMBRE","OCTUBRE","NOVIEMBRE","DICIEMBRE")&" "&YEAR(CP10),"") | DT7: =IF(MONTH(DT10)<>MONTH(DS10),CHOOSE(MONTH(DT10),"ENERO","FEBRERO","MARZO","ABRIL","MAYO","JUNIO","JULIO","AGOSTO","SEPTIEMBRE","OCTUBRE","NOVIEMBRE","DICIEMBRE")&" "&YEAR(DT10),"") | EY7: =IF(MONTH(EY10)<>MONTH(EX10),CHOOSE(MONTH(EY10),"ENERO","FEBRERO","MARZO","ABRIL","MAYO","JUNIO","JULIO","AGOSTO","SEPTIEMBRE","OCTUBRE","NOVIEMBRE","DICIEMBRE")&" "&YEAR(EY10),"") | GD7: =IF(MONTH(GD10)<>MONTH(GC10),CHOOSE(MONTH(GD10),"ENERO","FEBRERO","MARZO","ABRIL","MAYO","JUNIO","JULIO","AGOSTO","SEPTIEMBRE","OCTUBRE","NOVIEMBRE","DICIEMBRE")&" "&YEAR(GD10),"")
J8: SEMANA | K8: ="SEM "&1 | R8: ="SEM "&2 | Y8: ="SEM "&3 | AF8: ="SEM "&4 | AM8: ="SEM "&5 | AT8: ="SEM "&6 | BA8: ="SEM "&7 | BH8: ="SEM "&8 | BO8: ="SEM "&9 | BV8: ="SEM "&10 | CC8: ="SEM "&11 | CJ8: ="SEM "&12 | CQ8: ="SEM "&13 | CX8: ="SEM "&14 | DE8: ="SEM "&15 | DL8: ="SEM "&16 | DS8: ="SEM "&17 | DZ8: ="SEM "&18 | EG8: ="SEM "&19 | EN8: ="SEM "&20 | EU8: ="SEM "&21 | FB8: ="SEM "&22 | FI8: ="SEM "&23 | FP8: ="SEM "&24 | FW8: ="SEM "&25 | GD8: ="SEM "&26 | GK8: ="SEM "&27
J9: DÍA | K9: =CHOOSE(WEEKDAY(K10,2),"L","M","MI","J","V","S","D") | L9: =CHOOSE(WEEKDAY(L10,2),"L","M","MI","J","V","S","D") | M9: =CHOOSE(WEEKDAY(M10,2),"L","M","MI","J","V","S","D") | N9: =CHOOSE(WEEKDAY(N10,2),"L","M","MI","J","V","S","D") | O9: =CHOOSE(WEEKDAY(O10,2),"L","M","MI","J","V","S","D") | P9: =CHOOSE(WEEKDAY(P10,2),"L","M","MI","J","V","S","D") | Q9: =CHOOSE(WEEKDAY(Q10,2),"L","M","MI","J","V","S","D") | R9: =CHOOSE(WEEKDAY(R10,2),"L","M","MI","J","V","S","D") | ... GQ9: =CHOOSE(WEEKDAY(GQ10,2),"L","M","MI","J","V","S","D")
J10: FECHA | K10: =CARATULA!$C$27 | L10: =K10+1 | M10: =L10+1 | N10: =M10+1 | O10: =N10+1 | P10: =O10+1 | Q10: =P10+1 | R10: =Q10+1 | S10: =R10+1 | ... GQ10: =GP10+1
A11: CLAVE | B11: PARTIDA | D11: DESCRIPCIÓN DEL CONCEPTO | E11: IMPORTE | F11: INICIO | G11: FIN | H11: DÍAS | I11: AVANCE % | J11: ESTADO
A12: =IF(PRESUPUESTO!A12="","",PRESUPUESTO!A12) | B12: =PRESUPUESTO!A10 | C12: =PRESUPUESTO!A11 | D12: =IF(PRESUPUESTO!B12="","",PRESUPUESTO!B12) | E12: =IF(PRESUPUESTO!G12="",0,PRESUPUESTO!G12) | F12: 46251 | G12: 46265 | H12: =IF(OR(F12="",G12=""),"",G12-F12+1) | I12: 0 | J12: Planeado
A13: =IF(PRESUPUESTO!A13="","",PRESUPUESTO!A13) | B13: =PRESUPUESTO!A10 | C13: =PRESUPUESTO!A11 | D13: =IF(PRESUPUESTO!B13="","",PRESUPUESTO!B13) | E13: =IF(PRESUPUESTO!G13="",0,PRESUPUESTO!G13) | F13: 46254 | G13: 46270 | H13: =IF(OR(F13="",G13=""),"",G13-F13+1) | I13: 0 | J13: Planeado
A14: =IF(PRESUPUESTO!A14="","",PRESUPUESTO!A14) | B14: =PRESUPUESTO!A10 | C14: =PRESUPUESTO!A11 | D14: =IF(PRESUPUESTO!B14="","",PRESUPUESTO!B14) | E14: =IF(PRESUPUESTO!G14="",0,PRESUPUESTO!G14) | F14: 46257 | G14: 46275 | H14: =IF(OR(F14="",G14=""),"",G14-F14+1) | I14: 0 | J14: Planeado
A15: =IF(PRESUPUESTO!A15="","",PRESUPUESTO!A15) | B15: =PRESUPUESTO!A10 | C15: =PRESUPUESTO!A11 | D15: =IF(PRESUPUESTO!B15="","",PRESUPUESTO!B15) | E15: =IF(PRESUPUESTO!G15="",0,PRESUPUESTO!G15) | F15: 46260 | G15: 46280 | H15: =IF(OR(F15="",G15=""),"",G15-F15+1) | I15: 0 | J15: Planeado
A16: =IF(PRESUPUESTO!A16="","",PRESUPUESTO!A16) | B16: =PRESUPUESTO!A10 | C16: =PRESUPUESTO!A11 | D16: =IF(PRESUPUESTO!B16="","",PRESUPUESTO!B16) | E16: =IF(PRESUPUESTO!G16="",0,PRESUPUESTO!G16) | F16: 46263 | G16: 46285 | H16: =IF(OR(F16="",G16=""),"",G16-F16+1) | I16: 0 | J16: Planeado
A17: =IF(PRESUPUESTO!A17="","",PRESUPUESTO!A17) | B17: =PRESUPUESTO!A10 | C17: =PRESUPUESTO!A11 | D17: =IF(PRESUPUESTO!B17="","",PRESUPUESTO!B17) | E17: =IF(PRESUPUESTO!G17="",0,PRESUPUESTO!G17) | F17: 46266 | G17: 46290 | H17: =IF(OR(F17="",G17=""),"",G17-F17+1) | I17: 0 | J17: Planeado
A18: =IF(PRESUPUESTO!A18="","",PRESUPUESTO!A18) | B18: =PRESUPUESTO!A10 | C18: =PRESUPUESTO!A11 | D18: =IF(PRESUPUESTO!B18="","",PRESUPUESTO!B18) | E18: =IF(PRESUPUESTO!G18="",0,PRESUPUESTO!G18) | F18: 46269 | G18: 46295 | H18: =IF(OR(F18="",G18=""),"",G18-F18+1) | I18: 0 | J18: Planeado
A19: =IF(PRESUPUESTO!A19="","",PRESUPUESTO!A19) | B19: =PRESUPUESTO!A10 | C19: =PRESUPUESTO!A11 | D19: =IF(PRESUPUESTO!B19="","",PRESUPUESTO!B19) | E19: =IF(PRESUPUESTO!G19="",0,PRESUPUESTO!G19) | F19: 46272 | G19: 46300 | H19: =IF(OR(F19="",G19=""),"",G19-F19+1) | I19: 0 | J19: Planeado
A20: =IF(PRESUPUESTO!A21="","",PRESUPUESTO!A21) | B20: =PRESUPUESTO!A10 | C20: =PRESUPUESTO!A20 | D20: =IF(PRESUPUESTO!B21="","",PRESUPUESTO!B21) | E20: =IF(PRESUPUESTO!G21="",0,PRESUPUESTO!G21) | F20: 46275 | G20: 46305 | H20: =IF(OR(F20="",G20=""),"",G20-F20+1) | I20: 0 | J20: Planeado
A21: =IF(PRESUPUESTO!A22="","",PRESUPUESTO!A22) | B21: =PRESUPUESTO!A10 | C21: =PRESUPUESTO!A20 | D21: =IF(PRESUPUESTO!B22="","",PRESUPUESTO!B22) | E21: =IF(PRESUPUESTO!G22="",0,PRESUPUESTO!G22) | F21: 46278 | G21: 46310 | H21: =IF(OR(F21="",G21=""),"",G21-F21+1) | I21: 0 | J21: Planeado
A22: =IF(PRESUPUESTO!A24="","",PRESUPUESTO!A24) | B22: =PRESUPUESTO!A10 | C22: =PRESUPUESTO!A23 | D22: =IF(PRESUPUESTO!B24="","",PRESUPUESTO!B24) | E22: =IF(PRESUPUESTO!G24="",0,PRESUPUESTO!G24) | F22: 46281 | G22: 46315 | H22: =IF(OR(F22="",G22=""),"",G22-F22+1) | I22: 0 | J22: Planeado
A23: =IF(PRESUPUESTO!A25="","",PRESUPUESTO!A25) | B23: =PRESUPUESTO!A10 | C23: =PRESUPUESTO!A23 | D23: =IF(PRESUPUESTO!B25="","",PRESUPUESTO!B25) | E23: =IF(PRESUPUESTO!G25="",0,PRESUPUESTO!G25) | F23: 46284 | G23: 46320 | H23: =IF(OR(F23="",G23=""),"",G23-F23+1) | I23: 0 | J23: Planeado
A24: =IF(PRESUPUESTO!A27="","",PRESUPUESTO!A27) | B24: =PRESUPUESTO!A10 | C24: =PRESUPUESTO!A26 | D24: =IF(PRESUPUESTO!B27="","",PRESUPUESTO!B27) | E24: =IF(PRESUPUESTO!G27="",0,PRESUPUESTO!G27) | F24: 46287 | G24: 46325 | H24: =IF(OR(F24="",G24=""),"",G24-F24+1) | I24: 0 | J24: Planeado
A25: =IF(PRESUPUESTO!A28="","",PRESUPUESTO!A28) | B25: =PRESUPUESTO!A10 | C25: =PRESUPUESTO!A26 | D25: =IF(PRESUPUESTO!B28="","",PRESUPUESTO!B28) | E25: =IF(PRESUPUESTO!G28="",0,PRESUPUESTO!G28) | F25: 46290 | G25: 46330 | H25: =IF(OR(F25="",G25=""),"",G25-F25+1) | I25: 0 | J25: Planeado
A26: =IF(PRESUPUESTO!A29="","",PRESUPUESTO!A29) | B26: =PRESUPUESTO!A10 | C26: =PRESUPUESTO!A26 | D26: =IF(PRESUPUESTO!B29="","",PRESUPUESTO!B29) | E26: =IF(PRESUPUESTO!G29="",0,PRESUPUESTO!G29) | F26: 46293 | G26: 46335 | H26: =IF(OR(F26="",G26=""),"",G26-F26+1) | I26: 0 | J26: Planeado
A27: =IF(PRESUPUESTO!A31="","",PRESUPUESTO!A31) | B27: =PRESUPUESTO!A10 | C27: =PRESUPUESTO!A30 | D27: =IF(PRESUPUESTO!B31="","",PRESUPUESTO!B31) | E27: =IF(PRESUPUESTO!G31="",0,PRESUPUESTO!G31) | F27: 46296 | G27: 46340 | H27: =IF(OR(F27="",G27=""),"",G27-F27+1) | I27: 0 | J27: Planeado
A28: =IF(PRESUPUESTO!A32="","",PRESUPUESTO!A32) | B28: =PRESUPUESTO!A10 | C28: =PRESUPUESTO!A30 | D28: =IF(PRESUPUESTO!B32="","",PRESUPUESTO!B32) | E28: =IF(PRESUPUESTO!G32="",0,PRESUPUESTO!G32) | F28: 46299 | G28: 46345 | H28: =IF(OR(F28="",G28=""),"",G28-F28+1) | I28: 0 | J28: Planeado
A29: =IF(PRESUPUESTO!A33="","",PRESUPUESTO!A33) | B29: =PRESUPUESTO!A10 | C29: =PRESUPUESTO!A30 | D29: =IF(PRESUPUESTO!B33="","",PRESUPUESTO!B33) | E29: =IF(PRESUPUESTO!G33="",0,PRESUPUESTO!G33) | F29: 46302 | G29: 46350 | H29: =IF(OR(F29="",G29=""),"",G29-F29+1) | I29: 0 | J29: Planeado
A30: =IF(PRESUPUESTO!A34="","",PRESUPUESTO!A34) | B30: =PRESUPUESTO!A10 | C30: =PRESUPUESTO!A30 | D30: =IF(PRESUPUESTO!B34="","",PRESUPUESTO!B34) | E30: =IF(PRESUPUESTO!G34="",0,PRESUPUESTO!G34) | F30: 46305 | G30: 46355 | H30: =IF(OR(F30="",G30=""),"",G30-F30+1) | I30: 0 | J30: Planeado
A31: =IF(PRESUPUESTO!A35="","",PRESUPUESTO!A35) | B31: =PRESUPUESTO!A10 | C31: =PRESUPUESTO!A30 | D31: =IF(PRESUPUESTO!B35="","",PRESUPUESTO!B35) | E31: =IF(PRESUPUESTO!G35="",0,PRESUPUESTO!G35) | F31: 46308 | G31: 46360 | H31: =IF(OR(F31="",G31=""),"",G31-F31+1) | I31: 0 | J31: Planeado
A32: =IF(PRESUPUESTO!A36="","",PRESUPUESTO!A36) | B32: =PRESUPUESTO!A10 | C32: =PRESUPUESTO!A30 | D32: =IF(PRESUPUESTO!B36="","",PRESUPUESTO!B36) | E32: =IF(PRESUPUESTO!G36="",0,PRESUPUESTO!G36) | F32: 46311 | G32: 46365 | H32: =IF(OR(F32="",G32=""),"",G32-F32+1) | I32: 0 | J32: Planeado
A33: =IF(PRESUPUESTO!A37="","",PRESUPUESTO!A37) | B33: =PRESUPUESTO!A10 | C33: =PRESUPUESTO!A30 | D33: =IF(PRESUPUESTO!B37="","",PRESUPUESTO!B37) | E33: =IF(PRESUPUESTO!G37="",0,PRESUPUESTO!G37) | F33: 46314 | G33: 46370 | H33: =IF(OR(F33="",G33=""),"",G33-F33+1) | I33: 0 | J33: Planeado
A34: =IF(PRESUPUESTO!A38="","",PRESUPUESTO!A38) | B34: =PRESUPUESTO!A10 | C34: =PRESUPUESTO!A30 | D34: =IF(PRESUPUESTO!B38="","",PRESUPUESTO!B38) | E34: =IF(PRESUPUESTO!G38="",0,PRESUPUESTO!G38) | F34: 46317 | G34: 46375 | H34: =IF(OR(F34="",G34=""),"",G34-F34+1) | I34: 0 | J34: Planeado
A35: =IF(PRESUPUESTO!A40="","",PRESUPUESTO!A40) | B35: =PRESUPUESTO!A10 | C35: =PRESUPUESTO!A39 | D35: =IF(PRESUPUESTO!B40="","",PRESUPUESTO!B40) | E35: =IF(PRESUPUESTO!G40="",0,PRESUPUESTO!G40) | F35: 46320 | G35: 46380 | H35: =IF(OR(F35="",G35=""),"",G35-F35+1) | I35: 0 | J35: Planeado
A36: =IF(PRESUPUESTO!A41="","",PRESUPUESTO!A41) | B36: =PRESUPUESTO!A10 | C36: =PRESUPUESTO!A39 | D36: =IF(PRESUPUESTO!B41="","",PRESUPUESTO!B41) | E36: =IF(PRESUPUESTO!G41="",0,PRESUPUESTO!G41) | F36: 46323 | G36: 46385 | H36: =IF(OR(F36="",G36=""),"",G36-F36+1) | I36: 0 | J36: Planeado
A37: =IF(PRESUPUESTO!A43="","",PRESUPUESTO!A43) | B37: =PRESUPUESTO!A10 | C37: =PRESUPUESTO!A42 | D37: =IF(PRESUPUESTO!B43="","",PRESUPUESTO!B43) | E37: =IF(PRESUPUESTO!G43="",0,PRESUPUESTO!G43) | F37: 46326 | G37: 46390 | H37: =IF(OR(F37="",G37=""),"",G37-F37+1) | I37: 0 | J37: Planeado
A38: =IF(PRESUPUESTO!A44="","",PRESUPUESTO!A44) | B38: =PRESUPUESTO!A10 | C38: =PRESUPUESTO!A42 | D38: =IF(PRESUPUESTO!B44="","",PRESUPUESTO!B44) | E38: =IF(PRESUPUESTO!G44="",0,PRESUPUESTO!G44) | F38: 46329 | G38: 46395 | H38: =IF(OR(F38="",G38=""),"",G38-F38+1) | I38: 0 | J38: Planeado
A39: =IF(PRESUPUESTO!A46="","",PRESUPUESTO!A46) | B39: =PRESUPUESTO!A10 | C39: =PRESUPUESTO!A45 | D39: =IF(PRESUPUESTO!B46="","",PRESUPUESTO!B46) | E39: =IF(PRESUPUESTO!G46="",0,PRESUPUESTO!G46) | F39: 46332 | G39: 46400 | H39: =IF(OR(F39="",G39=""),"",G39-F39+1) | I39: 0 | J39: Planeado
A40: =IF(PRESUPUESTO!A47="","",PRESUPUESTO!A47) | B40: =PRESUPUESTO!A10 | C40: =PRESUPUESTO!A45 | D40: =IF(PRESUPUESTO!B47="","",PRESUPUESTO!B47) | E40: =IF(PRESUPUESTO!G47="",0,PRESUPUESTO!G47) | F40: 46335 | G40: 46405 | H40: =IF(OR(F40="",G40=""),"",G40-F40+1) | I40: 0 | J40: Planeado
A41: =IF(PRESUPUESTO!A50="","",PRESUPUESTO!A50) | B41: =PRESUPUESTO!A48 | C41: =PRESUPUESTO!A49 | D41: =IF(PRESUPUESTO!B50="","",PRESUPUESTO!B50) | E41: =IF(PRESUPUESTO!G50="",0,PRESUPUESTO!G50) | F41: 46338 | G41: 46410 | H41: =IF(OR(F41="",G41=""),"",G41-F41+1) | I41: 0 | J41: Planeado
A42: =IF(PRESUPUESTO!A52="","",PRESUPUESTO!A52) | B42: =PRESUPUESTO!A48 | C42: =PRESUPUESTO!A51 | D42: =IF(PRESUPUESTO!B52="","",PRESUPUESTO!B52) | E42: =IF(PRESUPUESTO!G52="",0,PRESUPUESTO!G52) | F42: 46341 | G42: 46415 | H42: =IF(OR(F42="",G42=""),"",G42-F42+1) | I42: 0 | J42: Planeado
A43: =IF(PRESUPUESTO!A53="","",PRESUPUESTO!A53) | B43: =PRESUPUESTO!A48 | C43: =PRESUPUESTO!A51 | D43: =IF(PRESUPUESTO!B53="","",PRESUPUESTO!B53) | E43: =IF(PRESUPUESTO!G53="",0,PRESUPUESTO!G53) | F43: 46344 | G43: 46420 | H43: =IF(OR(F43="",G43=""),"",G43-F43+1) | I43: 0 | J43: Planeado
A44: =IF(PRESUPUESTO!A55="","",PRESUPUESTO!A55) | B44: =PRESUPUESTO!A48 | C44: =PRESUPUESTO!A54 | D44: =IF(PRESUPUESTO!B55="","",PRESUPUESTO!B55) | E44: =IF(PRESUPUESTO!G55="",0,PRESUPUESTO!G55) | F44: 46347 | G44: 46425 | H44: =IF(OR(F44="",G44=""),"",G44-F44+1) | I44: 0 | J44: Planeado
A45: =IF(PRESUPUESTO!A57="","",PRESUPUESTO!A57) | B45: =PRESUPUESTO!A48 | C45: =PRESUPUESTO!A56 | D45: =IF(PRESUPUESTO!B57="","",PRESUPUESTO!B57) | E45: =IF(PRESUPUESTO!G57="",0,PRESUPUESTO!G57) | F45: 46350 | G45: 46430 | H45: =IF(OR(F45="",G45=""),"",G45-F45+1) | I45: 0 | J45: Planeado
A46: =IF(PRESUPUESTO!A58="","",PRESUPUESTO!A58) | B46: =PRESUPUESTO!A48 | C46: =PRESUPUESTO!A56 | D46: =IF(PRESUPUESTO!B58="","",PRESUPUESTO!B58) | E46: =IF(PRESUPUESTO!G58="",0,PRESUPUESTO!G58) | F46: 46353 | G46: 46435 | H46: =IF(OR(F46="",G46=""),"",G46-F46+1) | I46: 0 | J46: Planeado
A47: =IF(PRESUPUESTO!A59="","",PRESUPUESTO!A59) | B47: =PRESUPUESTO!A48 | C47: =PRESUPUESTO!A56 | D47: =IF(PRESUPUESTO!B59="","",PRESUPUESTO!B59) | E47: =IF(PRESUPUESTO!G59="",0,PRESUPUESTO!G59) | F47: 46356 | G47: 46440 | H47: =IF(OR(F47="",G47=""),"",G47-F47+1) | I47: 0 | J47: Planeado
A48: =IF(PRESUPUESTO!A60="","",PRESUPUESTO!A60) | B48: =PRESUPUESTO!A48 | C48: =PRESUPUESTO!A56 | D48: =IF(PRESUPUESTO!B60="","",PRESUPUESTO!B60) | E48: =IF(PRESUPUESTO!G60="",0,PRESUPUESTO!G60) | F48: 46359 | G48: 46445 | H48: =IF(OR(F48="",G48=""),"",G48-F48+1) | I48: 0 | J48: Planeado
A49: =IF(PRESUPUESTO!A61="","",PRESUPUESTO!A61) | B49: =PRESUPUESTO!A48 | C49: =PRESUPUESTO!A56 | D49: =IF(PRESUPUESTO!B61="","",PRESUPUESTO!B61) | E49: =IF(PRESUPUESTO!G61="",0,PRESUPUESTO!G61) | F49: 46362 | G49: 46450 | H49: =IF(OR(F49="",G49=""),"",G49-F49+1) | I49: 0 | J49: Planeado
A50: =IF(PRESUPUESTO!A62="","",PRESUPUESTO!A62) | B50: =PRESUPUESTO!A48 | C50: =PRESUPUESTO!A56 | D50: =IF(PRESUPUESTO!B62="","",PRESUPUESTO!B62) | E50: =IF(PRESUPUESTO!G62="",0,PRESUPUESTO!G62) | F50: 46365 | G50: 46455 | H50: =IF(OR(F50="",G50=""),"",G50-F50+1) | I50: 0 | J50: Planeado
A51: =IF(PRESUPUESTO!A63="","",PRESUPUESTO!A63) | B51: =PRESUPUESTO!A48 | C51: =PRESUPUESTO!A56 | D51: =IF(PRESUPUESTO!B63="","",PRESUPUESTO!B63) | E51: =IF(PRESUPUESTO!G63="",0,PRESUPUESTO!G63) | F51: 46368 | G51: 46460 | H51: =IF(OR(F51="",G51=""),"",G51-F51+1) | I51: 0 | J51: Planeado
A52: =IF(PRESUPUESTO!A64="","",PRESUPUESTO!A64) | B52: =PRESUPUESTO!A48 | C52: =PRESUPUESTO!A56 | D52: =IF(PRESUPUESTO!B64="","",PRESUPUESTO!B64) | E52: =IF(PRESUPUESTO!G64="",0,PRESUPUESTO!G64) | F52: 46371 | G52: 46465 | H52: =IF(OR(F52="",G52=""),"",G52-F52+1) | I52: 0 | J52: Planeado
A53: =IF(PRESUPUESTO!A65="","",PRESUPUESTO!A65) | B53: =PRESUPUESTO!A48 | C53: =PRESUPUESTO!A56 | D53: =IF(PRESUPUESTO!B65="","",PRESUPUESTO!B65) | E53: =IF(PRESUPUESTO!G65="",0,PRESUPUESTO!G65) | F53: 46374 | G53: 46470 | H53: =IF(OR(F53="",G53=""),"",G53-F53+1) | I53: 0 | J53: Planeado
A54: =IF(PRESUPUESTO!A66="","",PRESUPUESTO!A66) | B54: =PRESUPUESTO!A48 | C54: =PRESUPUESTO!A56 | D54: =IF(PRESUPUESTO!B66="","",PRESUPUESTO!B66) | E54: =IF(PRESUPUESTO!G66="",0,PRESUPUESTO!G66) | F54: 46377 | G54: 46475 | H54: =IF(OR(F54="",G54=""),"",G54-F54+1) | I54: 0 | J54: Planeado
A55: =IF(PRESUPUESTO!A68="","",PRESUPUESTO!A68) | B55: =PRESUPUESTO!A48 | C55: =PRESUPUESTO!A67 | D55: =IF(PRESUPUESTO!B68="","",PRESUPUESTO!B68) | E55: =IF(PRESUPUESTO!G68="",0,PRESUPUESTO!G68) | F55: 46380 | G55: 46480 | H55: =IF(OR(F55="",G55=""),"",G55-F55+1) | I55: 0 | J55: Planeado
A56: =IF(PRESUPUESTO!A69="","",PRESUPUESTO!A69) | B56: =PRESUPUESTO!A48 | C56: =PRESUPUESTO!A67 | D56: =IF(PRESUPUESTO!B69="","",PRESUPUESTO!B69) | E56: =IF(PRESUPUESTO!G69="",0,PRESUPUESTO!G69) | F56: 46383 | G56: 46485 | H56: =IF(OR(F56="",G56=""),"",G56-F56+1) | I56: 0 | J56: Planeado
A57: =IF(PRESUPUESTO!A70="","",PRESUPUESTO!A70) | B57: =PRESUPUESTO!A48 | C57: =PRESUPUESTO!A67 | D57: =IF(PRESUPUESTO!B70="","",PRESUPUESTO!B70) | E57: =IF(PRESUPUESTO!G70="",0,PRESUPUESTO!G70) | F57: 46386 | G57: 46490 | H57: =IF(OR(F57="",G57=""),"",G57-F57+1) | I57: 0 | J57: Planeado
A58: =IF(PRESUPUESTO!A71="","",PRESUPUESTO!A71) | B58: =PRESUPUESTO!A48 | C58: =PRESUPUESTO!A67 | D58: =IF(PRESUPUESTO!B71="","",PRESUPUESTO!B71) | E58: =IF(PRESUPUESTO!G71="",0,PRESUPUESTO!G71) | F58: 46389 | G58: 46495 | H58: =IF(OR(F58="",G58=""),"",G58-F58+1) | I58: 0 | J58: Planeado
A59: =IF(PRESUPUESTO!A72="","",PRESUPUESTO!A72) | B59: =PRESUPUESTO!A48 | C59: =PRESUPUESTO!A67 | D59: =IF(PRESUPUESTO!B72="","",PRESUPUESTO!B72) | E59: =IF(PRESUPUESTO!G72="",0,PRESUPUESTO!G72) | F59: 46392 | G59: 46500 | H59: =IF(OR(F59="",G59=""),"",G59-F59+1) | I59: 0 | J59: Planeado
A60: =IF(PRESUPUESTO!A73="","",PRESUPUESTO!A73) | B60: =PRESUPUESTO!A48 | C60: =PRESUPUESTO!A67 | D60: =IF(PRESUPUESTO!B73="","",PRESUPUESTO!B73) | E60: =IF(PRESUPUESTO!G73="",0,PRESUPUESTO!G73) | F60: 46395 | G60: 46505 | H60: =IF(OR(F60="",G60=""),"",G60-F60+1) | I60: 0 | J60: Planeado
A61: =IF(PRESUPUESTO!A74="","",PRESUPUESTO!A74) | B61: =PRESUPUESTO!A48 | C61: =PRESUPUESTO!A67 | D61: =IF(PRESUPUESTO!B74="","",PRESUPUESTO!B74) | E61: =IF(PRESUPUESTO!G74="",0,PRESUPUESTO!G74) | F61: 46398 | G61: 46510 | H61: =IF(OR(F61="",G61=""),"",G61-F61+1) | I61: 0 | J61: Planeado
A62: =IF(PRESUPUESTO!A75="","",PRESUPUESTO!A75) | B62: =PRESUPUESTO!A48 | C62: =PRESUPUESTO!A67 | D62: =IF(PRESUPUESTO!B75="","",PRESUPUESTO!B75) | E62: =IF(PRESUPUESTO!G75="",0,PRESUPUESTO!G75) | F62: 46401 | G62: 46515 | H62: =IF(OR(F62="",G62=""),"",G62-F62+1) | I62: 0 | J62: Planeado
A63: =IF(PRESUPUESTO!A76="","",PRESUPUESTO!A76) | B63: =PRESUPUESTO!A48 | C63: =PRESUPUESTO!A67 | D63: =IF(PRESUPUESTO!B76="","",PRESUPUESTO!B76) | E63: =IF(PRESUPUESTO!G76="",0,PRESUPUESTO!G76) | F63: 46404 | G63: 46520 | H63: =IF(OR(F63="",G63=""),"",G63-F63+1) | I63: 0 | J63: Planeado
A64: =IF(PRESUPUESTO!A77="","",PRESUPUESTO!A77) | B64: =PRESUPUESTO!A48 | C64: =PRESUPUESTO!A67 | D64: =IF(PRESUPUESTO!B77="","",PRESUPUESTO!B77) | E64: =IF(PRESUPUESTO!G77="",0,PRESUPUESTO!G77) | F64: 46407 | G64: 46525 | H64: =IF(OR(F64="",G64=""),"",G64-F64+1) | I64: 0 | J64: Planeado
A65: =IF(PRESUPUESTO!A78="","",PRESUPUESTO!A78) | B65: =PRESUPUESTO!A48 | C65: =PRESUPUESTO!A67 | D65: =IF(PRESUPUESTO!B78="","",PRESUPUESTO!B78) | E65: =IF(PRESUPUESTO!G78="",0,PRESUPUESTO!G78) | F65: 46410 | G65: 46530 | H65: =IF(OR(F65="",G65=""),"",G65-F65+1) | I65: 0 | J65: Planeado
A66: =IF(PRESUPUESTO!A79="","",PRESUPUESTO!A79) | B66: =PRESUPUESTO!A48 | C66: =PRESUPUESTO!A67 | D66: =IF(PRESUPUESTO!B79="","",PRESUPUESTO!B79) | E66: =IF(PRESUPUESTO!G79="",0,PRESUPUESTO!G79) | F66: 46413 | G66: 46535 | H66: =IF(OR(F66="",G66=""),"",G66-F66+1) | I66: 0 | J66: Planeado
A67: =IF(PRESUPUESTO!A81="","",PRESUPUESTO!A81) | B67: =PRESUPUESTO!A48 | C67: =PRESUPUESTO!A80 | D67: =IF(PRESUPUESTO!B81="","",PRESUPUESTO!B81) | E67: =IF(PRESUPUESTO!G81="",0,PRESUPUESTO!G81) | F67: 46416 | G67: 46540 | H67: =IF(OR(F67="",G67=""),"",G67-F67+1) | I67: 0 | J67: Planeado
A68: =IF(PRESUPUESTO!A82="","",PRESUPUESTO!A82) | B68: =PRESUPUESTO!A48 | C68: =PRESUPUESTO!A80 | D68: =IF(PRESUPUESTO!B82="","",PRESUPUESTO!B82) | E68: =IF(PRESUPUESTO!G82="",0,PRESUPUESTO!G82) | F68: 46419 | G68: 46545 | H68: =IF(OR(F68="",G68=""),"",G68-F68+1) | I68: 0 | J68: Planeado
A69: =IF(PRESUPUESTO!A83="","",PRESUPUESTO!A83) | B69: =PRESUPUESTO!A48 | C69: =PRESUPUESTO!A80 | D69: =IF(PRESUPUESTO!B83="","",PRESUPUESTO!B83) | E69: =IF(PRESUPUESTO!G83="",0,PRESUPUESTO!G83) | F69: 46422 | G69: 46550 | H69: =IF(OR(F69="",G69=""),"",G69-F69+1) | I69: 0 | J69: Planeado
A70: =IF(PRESUPUESTO!A84="","",PRESUPUESTO!A84) | B70: =PRESUPUESTO!A48 | C70: =PRESUPUESTO!A80 | D70: =IF(PRESUPUESTO!B84="","",PRESUPUESTO!B84) | E70: =IF(PRESUPUESTO!G84="",0,PRESUPUESTO!G84) | F70: 46425 | G70: 46555 | H70: =IF(OR(F70="",G70=""),"",G70-F70+1) | I70: 0 | J70: Planeado
A71: =IF(PRESUPUESTO!A85="","",PRESUPUESTO!A85) | B71: =PRESUPUESTO!A48 | C71: =PRESUPUESTO!A80 | D71: =IF(PRESUPUESTO!B85="","",PRESUPUESTO!B85) | E71: =IF(PRESUPUESTO!G85="",0,PRESUPUESTO!G85) | F71: 46428 | G71: 46560 | H71: =IF(OR(F71="",G71=""),"",G71-F71+1) | I71: 0 | J71: Planeado
A72: =IF(PRESUPUESTO!A86="","",PRESUPUESTO!A86) | B72: =PRESUPUESTO!A48 | C72: =PRESUPUESTO!A80 | D72: =IF(PRESUPUESTO!B86="","",PRESUPUESTO!B86) | E72: =IF(PRESUPUESTO!G86="",0,PRESUPUESTO!G86) | F72: 46431 | G72: 46565 | H72: =IF(OR(F72="",G72=""),"",G72-F72+1) | I72: 0 | J72: Planeado
A73: =IF(PRESUPUESTO!A87="","",PRESUPUESTO!A87) | B73: =PRESUPUESTO!A48 | C73: =PRESUPUESTO!A80 | D73: =IF(PRESUPUESTO!B87="","",PRESUPUESTO!B87) | E73: =IF(PRESUPUESTO!G87="",0,PRESUPUESTO!G87) | F73: 46434 | G73: 46570 | H73: =IF(OR(F73="",G73=""),"",G73-F73+1) | I73: 0 | J73: Planeado
A74: =IF(PRESUPUESTO!A88="","",PRESUPUESTO!A88) | B74: =PRESUPUESTO!A48 | C74: =PRESUPUESTO!A80 | D74: =IF(PRESUPUESTO!B88="","",PRESUPUESTO!B88) | E74: =IF(PRESUPUESTO!G88="",0,PRESUPUESTO!G88) | F74: 46437 | G74: 46575 | H74: =IF(OR(F74="",G74=""),"",G74-F74+1) | I74: 0 | J74: Planeado
A75: =IF(PRESUPUESTO!A89="","",PRESUPUESTO!A89) | B75: =PRESUPUESTO!A48 | C75: =PRESUPUESTO!A80 | D75: =IF(PRESUPUESTO!B89="","",PRESUPUESTO!B89) | E75: =IF(PRESUPUESTO!G89="",0,PRESUPUESTO!G89) | F75: 46440 | G75: 46580 | H75: =IF(OR(F75="",G75=""),"",G75-F75+1) | I75: 0 | J75: Planeado
A76: =IF(PRESUPUESTO!A90="","",PRESUPUESTO!A90) | B76: =PRESUPUESTO!A48 | C76: =PRESUPUESTO!A80 | D76: =IF(PRESUPUESTO!B90="","",PRESUPUESTO!B90) | E76: =IF(PRESUPUESTO!G90="",0,PRESUPUESTO!G90) | F76: 46443 | G76: 46585 | H76: =IF(OR(F76="",G76=""),"",G76-F76+1) | I76: 0 | J76: Planeado
A77: =IF(PRESUPUESTO!A91="","",PRESUPUESTO!A91) | B77: =PRESUPUESTO!A48 | C77: =PRESUPUESTO!A80 | D77: =IF(PRESUPUESTO!B91="","",PRESUPUESTO!B91) | E77: =IF(PRESUPUESTO!G91="",0,PRESUPUESTO!G91) | F77: 46446 | G77: 46590 | H77: =IF(OR(F77="",G77=""),"",G77-F77+1) | I77: 0 | J77: Planeado
A78: =IF(PRESUPUESTO!A92="","",PRESUPUESTO!A92) | B78: =PRESUPUESTO!A48 | C78: =PRESUPUESTO!A80 | D78: =IF(PRESUPUESTO!B92="","",PRESUPUESTO!B92) | E78: =IF(PRESUPUESTO!G92="",0,PRESUPUESTO!G92) | F78: 46449 | G78: 46595 | H78: =IF(OR(F78="",G78=""),"",G78-F78+1) | I78: 0 | J78: Planeado
A79: =IF(PRESUPUESTO!A93="","",PRESUPUESTO!A93) | B79: =PRESUPUESTO!A48 | C79: =PRESUPUESTO!A80 | D79: =IF(PRESUPUESTO!B93="","",PRESUPUESTO!B93) | E79: =IF(PRESUPUESTO!G93="",0,PRESUPUESTO!G93) | F79: 46452 | G79: 46600 | H79: =IF(OR(F79="",G79=""),"",G79-F79+1) | I79: 0 | J79: Planeado
A80: =IF(PRESUPUESTO!A94="","",PRESUPUESTO!A94) | B80: =PRESUPUESTO!A48 | C80: =PRESUPUESTO!A80 | D80: =IF(PRESUPUESTO!B94="","",PRESUPUESTO!B94) | E80: =IF(PRESUPUESTO!G94="",0,PRESUPUESTO!G94) | F80: 46455 | G80: 46605 | H80: =IF(OR(F80="",G80=""),"",G80-F80+1) | I80: 0 | J80: Planeado
A81: =IF(PRESUPUESTO!A95="","",PRESUPUESTO!A95) | B81: =PRESUPUESTO!A48 | C81: =PRESUPUESTO!A80 | D81: =IF(PRESUPUESTO!B95="","",PRESUPUESTO!B95) | E81: =IF(PRESUPUESTO!G95="",0,PRESUPUESTO!G95) | F81: 46458 | G81: 46610 | H81: =IF(OR(F81="",G81=""),"",G81-F81+1) | I81: 0 | J81: Planeado
A82: =IF(PRESUPUESTO!A96="","",PRESUPUESTO!A96) | B82: =PRESUPUESTO!A48 | C82: =PRESUPUESTO!A80 | D82: =IF(PRESUPUESTO!B96="","",PRESUPUESTO!B96) | E82: =IF(PRESUPUESTO!G96="",0,PRESUPUESTO!G96) | F82: 46461 | G82: 46615 | H82: =IF(OR(F82="",G82=""),"",G82-F82+1) | I82: 0 | J82: Planeado
A83: =IF(PRESUPUESTO!A97="","",PRESUPUESTO!A97) | B83: =PRESUPUESTO!A48 | C83: =PRESUPUESTO!A80 | D83: =IF(PRESUPUESTO!B97="","",PRESUPUESTO!B97) | E83: =IF(PRESUPUESTO!G97="",0,PRESUPUESTO!G97) | F83: 46464 | G83: 46620 | H83: =IF(OR(F83="",G83=""),"",G83-F83+1) | I83: 0 | J83: Planeado
A84: =IF(PRESUPUESTO!A98="","",PRESUPUESTO!A98) | B84: =PRESUPUESTO!A48 | C84: =PRESUPUESTO!A80 | D84: =IF(PRESUPUESTO!B98="","",PRESUPUESTO!B98) | E84: =IF(PRESUPUESTO!G98="",0,PRESUPUESTO!G98) | F84: 46467 | G84: 46625 | H84: =IF(OR(F84="",G84=""),"",G84-F84+1) | I84: 0 | J84: Planeado
A85: =IF(PRESUPUESTO!A99="","",PRESUPUESTO!A99) | B85: =PRESUPUESTO!A48 | C85: =PRESUPUESTO!A80 | D85: =IF(PRESUPUESTO!B99="","",PRESUPUESTO!B99) | E85: =IF(PRESUPUESTO!G99="",0,PRESUPUESTO!G99) | F85: 46470 | G85: 46630 | H85: =IF(OR(F85="",G85=""),"",G85-F85+1) | I85: 0 | J85: Planeado
A86: =IF(PRESUPUESTO!A101="","",PRESUPUESTO!A101) | B86: =PRESUPUESTO!A48 | C86: =PRESUPUESTO!A100 | D86: =IF(PRESUPUESTO!B101="","",PRESUPUESTO!B101) | E86: =IF(PRESUPUESTO!G101="",0,PRESUPUESTO!G101) | F86: 46473 | G86: 46635 | H86: =IF(OR(F86="",G86=""),"",G86-F86+1) | I86: 0 | J86: Planeado
A87: =IF(PRESUPUESTO!A103="","",PRESUPUESTO!A103) | B87: =PRESUPUESTO!A48 | C87: =PRESUPUESTO!A102 | D87: =IF(PRESUPUESTO!B103="","",PRESUPUESTO!B103) | E87: =IF(PRESUPUESTO!G103="",0,PRESUPUESTO!G103) | F87: 46476 | G87: 46640 | H87: =IF(OR(F87="",G87=""),"",G87-F87+1) | I87: 0 | J87: Planeado
A88: =IF(PRESUPUESTO!A104="","",PRESUPUESTO!A104) | B88: =PRESUPUESTO!A48 | C88: =PRESUPUESTO!A102 | D88: =IF(PRESUPUESTO!B104="","",PRESUPUESTO!B104) | E88: =IF(PRESUPUESTO!G104="",0,PRESUPUESTO!G104) | F88: 46479 | G88: 46645 | H88: =IF(OR(F88="",G88=""),"",G88-F88+1) | I88: 0 | J88: Planeado
A89: =IF(PRESUPUESTO!A105="","",PRESUPUESTO!A105) | B89: =PRESUPUESTO!A48 | C89: =PRESUPUESTO!A102 | D89: =IF(PRESUPUESTO!B105="","",PRESUPUESTO!B105) | E89: =IF(PRESUPUESTO!G105="",0,PRESUPUESTO!G105) | F89: 46482 | G89: 46650 | H89: =IF(OR(F89="",G89=""),"",G89-F89+1) | I89: 0 | J89: Planeado
A90: =IF(PRESUPUESTO!A106="","",PRESUPUESTO!A106) | B90: =PRESUPUESTO!A48 | C90: =PRESUPUESTO!A102 | D90: =IF(PRESUPUESTO!B106="","",PRESUPUESTO!B106) | E90: =IF(PRESUPUESTO!G106="",0,PRESUPUESTO!G106) | F90: 46485 | G90: 46655 | H90: =IF(OR(F90="",G90=""),"",G90-F90+1) | I90: 0 | J90: Planeado
A91: =IF(PRESUPUESTO!A107="","",PRESUPUESTO!A107) | B91: =PRESUPUESTO!A48 | C91: =PRESUPUESTO!A102 | D91: =IF(PRESUPUESTO!B107="","",PRESUPUESTO!B107) | E91: =IF(PRESUPUESTO!G107="",0,PRESUPUESTO!G107) | F91: 46488 | G91: 46660 | H91: =IF(OR(F91="",G91=""),"",G91-F91+1) | I91: 0 | J91: Planeado
A92: =IF(PRESUPUESTO!A108="","",PRESUPUESTO!A108) | B92: =PRESUPUESTO!A48 | C92: =PRESUPUESTO!A102 | D92: =IF(PRESUPUESTO!B108="","",PRESUPUESTO!B108) | E92: =IF(PRESUPUESTO!G108="",0,PRESUPUESTO!G108) | F92: 46491 | G92: 46665 | H92: =IF(OR(F92="",G92=""),"",G92-F92+1) | I92: 0 | J92: Planeado
A93: =IF(PRESUPUESTO!A109="","",PRESUPUESTO!A109) | B93: =PRESUPUESTO!A48 | C93: =PRESUPUESTO!A102 | D93: =IF(PRESUPUESTO!B109="","",PRESUPUESTO!B109) | E93: =IF(PRESUPUESTO!G109="",0,PRESUPUESTO!G109) | F93: 46494 | G93: 46670 | H93: =IF(OR(F93="",G93=""),"",G93-F93+1) | I93: 0 | J93: Planeado
A94: =IF(PRESUPUESTO!A110="","",PRESUPUESTO!A110) | B94: =PRESUPUESTO!A48 | C94: =PRESUPUESTO!A102 | D94: =IF(PRESUPUESTO!B110="","",PRESUPUESTO!B110) | E94: =IF(PRESUPUESTO!G110="",0,PRESUPUESTO!G110) | F94: 46497 | G94: 46675 | H94: =IF(OR(F94="",G94=""),"",G94-F94+1) | I94: 0 | J94: Planeado
A95: =IF(PRESUPUESTO!A111="","",PRESUPUESTO!A111) | B95: =PRESUPUESTO!A48 | C95: =PRESUPUESTO!A102 | D95: =IF(PRESUPUESTO!B111="","",PRESUPUESTO!B111) | E95: =IF(PRESUPUESTO!G111="",0,PRESUPUESTO!G111) | F95: 46500 | G95: 46680 | H95: =IF(OR(F95="",G95=""),"",G95-F95+1) | I95: 0 | J95: Planeado
A96: =IF(PRESUPUESTO!A112="","",PRESUPUESTO!A112) | B96: =PRESUPUESTO!A48 | C96: =PRESUPUESTO!A102 | D96: =IF(PRESUPUESTO!B112="","",PRESUPUESTO!B112) | E96: =IF(PRESUPUESTO!G112="",0,PRESUPUESTO!G112) | F96: 46503 | G96: 46685 | H96: =IF(OR(F96="",G96=""),"",G96-F96+1) | I96: 0 | J96: Planeado
A97: =IF(PRESUPUESTO!A113="","",PRESUPUESTO!A113) | B97: =PRESUPUESTO!A48 | C97: =PRESUPUESTO!A102 | D97: =IF(PRESUPUESTO!B113="","",PRESUPUESTO!B113) | E97: =IF(PRESUPUESTO!G113="",0,PRESUPUESTO!G113) | F97: 46506 | G97: 46690 | H97: =IF(OR(F97="",G97=""),"",G97-F97+1) | I97: 0 | J97: Planeado
A98: =IF(PRESUPUESTO!A115="","",PRESUPUESTO!A115) | B98: =PRESUPUESTO!A48 | C98: =PRESUPUESTO!A114 | D98: =IF(PRESUPUESTO!B115="","",PRESUPUESTO!B115) | E98: =IF(PRESUPUESTO!G115="",0,PRESUPUESTO!G115) | F98: 46509 | G98: 46695 | H98: =IF(OR(F98="",G98=""),"",G98-F98+1) | I98: 0 | J98: Planeado
A99: =IF(PRESUPUESTO!A116="","",PRESUPUESTO!A116) | B99: =PRESUPUESTO!A48 | C99: =PRESUPUESTO!A114 | D99: =IF(PRESUPUESTO!B116="","",PRESUPUESTO!B116) | E99: =IF(PRESUPUESTO!G116="",0,PRESUPUESTO!G116) | F99: 46512 | G99: 46700 | H99: =IF(OR(F99="",G99=""),"",G99-F99+1) | I99: 0 | J99: Planeado
A100: =IF(PRESUPUESTO!A117="","",PRESUPUESTO!A117) | B100: =PRESUPUESTO!A48 | C100: =PRESUPUESTO!A114 | D100: =IF(PRESUPUESTO!B117="","",PRESUPUESTO!B117) | E100: =IF(PRESUPUESTO!G117="",0,PRESUPUESTO!G117) | F100: 46515 | G100: 46705 | H100: =IF(OR(F100="",G100=""),"",G100-F100+1) | I100: 0 | J100: Planeado
A101: =IF(PRESUPUESTO!A118="","",PRESUPUESTO!A118) | B101: =PRESUPUESTO!A48 | C101: =PRESUPUESTO!A114 | D101: =IF(PRESUPUESTO!B118="","",PRESUPUESTO!B118) | E101: =IF(PRESUPUESTO!G118="",0,PRESUPUESTO!G118) | F101: 46518 | G101: 46710 | H101: =IF(OR(F101="",G101=""),"",G101-F101+1) | I101: 0 | J101: Planeado
...

Sheet FLUJO SEMANAL
A1: FLUJO SEMANAL · FLUJOGRAMA DE OBRA
A2: PROYECTO | C2: =CARATULA!$C$10
A3: CLIENTE | C3: =CARATULA!$C$12
A4: UBICACIÓN | C4: =CARATULA!$C$14
A5: EMPRESA | C5: =CARATULA!$C$19
A6: FOLIO | B6: ='NORMA BIM'!$H$18
A7: El importe de cada concepto se reparte por días entre las semanas que ocupa en el CRONOGRAMA.
D9: ="SEM "&1 | E9: ="SEM "&2 | F9: ="SEM "&3 | G9: ="SEM "&4 | H9: ="SEM "&5 | I9: ="SEM "&6 | J9: ="SEM "&7 | K9: ="SEM "&8 | L9: ="SEM "&9 | M9: ="SEM "&10 | N9: ="SEM "&11 | O9: ="SEM "&12 | P9: ="SEM "&13 | Q9: ="SEM "&14 | R9: ="SEM "&15 | S9: ="SEM "&16 | T9: ="SEM "&17 | U9: ="SEM "&18 | V9: ="SEM "&19 | W9: ="SEM "&20 | X9: ="SEM "&21 | Y9: ="SEM "&22 | Z9: ="SEM "&23 | AA9: ="SEM "&24 | AB9: ="SEM "&25 | AC9: ="SEM "&26 | AD9: ="SEM "&27
A10: CLAVE | B10: DESCRIPCIÓN DEL CONCEPTO | C10: IMPORTE | D10: =CARATULA!$C$27+0 | E10: =CARATULA!$C$27+7 | F10: =CARATULA!$C$27+14 | G10: =CARATULA!$C$27+21 | H10: =CARATULA!$C$27+28 | I10: =CARATULA!$C$27+35 | J10: =CARATULA!$C$27+42 | K10: =CARATULA!$C$27+49 | L10: =CARATULA!$C$27+56 | M10: =CARATULA!$C$27+63 | N10: =CARATULA!$C$27+70 | O10: =CARATULA!$C$27+77 | P10: =CARATULA!$C$27+84 | Q10: =CARATULA!$C$27+91 | R10: =CARATULA!$C$27+98 | S10: =CARATULA!$C$27+105 | T10: =CARATULA!$C$27+112 | U10: =CARATULA!$C$27+119 | V10: =CARATULA!$C$27+126 | W10: =CARATULA!$C$27+133 | X10: =CARATULA!$C$27+140 | Y10: =CARATULA!$C$27+147 | Z10: =CARATULA!$C$27+154 | AA10: =CARATULA!$C$27+161 | AB10: =CARATULA!$C$27+168 | AC10: =CARATULA!$C$27+175 | AD10: =CARATULA!$C$27+182
A11: =CRONOGRAMA!A12 | B11: =CRONOGRAMA!D12 | C11: =CRONOGRAMA!E12 | D11: =IF(OR(CRONOGRAMA!$F12="",CRONOGRAMA!$G12=""),0,IF(AND(D$10>=CRONOGRAMA!$F12-6,D$10<=CRONOGRAMA!$G12),$C11/MAX(1,ROUNDUP((CRONOGRAMA!$G12-CRONOGRAMA!$F12+1)/7,0)),0)) | E11: =IF(OR(CRONOGRAMA!$F12="",CRONOGRAMA!$G12=""),0,IF(AND(E$10>=CRONOGRAMA!$F12-6,E$10<=CRONOGRAMA!$G12),$C11/MAX(1,ROUNDUP((CRONOGRAMA!$G12-CRONOGRAMA!$F12+1)/7,0)),0)) | F11: =IF(OR(CRONOGRAMA!$F12="",CRONOGRAMA!$G12=""),0,IF(AND(F$10>=CRONOGRAMA!$F12-6,F$10<=CRONOGRAMA!$G12),$C11/MAX(1,ROUNDUP((CRONOGRAMA!$G12-CRONOGRAMA!$F12+1)/7,0)),0)) | G11: =IF(OR(CRONOGRAMA!$F12="",CRONOGRAMA!$G12=""),0,IF(AND(G$10>=CRONOGRAMA!$F12-6,G$10<=CRONOGRAMA!$G12),$C11/MAX(1,ROUNDUP((CRONOGRAMA!$G12-CRONOGRAMA!$F12+1)/7,0)),0)) | H11: =IF(OR(CRONOGRAMA!$F12="",CRONOGRAMA!$G12=""),0,IF(AND(H$10>=CRONOGRAMA!$F12-6,H$10<=CRONOGRAMA!$G12),$C11/MAX(1,ROUNDUP((CRONOGRAMA!$G12-CRONOGRAMA!$F12+1)/7,0)),0)) | I11: =IF(OR(CRONOGRAMA!$F12="",CRONOGRAMA!$G12=""),0,IF(AND(I$10>=CRONOGRAMA!$F12-6,I$10<=CRONOGRAMA!$G12),$C11/MAX(1,ROUNDUP((CRONOGRAMA!$G12-CRONOGRAMA!$F12+1)/7,0)),0)) | J11: =IF(OR(CRONOGRAMA!$F12="",CRONOGRAMA!$G12=""),0,IF(AND(J$10>=CRONOGRAMA!$F12-6,J$10<=CRONOGRAMA!$G12),$C11/MAX(1,ROUNDUP((CRONOGRAMA!$G12-CRONOGRAMA!$F12+1)/7,0)),0)) | K11: =IF(OR(CRONOGRAMA!$F12="",CRONOGRAMA!$G12=""),0,IF(AND(K$10>=CRONOGRAMA!$F12-6,K$10<=CRONOGRAMA!$G12),$C11/MAX(1,ROUNDUP((CRONOGRAMA!$G12-CRONOGRAMA!$F12+1)/7,0)),0)) | ... AD11: =IF(OR(CRONOGRAMA!$F12="",CRONOGRAMA!$G12=""),0,IF(AND(AD$10>=CRONOGRAMA!$F12-6,AD$10<=CRONOGRAMA!$G12),$C11/MAX(1,ROUNDUP((CRONOGRAMA!$G12-CRONOGRAMA!$F12+1)/7,0)),0))
A12: =CRONOGRAMA!A13 | B12: =CRONOGRAMA!D13 | C12: =CRONOGRAMA!E13 | D12: =IF(OR(CRONOGRAMA!$F13="",CRONOGRAMA!$G13=""),0,IF(AND(D$10>=CRONOGRAMA!$F13-6,D$10<=CRONOGRAMA!$G13),$C12/MAX(1,ROUNDUP((CRONOGRAMA!$G13-CRONOGRAMA!$F13+1)/7,0)),0)) | E12: =IF(OR(CRONOGRAMA!$F13="",CRONOGRAMA!$G13=""),0,IF(AND(E$10>=CRONOGRAMA!$F13-6,E$10<=CRONOGRAMA!$G13),$C12/MAX(1,ROUNDUP((CRONOGRAMA!$G13-CRONOGRAMA!$F13+1)/7,0)),0)) | F12: =IF(OR(CRONOGRAMA!$F13="",CRONOGRAMA!$G13=""),0,IF(AND(F$10>=CRONOGRAMA!$F13-6,F$10<=CRONOGRAMA!$G13),$C12/MAX(1,ROUNDUP((CRONOGRAMA!$G13-CRONOGRAMA!$F13+1)/7,0)),0)) | G12: =IF(OR(CRONOGRAMA!$F13="",CRONOGRAMA!$G13=""),0,IF(AND(G$10>=CRONOGRAMA!$F13-6,G$10<=CRONOGRAMA!$G13),$C12/MAX(1,ROUNDUP((CRONOGRAMA!$G13-CRONOGRAMA!$F13+1)/7,0)),0)) | H12: =IF(OR(CRONOGRAMA!$F13="",CRONOGRAMA!$G13=""),0,IF(AND(H$10>=CRONOGRAMA!$F13-6,H$10<=CRONOGRAMA!$G13),$C12/MAX(1,ROUNDUP((CRONOGRAMA!$G13-CRONOGRAMA!$F13+1)/7,0)),0)) | I12: =IF(OR(CRONOGRAMA!$F13="",CRONOGRAMA!$G13=""),0,IF(AND(I$10>=CRONOGRAMA!$F13-6,I$10<=CRONOGRAMA!$G13),$C12/MAX(1,ROUNDUP((CRONOGRAMA!$G13-CRONOGRAMA!$F13+1)/7,0)),0)) | J12: =IF(OR(CRONOGRAMA!$F13="",CRONOGRAMA!$G13=""),0,IF(AND(J$10>=CRONOGRAMA!$F13-6,J$10<=CRONOGRAMA!$G13),$C12/MAX(1,ROUNDUP((CRONOGRAMA!$G13-CRONOGRAMA!$F13+1)/7,0)),0)) | K12: =IF(OR(CRONOGRAMA!$F13="",CRONOGRAMA!$G13=""),0,IF(AND(K$10>=CRONOGRAMA!$F13-6,K$10<=CRONOGRAMA!$G13),$C12/MAX(1,ROUNDUP((CRONOGRAMA!$G13-CRONOGRAMA!$F13+1)/7,0)),0)) | ... AD12: =IF(OR(CRONOGRAMA!$F13="",CRONOGRAMA!$G13=""),0,IF(AND(AD$10>=CRONOGRAMA!$F13-6,AD$10<=CRONOGRAMA!$G13),$C12/MAX(1,ROUNDUP((CRONOGRAMA!$G13-CRONOGRAMA!$F13+1)/7,0)),0))
A13: =CRONOGRAMA!A14 | B13: =CRONOGRAMA!D14 | C13: =CRONOGRAMA!E14 | D13: =IF(OR(CRONOGRAMA!$F14="",CRONOGRAMA!$G14=""),0,IF(AND(D$10>=CRONOGRAMA!$F14-6,D$10<=CRONOGRAMA!$G14),$C13/MAX(1,ROUNDUP((CRONOGRAMA!$G14-CRONOGRAMA!$F14+1)/7,0)),0)) | E13: =IF(OR(CRONOGRAMA!$F14="",CRONOGRAMA!$G14=""),0,IF(AND(E$10>=CRONOGRAMA!$F14-6,E$10<=CRONOGRAMA!$G14),$C13/MAX(1,ROUNDUP((CRONOGRAMA!$G14-CRONOGRAMA!$F14+1)/7,0)),0)) | F13: =IF(OR(CRONOGRAMA!$F14="",CRONOGRAMA!$G14=""),0,IF(AND(F$10>=CRONOGRAMA!$F14-6,F$10<=CRONOGRAMA!$G14),$C13/MAX(1,ROUNDUP((CRONOGRAMA!$G14-CRONOGRAMA!$F14+1)/7,0)),0)) | G13: =IF(OR(CRONOGRAMA!$F14="",CRONOGRAMA!$G14=""),0,IF(AND(G$10>=CRONOGRAMA!$F14-6,G$10<=CRONOGRAMA!$G14),$C13/MAX(1,ROUNDUP((CRONOGRAMA!$G14-CRONOGRAMA!$F14+1)/7,0)),0)) | H13: =IF(OR(CRONOGRAMA!$F14="",CRONOGRAMA!$G14=""),0,IF(AND(H$10>=CRONOGRAMA!$F14-6,H$10<=CRONOGRAMA!$G14),$C13/MAX(1,ROUNDUP((CRONOGRAMA!$G14-CRONOGRAMA!$F14+1)/7,0)),0)) | I13: =IF(OR(CRONOGRAMA!$F14="",CRONOGRAMA!$G14=""),0,IF(AND(I$10>=CRONOGRAMA!$F14-6,I$10<=CRONOGRAMA!$G14),$C13/MAX(1,ROUNDUP((CRONOGRAMA!$G14-CRONOGRAMA!$F14+1)/7,0)),0)) | J13: =IF(OR(CRONOGRAMA!$F14="",CRONOGRAMA!$G14=""),0,IF(AND(J$10>=CRONOGRAMA!$F14-6,J$10<=CRONOGRAMA!$G14),$C13/MAX(1,ROUNDUP((CRONOGRAMA!$G14-CRONOGRAMA!$F14+1)/7,0)),0)) | K13: =IF(OR(CRONOGRAMA!$F14="",CRONOGRAMA!$G14=""),0,IF(AND(K$10>=CRONOGRAMA!$F14-6,K$10<=CRONOGRAMA!$G14),$C13/MAX(1,ROUNDUP((CRONOGRAMA!$G14-CRONOGRAMA!$F14+1)/7,0)),0)) | ... AD13: =IF(OR(CRONOGRAMA!$F14="",CRONOGRAMA!$G14=""),0,IF(AND(AD$10>=CRONOGRAMA!$F14-6,AD$10<=CRONOGRAMA!$G14),$C13/MAX(1,ROUNDUP((CRONOGRAMA!$G14-CRONOGRAMA!$F14+1)/7,0)),0))
A14: =CRONOGRAMA!A15 | B14: =CRONOGRAMA!D15 | C14: =CRONOGRAMA!E15 | D14: =IF(OR(CRONOGRAMA!$F15="",CRONOGRAMA!$G15=""),0,IF(AND(D$10>=CRONOGRAMA!$F15-6,D$10<=CRONOGRAMA!$G15),$C14/MAX(1,ROUNDUP((CRONOGRAMA!$G15-CRONOGRAMA!$F15+1)/7,0)),0)) | E14: =IF(OR(CRONOGRAMA!$F15="",CRONOGRAMA!$G15=""),0,IF(AND(E$10>=CRONOGRAMA!$F15-6,E$10<=CRONOGRAMA!$G15),$C14/MAX(1,ROUNDUP((CRONOGRAMA!$G15-CRONOGRAMA!$F15+1)/7,0)),0)) | F14: =IF(OR(CRONOGRAMA!$F15="",CRONOGRAMA!$G15=""),0,IF(AND(F$10>=CRONOGRAMA!$F15-6,F$10<=CRONOGRAMA!$G15),$C14/MAX(1,ROUNDUP((CRONOGRAMA!$G15-CRONOGRAMA!$F15+1)/7,0)),0)) | G14: =IF(OR(CRONOGRAMA!$F15="",CRONOGRAMA!$G15=""),0,IF(AND(G$10>=CRONOGRAMA!$F15-6,G$10<=CRONOGRAMA!$G15),$C14/MAX(1,ROUNDUP((CRONOGRAMA!$G15-CRONOGRAMA!$F15+1)/7,0)),0)) | H14: =IF(OR(CRONOGRAMA!$F15="",CRONOGRAMA!$G15=""),0,IF(AND(H$10>=CRONOGRAMA!$F15-6,H$10<=CRONOGRAMA!$G15),$C14/MAX(1,ROUNDUP((CRONOGRAMA!$G15-CRONOGRAMA!$F15+1)/7,0)),0)) | I14: =IF(OR(CRONOGRAMA!$F15="",CRONOGRAMA!$G15=""),0,IF(AND(I$10>=CRONOGRAMA!$F15-6,I$10<=CRONOGRAMA!$G15),$C14/MAX(1,ROUNDUP((CRONOGRAMA!$G15-CRONOGRAMA!$F15+1)/7,0)),0)) | J14: =IF(OR(CRONOGRAMA!$F15="",CRONOGRAMA!$G15=""),0,IF(AND(J$10>=CRONOGRAMA!$F15-6,J$10<=CRONOGRAMA!$G15),$C14/MAX(1,ROUNDUP((CRONOGRAMA!$G15-CRONOGRAMA!$F15+1)/7,0)),0)) | K14: =IF(OR(CRONOGRAMA!$F15="",CRONOGRAMA!$G15=""),0,IF(AND(K$10>=CRONOGRAMA!$F15-6,K$10<=CRONOGRAMA!$G15),$C14/MAX(1,ROUNDUP((CRONOGRAMA!$G15-CRONOGRAMA!$F15+1)/7,0)),0)) | ... AD14: =IF(OR(CRONOGRAMA!$F15="",CRONOGRAMA!$G15=""),0,IF(AND(AD$10>=CRONOGRAMA!$F15-6,AD$10<=CRONOGRAMA!$G15),$C14/MAX(1,ROUNDUP((CRONOGRAMA!$G15-CRONOGRAMA!$F15+1)/7,0)),0))
A15: =CRONOGRAMA!A16 | B15: =CRONOGRAMA!D16 | C15: =CRONOGRAMA!E16 | D15: =IF(OR(CRONOGRAMA!$F16="",CRONOGRAMA!$G16=""),0,IF(AND(D$10>=CRONOGRAMA!$F16-6,D$10<=CRONOGRAMA!$G16),$C15/MAX(1,ROUNDUP((CRONOGRAMA!$G16-CRONOGRAMA!$F16+1)/7,0)),0)) | E15: =IF(OR(CRONOGRAMA!$F16="",CRONOGRAMA!$G16=""),0,IF(AND(E$10>=CRONOGRAMA!$F16-6,E$10<=CRONOGRAMA!$G16),$C15/MAX(1,ROUNDUP((CRONOGRAMA!$G16-CRONOGRAMA!$F16+1)/7,0)),0)) | F15: =IF(OR(CRONOGRAMA!$F16="",CRONOGRAMA!$G16=""),0,IF(AND(F$10>=CRONOGRAMA!$F16-6,F$10<=CRONOGRAMA!$G16),$C15/MAX(1,ROUNDUP((CRONOGRAMA!$G16-CRONOGRAMA!$F16+1)/7,0)),0)) | G15: =IF(OR(CRONOGRAMA!$F16="",CRONOGRAMA!$G16=""),0,IF(AND(G$10>=CRONOGRAMA!$F16-6,G$10<=CRONOGRAMA!$G16),$C15/MAX(1,ROUNDUP((CRONOGRAMA!$G16-CRONOGRAMA!$F16+1)/7,0)),0)) | H15: =IF(OR(CRONOGRAMA!$F16="",CRONOGRAMA!$G16=""),0,IF(AND(H$10>=CRONOGRAMA!$F16-6,H$10<=CRONOGRAMA!$G16),$C15/MAX(1,ROUNDUP((CRONOGRAMA!$G16-CRONOGRAMA!$F16+1)/7,0)),0)) | I15: =IF(OR(CRONOGRAMA!$F16="",CRONOGRAMA!$G16=""),0,IF(AND(I$10>=CRONOGRAMA!$F16-6,I$10<=CRONOGRAMA!$G16),$C15/MAX(1,ROUNDUP((CRONOGRAMA!$G16-CRONOGRAMA!$F16+1)/7,0)),0)) | J15: =IF(OR(CRONOGRAMA!$F16="",CRONOGRAMA!$G16=""),0,IF(AND(J$10>=CRONOGRAMA!$F16-6,J$10<=CRONOGRAMA!$G16),$C15/MAX(1,ROUNDUP((CRONOGRAMA!$G16-CRONOGRAMA!$F16+1)/7,0)),0)) | K15: =IF(OR(CRONOGRAMA!$F16="",CRONOGRAMA!$G16=""),0,IF(AND(K$10>=CRONOGRAMA!$F16-6,K$10<=CRONOGRAMA!$G16),$C15/MAX(1,ROUNDUP((CRONOGRAMA!$G16-CRONOGRAMA!$F16+1)/7,0)),0)) | ... AD15: =IF(OR(CRONOGRAMA!$F16="",CRONOGRAMA!$G16=""),0,IF(AND(AD$10>=CRONOGRAMA!$F16-6,AD$10<=CRONOGRAMA!$G16),$C15/MAX(1,ROUNDUP((CRONOGRAMA!$G16-CRONOGRAMA!$F16+1)/7,0)),0))
A16: =CRONOGRAMA!A17 | B16: =CRONOGRAMA!D17 | C16: =CRONOGRAMA!E17 | D16: =IF(OR(CRONOGRAMA!$F17="",CRONOGRAMA!$G17=""),0,IF(AND(D$10>=CRONOGRAMA!$F17-6,D$10<=CRONOGRAMA!$G17),$C16/MAX(1,ROUNDUP((CRONOGRAMA!$G17-CRONOGRAMA!$F17+1)/7,0)),0)) | E16: =IF(OR(CRONOGRAMA!$F17="",CRONOGRAMA!$G17=""),0,IF(AND(E$10>=CRONOGRAMA!$F17-6,E$10<=CRONOGRAMA!$G17),$C16/MAX(1,ROUNDUP((CRONOGRAMA!$G17-CRONOGRAMA!$F17+1)/7,0)),0)) | F16: =IF(OR(CRONOGRAMA!$F17="",CRONOGRAMA!$G17=""),0,IF(AND(F$10>=CRONOGRAMA!$F17-6,F$10<=CRONOGRAMA!$G17),$C16/MAX(1,ROUNDUP((CRONOGRAMA!$G17-CRONOGRAMA!$F17+1)/7,0)),0)) | G16: =IF(OR(CRONOGRAMA!$F17="",CRONOGRAMA!$G17=""),0,IF(AND(G$10>=CRONOGRAMA!$F17-6,G$10<=CRONOGRAMA!$G17),$C16/MAX(1,ROUNDUP((CRONOGRAMA!$G17-CRONOGRAMA!$F17+1)/7,0)),0)) | H16: =IF(OR(CRONOGRAMA!$F17="",CRONOGRAMA!$G17=""),0,IF(AND(H$10>=CRONOGRAMA!$F17-6,H$10<=CRONOGRAMA!$G17),$C16/MAX(1,ROUNDUP((CRONOGRAMA!$G17-CRONOGRAMA!$F17+1)/7,0)),0)) | I16: =IF(OR(CRONOGRAMA!$F17="",CRONOGRAMA!$G17=""),0,IF(AND(I$10>=CRONOGRAMA!$F17-6,I$10<=CRONOGRAMA!$G17),$C16/MAX(1,ROUNDUP((CRONOGRAMA!$G17-CRONOGRAMA!$F17+1)/7,0)),0)) | J16: =IF(OR(CRONOGRAMA!$F17="",CRONOGRAMA!$G17=""),0,IF(AND(J$10>=CRONOGRAMA!$F17-6,J$10<=CRONOGRAMA!$G17),$C16/MAX(1,ROUNDUP((CRONOGRAMA!$G17-CRONOGRAMA!$F17+1)/7,0)),0)) | K16: =IF(OR(CRONOGRAMA!$F17="",CRONOGRAMA!$G17=""),0,IF(AND(K$10>=CRONOGRAMA!$F17-6,K$10<=CRONOGRAMA!$G17),$C16/MAX(1,ROUNDUP((CRONOGRAMA!$G17-CRONOGRAMA!$F17+1)/7,0)),0)) | ... AD16: =IF(OR(CRONOGRAMA!$F17="",CRONOGRAMA!$G17=""),0,IF(AND(AD$10>=CRONOGRAMA!$F17-6,AD$10<=CRONOGRAMA!$G17),$C16/MAX(1,ROUNDUP((CRONOGRAMA!$G17-CRONOGRAMA!$F17+1)/7,0)),0))
A17: =CRONOGRAMA!A18 | B17: =CRONOGRAMA!D18 | C17: =CRONOGRAMA!E18 | D17: =IF(OR(CRONOGRAMA!$F18="",CRONOGRAMA!$G18=""),0,IF(AND(D$10>=CRONOGRAMA!$F18-6,D$10<=CRONOGRAMA!$G18),$C17/MAX(1,ROUNDUP((CRONOGRAMA!$G18-CRONOGRAMA!$F18+1)/7,0)),0)) | E17: =IF(OR(CRONOGRAMA!$F18="",CRONOGRAMA!$G18=""),0,IF(AND(E$10>=CRONOGRAMA!$F18-6,E$10<=CRONOGRAMA!$G18),$C17/MAX(1,ROUNDUP((CRONOGRAMA!$G18-CRONOGRAMA!$F18+1)/7,0)),0)) | F17: =IF(OR(CRONOGRAMA!$F18="",CRONOGRAMA!$G18=""),0,IF(AND(F$10>=CRONOGRAMA!$F18-6,F$10<=CRONOGRAMA!$G18),$C17/MAX(1,ROUNDUP((CRONOGRAMA!$G18-CRONOGRAMA!$F18+1)/7,0)),0)) | G17: =IF(OR(CRONOGRAMA!$F18="",CRONOGRAMA!$G18=""),0,IF(AND(G$10>=CRONOGRAMA!$F18-6,G$10<=CRONOGRAMA!$G18),$C17/MAX(1,ROUNDUP((CRONOGRAMA!$G18-CRONOGRAMA!$F18+1)/7,0)),0)) | H17: =IF(OR(CRONOGRAMA!$F18="",CRONOGRAMA!$G18=""),0,IF(AND(H$10>=CRONOGRAMA!$F18-6,H$10<=CRONOGRAMA!$G18),$C17/MAX(1,ROUNDUP((CRONOGRAMA!$G18-CRONOGRAMA!$F18+1)/7,0)),0)) | I17: =IF(OR(CRONOGRAMA!$F18="",CRONOGRAMA!$G18=""),0,IF(AND(I$10>=CRONOGRAMA!$F18-6,I$10<=CRONOGRAMA!$G18),$C17/MAX(1,ROUNDUP((CRONOGRAMA!$G18-CRONOGRAMA!$F18+1)/7,0)),0)) | J17: =IF(OR(CRONOGRAMA!$F18="",CRONOGRAMA!$G18=""),0,IF(AND(J$10>=CRONOGRAMA!$F18-6,J$10<=CRONOGRAMA!$G18),$C17/MAX(1,ROUNDUP((CRONOGRAMA!$G18-CRONOGRAMA!$F18+1)/7,0)),0)) | K17: =IF(OR(CRONOGRAMA!$F18="",CRONOGRAMA!$G18=""),0,IF(AND(K$10>=CRONOGRAMA!$F18-6,K$10<=CRONOGRAMA!$G18),$C17/MAX(1,ROUNDUP((CRONOGRAMA!$G18-CRONOGRAMA!$F18+1)/7,0)),0)) | ... AD17: =IF(OR(CRONOGRAMA!$F18="",CRONOGRAMA!$G18=""),0,IF(AND(AD$10>=CRONOGRAMA!$F18-6,AD$10<=CRONOGRAMA!$G18),$C17/MAX(1,ROUNDUP((CRONOGRAMA!$G18-CRONOGRAMA!$F18+1)/7,0)),0))
